Workbook

Sheet Index
B2: # | C2: Steps | D2: POC | E2: Links | F2: Day (t)
B3: 1 | C3: Input Stress levels and respective time horizons | D3: All | E3: Link | F3: 0
B4: =B3+1 -> 2 | C4: Input Disbursals (Stressed) | D4: Business | E4: Link | F4: 2
B5: =B4+1 -> 3 | C5: Input ENR (Stressed - pre writeoff) | D5: Finance | E5: Link | F5: 4 | G5: CoF assumption - Treasury
B6: =B5+1 -> 4 | C6: Input ANR (Stressed - pre writeoff) | D6: Finance | E6: Link | F6: 4
B7: =B6+1 -> 5 | C7: Input CoC (Plan) | D7: AIM | E7: Link | F7: 6 | G7: Credit Stress
B8: =B7+1 -> 6 | C8: Update NCL (Stressed Disbursal impact) | D8: AIM | E8: Link | F8: 6
B9: =B8+1 -> 7 | C9: Input PDLGD (Plan) | D9: AIM | E9: Link | F9: 6
B10: =B9+1 -> 8 | C10: Update Stress Parameters | D10: AIM | E10: Link | F10: 6
B11: =B10+1 -> 9 | C11: Update NCL and ECL | D11: AIM | E11: Link | F11: 6
B12: =B11+1 -> 10 | C12: Update Stage Distribution | D12: AIM | E12: Link | F12: 6
B13: =B12+1 -> 11 | C13: Update ENR (Stressed - post writeoff) | D13: Finance | E13: Link | F13: 8
B14: =B13+1 -> 12 | C14: Update ANR (Stressed - post writeoff) | D14: Finance | E14: Link | F14: 8
B15: =B14+1 -> 13 | C15: Input Financials for Stressed scenario (with Stress inputs on margin, expense, CoF) | D15: Finance/Treasury | E15: Link | F15: 10
B16: =B15+1 -> 14 | C16: Output Summary | D16: Finance | E16: Link | F16: 11
B17: =B16+1 -> 15 | C17: Stress test deck | D17: AIM | F17: 12

Sheet Assumptions
C3: Assumptions
C5: Base Scenario | D5: The base scenario is considered as revised ABP plan for FY25-FY27
C7: Stress Scenario | D7: The stress scenario is considered for the period of 30 months with split in 3 levels.
D9: Stress Level | E9: Definition | F9: Stress Period | G9: Disbursal
G10: HL + LAP | H10: DF
D11: SL1: Slowdown | E11: 1 in 7 years | F11: 6 months (Apr’24 to Sep’24) | G11: @60% of Base scenario | H11: @40% of Base scenario
D12: SL2: Recession | E12: 1 in 25 years | F12: 12 months (Oct’24 to Sep'25) | G12: @40% of Base scenario | H12: @20% of Base scenario
D13: SL3: Recovery | E13: 1 in 10 years | F13: 12 months (Oct’25 to Sep’26) | G13: @60% of Base scenario | H13: @40% of Base scenario
D14: BAU | F14: 6 months (Oct’26 to Mar’27) | G14: @100% of Base scenario | H14: @100% of Base scenario
C17: Stress Methodology | D17: Parameter | E17: Stress Methodology
D18: PD | E18: Base-line PD is stressed through Vasicek equation to get stressed PD across stress levels
D19: LGD | E19: Compute the downturn LGD as against Base-line LGD basis till inception trend
D20: NCL | E20: Compute stressed NCL by using Vasicek formula across 3 levels of stress
D21: ECL (PnL) | E21: 1- Stage distribution is worsened basis the historical stage distribution observed after covid wave 1 , some improvement is considered factoring better sourcing quality post covid
E22: 2- ECL rate for Stage-1 is worsened by extent of worsening of stage 2
E23: 3- Plan overlay is kept same as base period
E24: 4- Additional overlay has been built on ONAN pool to get the PCR of ONAN pool equal to stage 3 ECL rates
E25: 5- Actual ECL BS is computed on stressed ENR
D26: NPA | E26: 1 - 90 + GNPA is computed using worsened stage distribution
E27: 2- ONAN GNPA is computed using Non ONAN to ONAN pool ratio in stage2 of base scenario
E28: 3- Model PCR for 90+ GNPA and ONAN GNPA is same as base scenario
E29: 4- Additional overlay has been built on ONAN pool maintain stage 3 model PCR

Sheet Summary-S
E2: ABP | I2: Stress Scenario | M2: FY19-FY23 | Z2: ABP (revised) plan | AD2: Stress Scenario (Revised)
E3: FY25 | F3: FY26 | G3: FY27 | I3: FY25 | J3: FY26 | K3: FY27 | M3: FY19 | N3: FY20 | O3: FY21 | P3: FY22 | Q3: FY23 | Z3: FY24 | AA3: FY25 | AB3: FY26 | AD3: FY24 | AE3: FY25 | AF3: FY26
D4: GWO | E4: =Summary!E4 -> 548.34973 | F4: =Summary!F4 -> 645.75647 | G4: =Summary!G4 -> 790.29476 | I4: =Summary!I4 -> 548.34973 | J4: =Summary!J4 -> 764.78404 | K4: =Summary!K4 -> 929.38938 | M4: 393.85129 | N4: 442.05321 | O4: 904.60849 | P4: 457.59212 | Q4: 1797.0578 | Z4: 531.41761 | AA4: 1005.6938 | AB4: 776.19789 | AD4: 531.41761 | AE4: 1165.4088 | AF4: 894.97604
D5: Recovery | E5: =Summary!E5 -> 94.402361 | F5: =Summary!F5 -> 121.03769 | G5: =Summary!G5 -> 138.43137 | I5: =Summary!I5 -> 90.907807 | J5: =Summary!J5 -> 115.33068 | K5: =Summary!K5 -> 135.62991 | M5: 237.7953 | N5: 158.96618 | O5: 160.16087 | P5: 121.69172 | Q5: 667.84907 | Z5: 97.440846 | AA5: 169.04768 | AB5: 166.23342 | AD5: 91.496518 | AE5: 155.32698 | AF5: 159.39922
D6: NCL | E6: =Summary!E6 -> 453.94737 | F6: =Summary!F6 -> 524.71878 | G6: =Summary!G6 -> 651.8634 | I6: =Summary!I6 -> 457.44192 | J6: =Summary!J6 -> 649.45336 | K6: =Summary!K6 -> 793.75947 | M6: =M4-M5 -> 156.05599 | N6: =N4-N5 -> 283.08703 | O6: =O4-O5 -> 744.44762 | P6: =P4-P5 -> 335.9004 | Q6: =Q4-Q5 -> 1129.2087 | Z6: 433.97676 | AA6: 836.64616 | AB6: 609.96447 | AD6: 439.92109 | AE6: 1010.0819 | AF6: 735.57682
D7: ECL Pnl | E7: =Summary!E9 -> 170.67294 | F7: =Summary!F9 -> 279.45746 | G7: =Summary!G9 -> 344.84454 | I7: =Summary!I9 -> 596.03728 | J7: =Summary!J9 -> 125.20797 | K7: =Summary!K9 -> 121.59493 | M7: =SUM(#REF!) -> #REF! | N7: =SUM(#REF!) -> #REF! | O7: =SUM(#REF!) -> #REF! | P7: =SUM(#REF!) -> #REF! | Q7: =SUM(#REF!) -> #REF! | Z7: 192.31741 | AA7: 74.168555 | AB7: 431.20279 | AD7: 568.2236 | AE7: 105.61727 | AF7: 136.05036
D8: COC | E8: =Summary!E10 -> 624.6203 | F8: =Summary!F10 -> 804.17624 | G8: =Summary!G10 -> 996.70794 | I8: =Summary!I10 -> 1053.4792 | J8: =Summary!J10 -> 774.66133 | K8: =Summary!K10 -> 915.35441 | M8: =M4-M5+#REF!+#REF! -> #REF! | N8: =N4-N5+#REF!+#REF! -> #REF! | O8: =O4-O5+#REF!+#REF! -> #REF! | P8: =P4-P5+#REF!+#REF! -> #REF! | Q8: =Q4-Q5+#REF!+#REF! -> #REF! | R8: 1280.2768 | S8: 1575.0411 | T8: 781.41958 | X8: =SUM(I8:K8)/SUM(E8:G8) -> 1.1311028 | Z8: 626.29417 | AA8: 910.81471 | AB8: 1041.1673 | AD8: 1008.1447 | AE8: 1115.6991 | AF8: 871.62718 | AH8: =SUM(AD8:AF8)/SUM(Z8:AB8) -> 1.1618116
D9: CoC % | E9: =Summary!E11 -> 0.0060022903 | F9: =Summary!F11 -> 0.005594111 | G9: =Summary!G11 -> 0.0053038379 | I9: =Summary!I11 -> 0.011197131 | J9: =Summary!J11 -> 0.0077192859 | K9: =Summary!K11 -> 0.0072623405 | M9: =M8/M10 -> #REF! | N9: =N8/N10 -> #REF! | O9: =O8/O10 -> #REF! | P9: =P8/P10 -> #REF! | Q9: =Q8/Q10 -> #REF! | R9: 0.018933056 | S9: 0.021166365 | T9: 0.0077730378 | Z9: 0.0082141274 | AA9: 0.0082016771 | AB9: 0.0068720397 | AD9: 0.014751193 | AE9: 0.014210265 | AF9: 0.0083728501
D10: ANR | E10: =Summary!E13 -> 104063.66 | F10: =Summary!F13 -> 143754.07 | G10: =Summary!G13 -> 187922.02 | I10: =Summary!I13 -> 94084.743 | J10: =Summary!J13 -> 100354.01 | K10: =Summary!K13 -> 126041.24 | M10: 30191.291 | N10: 39210.151 | O10: 42720.108 | P10: 42630.648 | Q10: 54946.128 | Z10: 76245.978 | AA10: 111052.25 | AB10: 151507.75 | AD10: 68343.266 | AE10: 78513.605 | AF10: 104101.61
D11: ENR | E11: =Summary!E14 -> 112136.8 | F11: =Summary!F14 -> 150480.17 | G11: =Summary!G14 -> 193146.81 | I11: =Summary!I14 -> 86930.596 | J11: =Summary!J14 -> 92702.224 | K11: =Summary!K14 -> 143181.26 | M11: 30645.169 | N11: 39398.285 | O11: 38275.721 | P11: 41260.274 | Q11: 59276.646 | Z11: 89826.036 | AA11: 125498.39 | AB11: 162285.83 | AD11: 65255.747 | AE11: 77975.775 | AF11: 121832.96
D12: ECL BS | E12: =Summary!E15 -> 1839.2751 | F12: =Summary!F15 -> 2118.7326 | G12: =Summary!G15 -> 2463.5771 | I12: =Summary!I15 -> 2264.6395 | J12: =Summary!J15 -> 2389.8474 | K12: =Summary!K15 -> 2511.4424 | M12: 468.565 | N12: =M12+#REF! -> #REF! | O12: =N12+#REF! -> #REF! | P12: =O12+#REF! -> #REF! | Q12: =P12+#REF! -> #REF! | Z12: 1801.2291 | AA12: 1875.3977 | AB12: 2306.6005 | AD12: 2177.1358 | AE12: 2282.7531 | AF12: 2418.8035
D13: ECL BS/ENR | E13: =Summary!E16 -> 0.016402065 | F13: =Summary!F16 -> 0.014079812 | G13: =Summary!G16 -> 0.012754946 | I13: =Summary!I16 -> 0.026051121 | J13: =Summary!J16 -> 0.025779828 | K13: =Summary!K16 -> 0.017540301 | M13: =M12/M11 -> 0.015290012 | N13: =N12/N11 -> #REF! | O13: =O12/O11 -> #REF! | P13: =P12/P11 -> #REF! | Q13: =Q12/Q11 -> #REF! | Z13: 0.020052417 | AA13: 0.014943599 | AB13: 0.014213197 | AD13: 0.033363128 | AE13: 0.029275158 | AF13: 0.019853442
D14: GNPA% | E14: =Summary!E20 -> 0.020403727 | F14: =Summary!F20 -> 0.01714911 | G14: =Summary!G20 -> 0.015114985 | I14: =Summary!I20 -> 0.035715322 | J14: =Summary!J20 -> 0.037408138 | K14: =Summary!K20 -> 0.023801644 | M14: 0.020678312 | N14: 0.036817477 | O14: 0.056028682 | P14: 0.062302654 | Q14: 0.037431908 | R14: 0.069741801 | S14: 0.092798823 | T14: 0.051739469 | U14: =I14/E14 -> 1.7504313 | V14: =J14/F14 -> 2.1813457 | W14: =K14/G14 -> 1.5747051 | Z14: 0.027027797 | AA14: 0.018645964 | AB14: 0.015389441 | AD14: 0.04668013 | AE14: 0.045474874 | AF14: 0.024471418
D15: NNPA% | E15: =Summary!E21 -> 0.01335173 | F15: =Summary!F21 -> 0.011471243 | G15: =Summary!G21 -> 0.010290472 | I15: =Summary!I21 -> 0.021573257 | J15: =Summary!J21 -> 0.02313496 | K15: =Summary!K21 -> 0.01487465 | M15: 0.012300268 | N15: 0.019536555 | O15: 0.028748404 | P15: 0.030408628 | Q15: 0.023407939 | R15: 0.046627375 | S15: 0.066861049 | T15: 0.037048977 | U15: =(#REF!-#REF!)+(#REF!*5%) -> #REF! | Z15: 0.017790838 | AA15: 0.013233197 | AB15: 0.010967345 | AD15: 0.02641212 | AE15: 0.028454543 | AF15: 0.015351205

Sheet Summary
E2: ABP | I2: Stress Scenario | M2: FY19-FY23 | Z2: ABP (revised) plan | AD2: Stress Scenario (Revised)
E3: FY25 | F3: FY26 | G3: FY27 | I3: FY25 | J3: FY26 | K3: FY27 | M3: FY19 | N3: FY20 | O3: FY21 | P3: FY22 | Q3: FY23 | Z3: FY24 | AA3: FY25 | AB3: FY26 | AD3: FY24 | AE3: FY25 | AF3: FY26
D4: GWO | E4: =SUM('Plan - CoC'!D4:O6) -> 548.34973 | F4: =SUM('Plan - CoC'!P4:AA6) -> 645.75647 | G4: =SUM('Plan - CoC'!AB4:AM6) -> 790.29476 | I4: ='MOM Summary'!BM3 -> 548.34973 | J4: ='MOM Summary'!BN3 -> 764.78404 | K4: ='MOM Summary'!BO3 -> 929.38938 | M4: 393.85129 | N4: 442.05321 | O4: 904.60849 | P4: 457.59212 | Q4: 1797.0578 | Z4: 531.41761 | AA4: 1005.6938 | AB4: 776.19789 | AD4: 531.41761 | AE4: 1165.4088 | AF4: 894.97604
D5: Recovery | E5: =SUM('Plan - CoC'!D10:O12) -> 94.402361 | F5: =SUM('Plan - CoC'!P10:AA12) -> 121.03769 | G5: =SUM('Plan - CoC'!AB10:AM12) -> 138.43137 | I5: ='MOM Summary'!BM9 -> 90.907807 | J5: ='MOM Summary'!BN9 -> 115.33068 | K5: ='MOM Summary'!BO9 -> 135.62991 | M5: 237.7953 | N5: 158.96618 | O5: 160.16087 | P5: 121.69172 | Q5: 667.84907 | Z5: 97.440846 | AA5: 169.04768 | AB5: 166.23342 | AD5: 91.496518 | AE5: 155.32698 | AF5: 159.39922
D6: NCL | E6: =SUM('Input - NCL'!D10:O10) -> 453.94737 | F6: =SUM('Input - NCL'!P10:AA10) -> 524.71878 | G6: =SUM('Input - NCL'!AB10:AM10) -> 651.8634 | I6: =I4-I5 -> 457.44192 | J6: =J4-J5 -> 649.45336 | K6: =K4-K5 -> 793.75947 | M6: =M4-M5 -> 156.05599 | N6: =N4-N5 -> 283.08703 | O6: =O4-O5 -> 744.44762 | P6: =P4-P5 -> 335.9004 | Q6: =Q4-Q5 -> 1129.2087 | Z6: 433.97676 | AA6: 836.64616 | AB6: 609.96447 | AD6: 439.92109 | AE6: 1010.0819 | AF6: 735.57682
D7: ECL Model | E7: =SUM('Calculation - NCL and ECL'!F19:Q21) -> 212.49193 | F7: =SUM('Calculation - NCL and ECL'!R19:AC21) -> 317.72917 | G7: =SUM('Calculation - NCL and ECL'!AD19:AO21) -> 393.58197 | I7: ='MOM Summary'!BM15 -> 468.63553 | J7: ='MOM Summary'!BN15 -> 153.07826 | K7: ='MOM Summary'!BO15 -> 150.69271 | M7: -253.35745 | N7: 567.72418 | O7: 1060.3683 | P7: 335.76411 | Q7: -812.78953 | Z7: 349.21297 | AA7: 180.89224 | AB7: 445.01657 | AD7: 519.27564 | AE7: 188.4991 | AF7: 177.0906
D8: Overlay | E8: =SUM('Calculation - NCL and ECL'!F37:Q39) -> -41.818993 | F8: =SUM('Calculation - NCL and ECL'!R37:AC39) -> -38.27171 | G8: =+SUM('Calculation - NCL and ECL'!AD37:AO39) -> -48.73743 | I8: ='MOM Summary'!BM21 -> 127.40175 | J8: ='MOM Summary'!BN21 -> -27.870289 | K8: ='MOM Summary'!BO21 -> -29.097773 | M8: 0 | N8: 0 | Z8: -156.89556 | AA8: -106.72369 | AB8: -13.813785 | AD8: 48.947962 | AE8: -82.881832 | AF8: -41.040235
D9: ECL Pnl | E9: =SUM(E7:E8) -> 170.67294 | F9: =SUM(F7:F8) -> 279.45746 | G9: =SUM(G7:G8) -> 344.84454 | I9: =SUM(I7:I8) -> 596.03728 | J9: =SUM(J7:J8) -> 125.20797 | K9: =SUM(K7:K8) -> 121.59493 | M9: =SUM(M7:M8) -> -253.35745 | N9: =SUM(N7:N8) -> 567.72418 | O9: =SUM(O7:O8) -> 1060.3683 | P9: =SUM(P7:P8) -> 335.76411 | Q9: =SUM(Q7:Q8) -> -812.78953 | Z9: 192.31741 | AA9: 74.168555 | AB9: 431.20279 | AD9: 568.2236 | AE9: 105.61727 | AF9: 136.05036
D10: COC (with overlay) | E10: =E4-E5+E7+E8 -> 624.6203 | F10: =F4-F5+F7+F8 -> 804.17624 | G10: =G4-G5+G7+G8 -> 996.70794 | H10: =I10/E10 -> 1.6865913 | I10: =I4-I5+I7+I8 -> 1053.4792 | J10: =J4-J5+J7+J8 -> 774.66133 | K10: =K4-K5+K7+K8 -> 915.35441 | L10: =SUM(I10:K10)/SUM(E10:G10) -> 1.1311028 | M10: =M4-M5+M7+M8 -> -97.301456 | N10: =N4-N5+N7+N8 -> 850.81121 | O10: =O4-O5+O7+O8 -> 1804.8159 | P10: =P4-P5+P7+P8 -> 671.66451 | Q10: =Q4-Q5+Q7+Q8 -> 316.41915 | R10: 1280.2768 | S10: 1575.0411 | T10: 781.41958 | X10: =SUM(I10:K10)/SUM(E10:G10) -> 1.1311028 | Z10: 626.29417 | AA10: 910.81471 | AB10: 1041.1673 | AC10: =AD10/Z10 -> 1.6096983 | AD10: 1008.1447 | AE10: 1115.6991 | AF10: 871.62718 | AH10: =SUM(AD10:AF10)/SUM(Z10:AB10) -> 1.1618116
D11: CoC % | E11: =E10/E13 -> 0.0060022903 | F11: =F10/F13 -> 0.005594111 | G11: =G10/G13 -> 0.0053038379 | I11: =I10/I13 -> 0.011197131 | J11: =J10/J13 -> 0.0077192859 | K11: =K10/K13 -> 0.0072623405 | M11: =M10/M13 -> -0.0032228319 | N11: =N10/N13 -> 0.021698749 | O11: =O10/O13 -> 0.042247457 | P11: =P10/P13 -> 0.015755437 | Q11: =Q10/Q13 -> 0.0057587162 | R11: 0.018933056 | S11: 0.021166365 | T11: 0.0077730378 | Z11: 0.0082141274 | AA11: 0.0082016771 | AB11: 0.0068720397 | AD11: 0.014751193 | AE11: 0.014210265 | AF11: 0.0083728501
D12: Disbursals | E12: =SUM('Input - Disbursals'!D9:O9) -> 65610 | F12: =SUM('Input - Disbursals'!P9:AA9) -> 79000 | G12: =SUM('Input - Disbursals'!AB9:AM9) -> 91000 | I12: =SUM('Input - Disbursals'!D3:O3) -> 31451.25 | J12: =SUM('Input - Disbursals'!P3:AA3) -> 30923.414 | K12: =SUM('Input - Disbursals'!AB3:AM3) -> 81642.115 | Z12: 48926.841 | AA12: 65608.78 | AB12: 76267.656 | AD12: 21651.841 | AE12: 31322.075 | AF12: 68718.496
D13: ANR | E13: =AVERAGE('Input - ANR'!D15:O15) -> 104063.66 | F13: =AVERAGE('Input - ANR'!P15:AA15) -> 143754.07 | G13: =AVERAGE('Input - ANR'!AB15:AM15) -> 187922.02 | I13: ='MOM Summary'!BM45 -> 94084.743 | J13: ='MOM Summary'!BN45 -> 100354.01 | K13: ='MOM Summary'!BO45 -> 126041.24 | M13: 30191.291 | N13: 39210.151 | O13: 42720.108 | P13: 42630.648 | Q13: 54946.128 | Z13: 76245.978 | AA13: 111052.25 | AB13: 151507.75 | AD13: 68343.266 | AE13: 78513.605 | AF13: 104101.61
D14: ENR | E14: ='Input - ENR'!O9 -> 112136.8 | F14: ='Input - ENR'!AA9 -> 150480.17 | G14: ='Input - ENR'!AM9 -> 193146.81 | I14: ='MOM Summary'!BM39 -> 86930.596 | J14: ='MOM Summary'!BN39 -> 92702.224 | K14: ='MOM Summary'!BO39 -> 143181.26 | M14: 30645.169 | N14: 39398.285 | O14: 38275.721 | P14: 41260.274 | Q14: 59276.646 | Z14: 89826.036 | AA14: 125498.39 | AB14: 162285.83 | AD14: 65255.747 | AE14: 77975.775 | AF14: 121832.96
D15: ECL BS | E15: ='ECL BS'!O4+'ECL BS'!O10 -> 1839.2751 | F15: ='ECL BS'!AA4+'ECL BS'!AA10 -> 2118.7326 | G15: ='ECL BS'!AM4+'ECL BS'!AM10 -> 2463.5771 | I15: ='MOM Summary'!BM33 -> 2264.6395 | J15: ='MOM Summary'!BN33 -> 2389.8474 | K15: ='MOM Summary'!BO33 -> 2511.4424 | M15: 468.565 | N15: =M15+N7 -> 1036.2892 | O15: =N15+O7 -> 2096.6575 | P15: =O15+P7 -> 2432.4216 | Q15: =P15+Q7 -> 1619.632 | Z15: 1801.2291 | AA15: 1875.3977 | AB15: 2306.6005 | AD15: 2177.1358 | AE15: 2282.7531 | AF15: 2418.8035
D16: ECL BS/ENR | E16: =E15/E14 -> 0.016402065 | F16: =F15/F14 -> 0.014079812 | G16: =G15/G14 -> 0.012754946 | I16: =I15/I14 -> 0.026051121 | J16: =J15/J14 -> 0.025779828 | K16: =K15/K14 -> 0.017540301 | M16: =M15/M14 -> 0.015290012 | N16: =N15/N14 -> 0.026302901 | O16: =O15/O14 -> 0.054777738 | P16: =P15/P14 -> 0.058953112 | Q16: =Q15/Q14 -> 0.027323274 | Z16: 0.020052417 | AA16: 0.014943599 | AB16: 0.014213197 | AD16: 0.033363128 | AE16: 0.029275158 | AF16: 0.019853442
D17: GWO/ANR | E17: =E4/E13 -> 0.005269368 | F17: =F4/F13 -> 0.0044920916 | G17: =G4/G13 -> 0.0042054399 | I17: =I4/I13 -> 0.0058282534 | J17: =J4/J13 -> 0.0076208615 | K17: =K4/K13 -> 0.0073736928 | M17: =M4/M13 -> 0.013045195 | N17: =N4/N13 -> 0.011273948 | O17: =O4/O13 -> 0.021175239 | P17: =P4/P13 -> 0.010733877 | Q17: =Q4/Q13 -> 0.032705812 | Z17: 0.0069697789 | AA17: 0.0090560418 | AB17: 0.0051231564 | AD17: 0.0077757128 | AE17: 0.0148434 | AF17: 0.0085971392
D18: GNPA | E18: ='Input - GNPA'!O39 -> 2313.1767 | F18: ='Input - GNPA'!AA39 -> 2608.9877 | G18: ='Input - GNPA'!AM39 -> 2951.5247 | I18: ='MOM Summary'!BM51 -> 3094.7105 | J18: ='MOM Summary'!BN51 -> 3456.5928 | K18: ='MOM Summary'!BO51 -> 3396.9269 | Z18: 2454.5056 | AA18: 2365.779 | AB18: 2532.1747 | AD18: 3076.6082 | AE18: 3581.3979 | AF18: 3011.2394
D19: NNPA | E19: ='Input - GNPA'!O45 -> 1502.8707 | F19: ='Input - GNPA'!AA45 -> 1735.1589 | G19: ='Input - GNPA'!AM45 -> 1999.6398 | I19: ='MOM Summary'!BM57 -> 1851.8092 | J19: ='MOM Summary'!BN57 -> 2118.8827 | K19: ='MOM Summary'!BO57 -> 2104.6887 | Z19: 1591.3023 | AA19: 1684.8803 | AB19: 1760.2332 | AD19: 1740.778 | AE19: 2240.9527 | AF19: 1888.9856
D20: GNPA% | E20: ='Input - GNPA'!O51 -> 0.020403727 | F20: ='Input - GNPA'!AA51 -> 0.01714911 | G20: ='Input - GNPA'!AM51 -> 0.015114985 | I20: ='MOM Summary'!BM63 -> 0.035715322 | J20: ='MOM Summary'!BN63 -> 0.037408138 | K20: ='MOM Summary'!BO63 -> 0.023801644 | M20: 0.020678312 | N20: 0.036817477 | O20: 0.056028682 | P20: 0.062302654 | Q20: 0.037431908 | R20: 0.069741801 | S20: 0.092798823 | T20: 0.051739469 | U20: =I20/E20 -> 1.7504313 | V20: =J20/F20 -> 2.1813457 | W20: =K20/G20 -> 1.5747051 | Z20: 0.027027797 | AA20: 0.018645964 | AB20: 0.015389441 | AD20: 0.04668013 | AE20: 0.045474874 | AF20: 0.024471418
D21: NNPA% | E21: ='Input - GNPA'!O57 -> 0.01335173 | F21: ='Input - GNPA'!AA57 -> 0.011471243 | G21: ='Input - GNPA'!AM57 -> 0.010290472 | I21: ='MOM Summary'!BM69 -> 0.021573257 | J21: ='MOM Summary'!BN69 -> 0.02313496 | K21: ='MOM Summary'!BO69 -> 0.01487465 | M21: 0.012300268 | N21: 0.019536555 | O21: 0.028748404 | P21: 0.030408628 | Q21: 0.023407939 | R21: 0.046627375 | S21: 0.066861049 | T21: 0.037048977 | U21: =(U18-U19)+(U18*5%) -> 0 | Z21: 0.017790838 | AA21: 0.013233197 | AB21: 0.010967345 | AD21: 0.02641212 | AE21: 0.028454543 | AF21: 0.015351205
D22: Stage1 | E22: ='Calculation - Stage dist'!R35 -> 0.96630674 | F22: ='Calculation - Stage dist'!AD35 -> 0.97136969 | G22: ='Calculation - Stage dist'!AP35 -> 0.97418117 | I22: ='Calculation - Stage dist'!R40 -> 0.94261888 | J22: ='Calculation - Stage dist'!AD40 -> 0.94048853 | K22: ='Calculation - Stage dist'!AP40 -> 0.96103245 | M22: 0.964 | N22: 0.941 | O22: 0.851 | P22: 0.837 | Q22: 0.94092999 | Z22: 0.95635563 | AA22: 0.96842306 | AB22: 0.96865616 | AD22: 0.92872922 | AE22: 0.93163254 | AF22: 0.95560288
D23: Stage2 | E23: ='Calculation - Stage dist'!R36 -> 0.019326476 | F23: ='Calculation - Stage dist'!AD36 -> 0.017002945 | G23: ='Calculation - Stage dist'!AP36 -> 0.015682762 | I23: ='Calculation - Stage dist'!R41 -> 0.031835921 | J23: ='Calculation - Stage dist'!AD41 -> 0.033200693 | K23: ='Calculation - Stage dist'!AP41 -> 0.022800786 | M23: 0.016 | N23: 0.022 | O23: 0.095 | P23: 0.103 | Q23: 0.036119753 | Z23: 0.028151897 | AA23: 0.022410569 | AB23: 0.023408625 | AD23: 0.041388488 | AE23: 0.040385146 | AF23: 0.029566791
D24: Stage3 | E24: ='Calculation - Stage dist'!R37 -> 0.014366784 | F24: ='Calculation - Stage dist'!AD37 -> 0.011627365 | G24: ='Calculation - Stage dist'!AP37 -> 0.010136072 | I24: ='Calculation - Stage dist'!R42 -> 0.025545196 | J24: ='Calculation - Stage dist'!AD42 -> 0.026310781 | K24: ='Calculation - Stage dist'!AP42 -> 0.016166767 | M24: 0.02 | N24: 0.037 | O24: 0.055 | P24: 0.06 | Q24: 0.022950255 | U24: =I24/E24 -> 1.7780733 | V24: =J24/F24 -> 2.2628327 | W24: =K24/G24 -> 1.5949735 | Z24: 0.015492477 | AA24: 0.0091663698 | AB24: 0.0079352188 | AD24: 0.029882289 | AE24: 0.027982312 | AF24: 0.014830329
E25: =1-E21/E20 -> 0.34562297 | F25: =1-F21/F20 -> 0.33108814 | G25: =1-G21/G20 -> 0.3191874 | I25: =1-I21/I20 -> 0.39596633 | J25: =1-J21/J20 -> 0.38155275 | K25: =1-K21/K20 -> 0.37505788 | S25: =S18-S21 -> -0.066861049 | T25: =T18-T21 -> -0.037048977 | U25: =U18-U21 -> 0 | Z25: 0.34175773 | AA25: 0.29029161 | AB25: 0.28734607 | AD25: 0.43418924 | AE25: 0.3742799 | AF25: 0.37268835
S26: =S21-S17 -> 0.066861049
I27: 1294.8645 | J27: 913.53111 | K27: 662.05612
E28: =E9/E13 -> 0.001640082 | F28: =F9/F13 -> 0.0019439968 | I28: =I9/I13 -> 0.0063351109 | J28: =J9/J13 -> 0.0012476628 | K28: =K9/K13 -> 0.0009647234 | Z28: =Z9/Z13 -> 0.0025223286 | AA28: =AA9/AA13 -> 0.00066787079 | AD28: =AD9/AD13 -> 0.0083142588
I30: =I10-I27 -> -241.38527 | J30: =J10-J27 -> -138.86978 | K30: =K10-K27 -> 253.29828

Sheet MOM Summary
C1: =LOOKUP(C2,'Input-Stress Parameters'!$C$9:$BJ$9,'Input-Stress Parameters'!$C$11:$BJ$11) -> N | D1: =LOOKUP(D2,'Input-Stress Parameters'!$C$9:$BJ$9,'Input-Stress Parameters'!$C$11:$BJ$11) -> SL1 | E1: =LOOKUP(E2,'Input-Stress Parameters'!$C$9:$BJ$9,'Input-Stress Parameters'!$C$11:$BJ$11) -> SL1 | F1: =LOOKUP(F2,'Input-Stress Parameters'!$C$9:$BJ$9,'Input-Stress Parameters'!$C$11:$BJ$11) -> SL1 | G1: =LOOKUP(G2,'Input-Stress Parameters'!$C$9:$BJ$9,'Input-Stress Parameters'!$C$11:$BJ$11) -> SL1 | H1: =LOOKUP(H2,'Input-Stress Parameters'!$C$9:$BJ$9,'Input-Stress Parameters'!$C$11:$BJ$11) -> SL1 | I1: =LOOKUP(I2,'Input-Stress Parameters'!$C$9:$BJ$9,'Input-Stress Parameters'!$C$11:$BJ$11) -> SL1 | J1: =LOOKUP(J2,'Input-Stress Parameters'!$C$9:$BJ$9,'Input-Stress Parameters'!$C$11:$BJ$11) -> SL2 | ... BJ1: =LOOKUP(BJ2,'Input-Stress Parameters'!$C$9:$BJ$9,'Input-Stress Parameters'!$C$11:$BJ$11) -> N | BM1: ABP Stress
A2: GWO (Stress) | B2: Inputs | C2: ='Input-Stress Parameters'!C9 -> 45352 | D2: =EDATE(C2,1) -> 45383 | E2: =EDATE(D2,1) -> 45413 | F2: =EDATE(E2,1) -> 45444 | G2: =EDATE(F2,1) -> 45474 | H2: =EDATE(G2,1) -> 45505 | I2: =EDATE(H2,1) -> 45536 | J2: =EDATE(I2,1) -> 45566 | K2: =EDATE(J2,1) -> 45597 | ... BJ2: =EDATE(BI2,1) -> 47150 | BM2: FY24 | BN2: FY25 | BO2: FY26
A3: =$A$2 -> GWO (Stress) | B3: SMHFC | C3: =SUM(C4:C6) -> 66.317611 | D3: =SUM(D4:D6) -> 58.280029 | E3: =SUM(E4:E6) -> 33.734083 | F3: =SUM(F4:F6) -> 39.460786 | G3: =SUM(G4:G6) -> 37.144067 | H3: =SUM(H4:H6) -> 38.522038 | I3: =SUM(I4:I6) -> 31.964472 | J3: =SUM(J4:J6) -> 50.814669 | ... BJ3: =SUM(BJ4:BJ6) -> 0 | BM3: =SUM(BM4:BM6) -> 548.34973 | BN3: =SUM(BN4:BN6) -> 764.78404 | BO3: =SUM(BO4:BO6) -> 929.38938
A4: =$A$2 -> GWO (Stress) | B4: HL | C4: ='Calculation - NCL and ECL'!E25 -> 27.583752 | D4: ='Calculation - NCL and ECL'!F25 -> 41.364333 | E4: ='Calculation - NCL and ECL'!G25 -> 16.61273 | F4: ='Calculation - NCL and ECL'!H25 -> 22.733168 | G4: ='Calculation - NCL and ECL'!I25 -> 17.815778 | H4: ='Calculation - NCL and ECL'!J25 -> 21.977915 | I4: ='Calculation - NCL and ECL'!K25 -> 15.819071 | J4: ='Calculation - NCL and ECL'!L25 -> 29.975829 | ... AM4: ='Calculation - NCL and ECL'!AO25 -> 47.199753 | BM4: =SUM(D4:O4) -> 267.24392 | BN4: =SUM(P4:AA4) -> 480.05523 | BO4: =SUM(AB4:AM4) -> 648.17867
A5: =$A$2 -> GWO (Stress) | B5: LAP | C5: ='Calculation - NCL and ECL'!E26 -> 38.733859 | D5: ='Calculation - NCL and ECL'!F26 -> 16.915696 | E5: ='Calculation - NCL and ECL'!G26 -> 17.121354 | F5: ='Calculation - NCL and ECL'!H26 -> 16.727618 | G5: ='Calculation - NCL and ECL'!I26 -> 19.328289 | H5: ='Calculation - NCL and ECL'!J26 -> 16.544124 | I5: ='Calculation - NCL and ECL'!K26 -> 16.145401 | J5: ='Calculation - NCL and ECL'!L26 -> 20.83884 | ... AM5: ='Calculation - NCL and ECL'!AO26 -> 20.416041 | BM5: =SUM(D5:O5) -> 281.10581 | BN5: =SUM(P5:AA5) -> 284.72881 | BO5: =SUM(AB5:AM5) -> 281.21071
A6: =$A$2 -> GWO (Stress) | B6: DF | C6: ='Calculation - NCL and ECL'!E27 -> 0 | D6: ='Calculation - NCL and ECL'!F27 -> 0 | E6: ='Calculation - NCL and ECL'!G27 -> 0 | F6: ='Calculation - NCL and ECL'!H27 -> 0 | G6: ='Calculation - NCL and ECL'!I27 -> 0 | H6: ='Calculation - NCL and ECL'!J27 -> 0 | I6: ='Calculation - NCL and ECL'!K27 -> 0 | J6: ='Calculation - NCL and ECL'!L27 -> 0 | ... AM6: ='Calculation - NCL and ECL'!AO27 -> 0 | BM6: =SUM(D6:O6) -> 0 | BN6: =SUM(P6:AA6) -> 0 | BO6: =SUM(AB6:AM6) -> 0
A8: Recovery (Stress) | B8: Inputs | C8: =C2 -> 45352 | D8: =EDATE(C8,1) -> 45383 | E8: =EDATE(D8,1) -> 45413 | F8: =EDATE(E8,1) -> 45444 | G8: =EDATE(F8,1) -> 45474 | H8: =EDATE(G8,1) -> 45505 | I8: =EDATE(H8,1) -> 45536 | J8: =EDATE(I8,1) -> 45566 | K8: =EDATE(J8,1) -> 45597 | ... BJ8: =EDATE(BI8,1) -> 47150 | BM8: =BM2 -> FY24 | BN8: =BN2 -> FY25 | BO8: =BO2 -> FY26
A9: =$A$8 -> Recovery (Stress) | B9: SMHFC | C9: =SUM(C10:C12) -> 0 | D9: =SUM(D10:D12) -> 6.5699547 | E9: =SUM(E10:E12) -> 7.7444647 | F9: =SUM(F10:F12) -> 8.4426556 | G9: =SUM(G10:G12) -> 7.0648273 | H9: =SUM(H10:H12) -> 5.5511866 | I9: =SUM(I10:I12) -> 5.5447484 | J9: =SUM(J10:J12) -> 7.1814032 | ... BJ9: =SUM(BJ10:BJ12) -> 0 | BM9: =SUM(BM10:BM12) -> 90.907807 | BN9: =SUM(BN10:BN12) -> 115.33068 | BO9: =SUM(BO10:BO12) -> 135.62991
A10: =$A$8 -> Recovery (Stress) | B10: HL | C10: ='Calculation - NCL and ECL'!E28 -> 0 | D10: ='Calculation - NCL and ECL'!F28 -> 4.5369999 | E10: ='Calculation - NCL and ECL'!G28 -> 5.2758892 | F10: ='Calculation - NCL and ECL'!H28 -> 5.7267373 | G10: ='Calculation - NCL and ECL'!I28 -> 4.8491776 | H10: ='Calculation - NCL and ECL'!J28 -> 3.836753 | I10: ='Calculation - NCL and ECL'!K28 -> 3.8099655 | J10: ='Calculation - NCL and ECL'!L28 -> 4.854774 | ... AM10: ='Calculation - NCL and ECL'!AO28 -> 9.0975916 | BM10: =SUM(D10:O10) -> 60.539428 | BN10: =SUM(P10:AA10) -> 65.808495 | BO10: =SUM(AB10:AM10) -> 82.194201
A11: =$A$8 -> Recovery (Stress) | B11: LAP | C11: ='Calculation - NCL and ECL'!E29 -> 0 | D11: ='Calculation - NCL and ECL'!F29 -> 2.0329549 | E11: ='Calculation - NCL and ECL'!G29 -> 2.4685755 | F11: ='Calculation - NCL and ECL'!H29 -> 2.7159184 | G11: ='Calculation - NCL and ECL'!I29 -> 2.2156497 | H11: ='Calculation - NCL and ECL'!J29 -> 1.7144336 | I11: ='Calculation - NCL and ECL'!K29 -> 1.7347828 | J11: ='Calculation - NCL and ECL'!L29 -> 2.3266292 | ... AM11: ='Calculation - NCL and ECL'!AO29 -> 5.4399638 | BM11: =SUM(D11:O11) -> 30.368378 | BN11: =SUM(P11:AA11) -> 49.522184 | BO11: =SUM(AB11:AM11) -> 53.435711
A12: =$A$8 -> Recovery (Stress) | B12: DF | C12: ='Calculation - NCL and ECL'!E30 -> 0 | D12: ='Calculation - NCL and ECL'!F30 -> 0 | E12: ='Calculation - NCL and ECL'!G30 -> 0 | F12: ='Calculation - NCL and ECL'!H30 -> 0 | G12: ='Calculation - NCL and ECL'!I30 -> 0 | H12: ='Calculation - NCL and ECL'!J30 -> 0 | I12: ='Calculation - NCL and ECL'!K30 -> 0 | J12: ='Calculation - NCL and ECL'!L30 -> 0 | ... AM12: ='Calculation - NCL and ECL'!AO30 -> 0 | BM12: =SUM(D12:O12) -> 0 | BN12: =SUM(P12:AA12) -> 0 | BO12: =SUM(AB12:AM12) -> 0
A14: Model ECL (Stress) | B14: Inputs | C14: =C2 -> 45352 | D14: =EDATE(C14,1) -> 45383 | E14: =EDATE(D14,1) -> 45413 | F14: =EDATE(E14,1) -> 45444 | G14: =EDATE(F14,1) -> 45474 | H14: =EDATE(G14,1) -> 45505 | I14: =EDATE(H14,1) -> 45536 | J14: =EDATE(I14,1) -> 45566 | K14: =EDATE(J14,1) -> 45597 | ... BJ14: =EDATE(BI14,1) -> 47150 | BM14: =BM8 -> FY24 | BN14: =BN8 -> FY25 | BO14: =BO8 -> FY26
A15: =A14 -> Model ECL (Stress) | B15: SMHFC | C15: =SUM(C16:C18) -> -3.4131772 | D15: =SUM(D16:D18) -> 56.977991 | E15: =SUM(E16:E18) -> 53.291542 | F15: =SUM(F16:F18) -> 58.327149 | G15: =SUM(G16:G18) -> 56.37601 | H15: =SUM(H16:H18) -> 55.001484 | I15: =SUM(I16:I18) -> 6.3742211 | J15: =SUM(J16:J18) -> 58.421872 | ... BJ15: =SUM(BJ16:BJ18) -> 0 | BM15: =SUM(BM16:BM18) -> 468.63553 | BN15: =SUM(BN16:BN18) -> 153.07826 | BO15: =SUM(BO16:BO18) -> 150.69271
A16: =A15 -> Model ECL (Stress) | B16: HL | C16: ='Calculation - NCL and ECL'!E22 -> 12.24177 | D16: ='Calculation - NCL and ECL'!F22 -> 26.191163 | E16: ='Calculation - NCL and ECL'!G22 -> 32.177183 | F16: ='Calculation - NCL and ECL'!H22 -> 31.334479 | G16: ='Calculation - NCL and ECL'!I22 -> 29.810836 | H16: ='Calculation - NCL and ECL'!J22 -> 31.031067 | I16: ='Calculation - NCL and ECL'!K22 -> 32.328561 | J16: ='Calculation - NCL and ECL'!L22 -> 33.186034 | ... AM16: ='Calculation - NCL and ECL'!AO22 -> 16.937631 | BM16: =SUM(D16:O16) -> 380.42408 | BN16: =SUM(P16:AA16) -> 144.78224 | BO16: =SUM(AB16:AM16) -> 82.927908
A17: =A16 -> Model ECL (Stress) | B17: LAP | C17: ='Calculation - NCL and ECL'!E23 -> -17.918123 | D17: ='Calculation - NCL and ECL'!F23 -> 31.278298 | E17: ='Calculation - NCL and ECL'!G23 -> 23.893866 | F17: ='Calculation - NCL and ECL'!H23 -> 29.560409 | G17: ='Calculation - NCL and ECL'!I23 -> 28.872835 | H17: ='Calculation - NCL and ECL'!J23 -> 26.075922 | I17: ='Calculation - NCL and ECL'!K23 -> -23.981502 | J17: ='Calculation - NCL and ECL'!L23 -> 27.233429 | ... AM17: ='Calculation - NCL and ECL'!AO23 -> 21.035297 | BM17: =SUM(D17:O17) -> 111.88639 | BN17: =SUM(P17:AA17) -> 20.687978 | BO17: =SUM(AB17:AM17) -> 10.467159
A18: =A17 -> Model ECL (Stress) | B18: DF | C18: ='Calculation - NCL and ECL'!E24 -> 2.2631753 | D18: ='Calculation - NCL and ECL'!F24 -> -0.49147059 | E18: ='Calculation - NCL and ECL'!G24 -> -2.7795071 | F18: ='Calculation - NCL and ECL'!H24 -> -2.5677393 | G18: ='Calculation - NCL and ECL'!I24 -> -2.3076602 | H18: ='Calculation - NCL and ECL'!J24 -> -2.1055049 | I18: ='Calculation - NCL and ECL'!K24 -> -1.9728373 | J18: ='Calculation - NCL and ECL'!L24 -> -1.9975911 | ... AM18: ='Calculation - NCL and ECL'!AO24 -> 9.9277804 | BM18: =SUM(D18:O18) -> -23.67494 | BN18: =SUM(P18:AA18) -> -12.391961 | BO18: =SUM(AB18:AM18) -> 57.29764
A20: Overlay (Stress) | B20: Inputs | C20: =C14 -> 45352 | D20: =EDATE(C20,1) -> 45383 | E20: =EDATE(D20,1) -> 45413 | F20: =EDATE(E20,1) -> 45444 | G20: =EDATE(F20,1) -> 45474 | H20: =EDATE(G20,1) -> 45505 | I20: =EDATE(H20,1) -> 45536 | J20: =EDATE(I20,1) -> 45566 | K20: =EDATE(J20,1) -> 45597 | ... BJ20: =EDATE(BI20,1) -> 47150 | BM20: =BM14 -> FY24 | BN20: =BN14 -> FY25 | BO20: =BO14 -> FY26
A21: =A20 -> Overlay (Stress) | B21: SMHFC | C21: =SUM(C22:C24) -> -4.3338134 | D21: =SUM(D22:D24) -> -5.1007068 | E21: =SUM(E22:E24) -> -1.5665816 | F21: =SUM(F22:F24) -> -1.4301741 | G21: =SUM(G22:G24) -> -0.65208373 | H21: =SUM(H22:H24) -> -2.7817298 | I21: =SUM(I22:I24) -> -2.3709063 | J21: =SUM(J22:J24) -> 114.26704 | ... BJ21: =SUM(BJ22:BJ24) -> 0 | BM21: =SUM(BM22:BM24) -> 127.40175 | BN21: =SUM(BN22:BN24) -> -27.870289 | BO21: =SUM(BO22:BO24) -> -29.097773
A22: =A21 -> Overlay (Stress) | B22: HL | C22: ='Calculation - NCL and ECL'!E37+'Calculation - NCL and ECL'!E40 -> -1 | D22: ='Calculation - NCL and ECL'!F37+'Calculation - NCL and ECL'!F40 -> -5.3353083 | E22: ='Calculation - NCL and ECL'!G37+'Calculation - NCL and ECL'!G40 -> -0.20400505 | F22: ='Calculation - NCL and ECL'!H37+'Calculation - NCL and ECL'!H40 -> -1.3312835 | G22: ='Calculation - NCL and ECL'!I37+'Calculation - NCL and ECL'!I40 -> -0.47259535 | H22: ='Calculation - NCL and ECL'!J37+'Calculation - NCL and ECL'!J40 -> -1.7460392 | I22: ='Calculation - NCL and ECL'!K37+'Calculation - NCL and ECL'!K40 -> -1.5158346 | J22: ='Calculation - NCL and ECL'!L37+'Calculation - NCL and ECL'!L40 -> 68.771536 | ... AM22: ='Calculation - NCL and ECL'!AO37+'Calculation - NCL and ECL'!AO40 -> 0.69058364 | BM22: =SUM(D22:O22) -> 89.160292 | BN22: =SUM(P22:AA22) -> -7.0906116 | BO22: =SUM(AB22:AM22) -> -18.875964
A23: =A22 -> Overlay (Stress) | B23: LAP | C23: ='Calculation - NCL and ECL'!E38+'Calculation - NCL and ECL'!E41 -> -3.3338134 | D23: ='Calculation - NCL and ECL'!F38+'Calculation - NCL and ECL'!F41 -> 0.2346015 | E23: ='Calculation - NCL and ECL'!G38+'Calculation - NCL and ECL'!G41 -> -1.3625766 | F23: ='Calculation - NCL and ECL'!H38+'Calculation - NCL and ECL'!H41 -> -0.098890666 | G23: ='Calculation - NCL and ECL'!I38+'Calculation - NCL and ECL'!I41 -> -0.17948837 | H23: ='Calculation - NCL and ECL'!J38+'Calculation - NCL and ECL'!J41 -> -1.0356907 | I23: ='Calculation - NCL and ECL'!K38+'Calculation - NCL and ECL'!K41 -> -0.85507178 | J23: ='Calculation - NCL and ECL'!L38+'Calculation - NCL and ECL'!L41 -> 45.495502 | ... AM23: ='Calculation - NCL and ECL'!AO38+'Calculation - NCL and ECL'!AO41 -> 1.0647865 | BM23: =SUM(D23:O23) -> 38.241459 | BN23: =SUM(P23:AA23) -> -20.779677 | BO23: =SUM(AB23:AM23) -> -10.221809
A24: =A23 -> Overlay (Stress) | B24: DF | C24: ='Calculation - NCL and ECL'!E39+'Calculation - NCL and ECL'!E42 -> 0 | D24: ='Calculation - NCL and ECL'!F39+'Calculation - NCL and ECL'!F42 -> 0 | E24: ='Calculation - NCL and ECL'!G39+'Calculation - NCL and ECL'!G42 -> 0 | F24: ='Calculation - NCL and ECL'!H39+'Calculation - NCL and ECL'!H42 -> 0 | G24: ='Calculation - NCL and ECL'!I39+'Calculation - NCL and ECL'!I42 -> 0 | H24: ='Calculation - NCL and ECL'!J39+'Calculation - NCL and ECL'!J42 -> 0 | I24: ='Calculation - NCL and ECL'!K39+'Calculation - NCL and ECL'!K42 -> 0 | J24: ='Calculation - NCL and ECL'!L39+'Calculation - NCL and ECL'!L42 -> 0 | ... AM24: ='Calculation - NCL and ECL'!AO39+'Calculation - NCL and ECL'!AO42 -> 0 | BM24: =SUM(D24:O24) -> 0 | BN24: =SUM(P24:AA24) -> 0 | BO24: =SUM(AB24:AM24) -> 0
A26: COC (Stress) | B26: Inputs | C26: =C20 -> 45352 | D26: =EDATE(C26,1) -> 45383 | E26: =EDATE(D26,1) -> 45413 | F26: =EDATE(E26,1) -> 45444 | G26: =EDATE(F26,1) -> 45474 | H26: =EDATE(G26,1) -> 45505 | I26: =EDATE(H26,1) -> 45536 | J26: =EDATE(I26,1) -> 45566 | K26: =EDATE(J26,1) -> 45597 | ... BJ26: =EDATE(BI26,1) -> 47150 | BM26: =BM20 -> FY24 | BN26: =BN20 -> FY25 | BO26: =BO20 -> FY26
A27: =A26 -> COC (Stress) | B27: SMHFC | C27: =SUM(C28:C30) -> 58.57062 | D27: =SUM(D28:D30) -> 103.58736 | E27: =SUM(E28:E30) -> 77.714579 | F27: =SUM(F28:F30) -> 87.915105 | G27: =SUM(G28:G30) -> 85.803166 | H27: =SUM(H28:H30) -> 85.190606 | I27: =SUM(I28:I30) -> 30.423039 | J27: =SUM(J28:J30) -> 216.32218 | ... BJ27: =SUM(BJ28:BJ30) -> 0 | BM27: =SUM(BM28:BM30) -> 1053.4792 | BN27: =SUM(BN28:BN30) -> 774.66133 | BO27: =SUM(BO28:BO30) -> 915.35441
A28: =A27 -> COC (Stress) | B28: HL | C28: =C4-C10+C16+C22 -> 38.825522 | D28: =D4-D10+D16+D22 -> 57.683189 | E28: =E4-E10+E16+E22 -> 43.310018 | F28: =F4-F10+F16+F22 -> 47.009626 | G28: =G4-G10+G16+G22 -> 42.304841 | H28: =H4-H10+H16+H22 -> 47.426189 | I28: =I4-I10+I16+I22 -> 42.821832 | J28: =J4-J10+J16+J22 -> 127.07862 | ... AM28: =AM4-AM10+AM16+AM22 -> 55.730376 | BM28: =SUM(D28:O28) -> 676.28887 | BN28: =SUM(P28:AA28) -> 551.93837 | BO28: =SUM(AB28:AM28) -> 630.03642
A29: =A28 -> COC (Stress) | B29: LAP | C29: =C5-C11+C17+C23 -> 17.481922 | D29: =D5-D11+D17+D23 -> 46.39564 | E29: =E5-E11+E17+E23 -> 37.184068 | F29: =F5-F11+F17+F23 -> 43.473218 | G29: =G5-G11+G17+G23 -> 45.805986 | H29: =H5-H11+H17+H23 -> 39.869922 | I29: =I5-I11+I17+I23 -> -10.425956 | J29: =J5-J11+J17+J23 -> 91.241142 | ... AM29: =AM5-AM11+AM17+AM23 -> 37.07616 | BM29: =SUM(D29:O29) -> 400.86528 | BN29: =SUM(P29:AA29) -> 235.11493 | BO29: =SUM(AB29:AM29) -> 228.02035
A30: =A29 -> COC (Stress) | B30: DF | C30: =C6-C12+C18+C24 -> 2.2631753 | D30: =D6-D12+D18+D24 -> -0.49147059 | E30: =E6-E12+E18+E24 -> -2.7795071 | F30: =F6-F12+F18+F24 -> -2.5677393 | G30: =G6-G12+G18+G24 -> -2.3076602 | H30: =H6-H12+H18+H24 -> -2.1055049 | I30: =I6-I12+I18+I24 -> -1.9728373 | J30: =J6-J12+J18+J24 -> -1.9975911 | ... AM30: =AM6-AM12+AM18+AM24 -> 9.9277804 | BM30: =SUM(D30:O30) -> -23.67494 | BN30: =SUM(P30:AA30) -> -12.391961 | BO30: =SUM(AB30:AM30) -> 57.29764
A32: ECL BS (Stress) | B32: Inputs | C32: =C26 -> 45352 | D32: =EDATE(C32,1) -> 45383 | E32: =EDATE(D32,1) -> 45413 | F32: =EDATE(E32,1) -> 45444 | G32: =EDATE(F32,1) -> 45474 | H32: =EDATE(G32,1) -> 45505 | I32: =EDATE(H32,1) -> 45536 | J32: =EDATE(I32,1) -> 45566 | K32: =EDATE(J32,1) -> 45597 | ... BJ32: =EDATE(BI32,1) -> 47150 | BM32: =BM26 -> FY24 | BN32: =BN26 -> FY25 | BO32: =BO26 -> FY26
A33: =A32 -> ECL BS (Stress) | B33: SMHFC | C33: =SUM(C34:C36) -> 1668.6022 | D33: =SUM(D34:D36) -> 1720.4795 | E33: =SUM(E34:E36) -> 1772.2044 | F33: =SUM(F34:F36) -> 1829.1014 | G33: =SUM(G34:G36) -> 1884.8253 | H33: =SUM(H34:H36) -> 1937.0451 | I33: =SUM(I34:I36) -> 1941.0484 | J33: =SUM(J34:J36) -> 2113.7373 | ... BJ33: =SUM(BJ34:BJ36) -> 0 | BM33: =SUM(BM34:BM36) -> 2264.6395 | BN33: =SUM(BN34:BN36) -> 2389.8474 | BO33: =SUM(BO34:BO36) -> 2511.4424
A34: =A33 -> ECL BS (Stress) | B34: HL | C34: ='ECL BS'!C17+'ECL BS'!C23+'ECL BS'!C29 -> 1021.0778 | D34: ='ECL BS'!D17+'ECL BS'!D23+'ECL BS'!D29 -> 1041.9336 | E34: ='ECL BS'!E17+'ECL BS'!E23+'ECL BS'!E29 -> 1073.9068 | F34: ='ECL BS'!F17+'ECL BS'!F23+'ECL BS'!F29 -> 1103.91 | G34: ='ECL BS'!G17+'ECL BS'!G23+'ECL BS'!G29 -> 1133.2482 | H34: ='ECL BS'!H17+'ECL BS'!H23+'ECL BS'!H29 -> 1162.5333 | I34: ='ECL BS'!I17+'ECL BS'!I23+'ECL BS'!I29 -> 1193.346 | J34: ='ECL BS'!J17+'ECL BS'!J23+'ECL BS'!J29 -> 1295.3036 | ... AM34: ='ECL BS'!AM17+'ECL BS'!AM23+'ECL BS'!AM29 -> 1692.4057 | BM34: =O34 -> 1490.6621 | BN34: =AA34 -> 1628.3538 | BO34: =AM34 -> 1692.4057
A35: =A34 -> ECL BS (Stress) | B35: LAP | C35: ='ECL BS'!C18+'ECL BS'!C24+'ECL BS'!C30 -> 564.43113 | D35: ='ECL BS'!D18+'ECL BS'!D24+'ECL BS'!D30 -> 595.94403 | E35: ='ECL BS'!E18+'ECL BS'!E24+'ECL BS'!E30 -> 618.47532 | F35: ='ECL BS'!F18+'ECL BS'!F24+'ECL BS'!F30 -> 647.93684 | G35: ='ECL BS'!G18+'ECL BS'!G24+'ECL BS'!G30 -> 676.63018 | H35: ='ECL BS'!H18+'ECL BS'!H24+'ECL BS'!H30 -> 701.67041 | I35: ='ECL BS'!I18+'ECL BS'!I24+'ECL BS'!I30 -> 676.83384 | J35: ='ECL BS'!J18+'ECL BS'!J24+'ECL BS'!J30 -> 749.56277 | ... AM35: ='ECL BS'!AM18+'ECL BS'!AM24+'ECL BS'!AM30 -> 714.71263 | BM35: =O35 -> 714.55898 | BN35: =AA35 -> 714.46728 | BO35: =AM35 -> 714.71263
A36: =A35 -> ECL BS (Stress) | B36: DF | C36: ='ECL BS'!C19+'ECL BS'!C25+'ECL BS'!C31 -> 83.093289 | D36: ='ECL BS'!D19+'ECL BS'!D25+'ECL BS'!D31 -> 82.601818 | E36: ='ECL BS'!E19+'ECL BS'!E25+'ECL BS'!E31 -> 79.822311 | F36: ='ECL BS'!F19+'ECL BS'!F25+'ECL BS'!F31 -> 77.254572 | G36: ='ECL BS'!G19+'ECL BS'!G25+'ECL BS'!G31 -> 74.946912 | H36: ='ECL BS'!H19+'ECL BS'!H25+'ECL BS'!H31 -> 72.841407 | I36: ='ECL BS'!I19+'ECL BS'!I25+'ECL BS'!I31 -> 70.86857 | J36: ='ECL BS'!J19+'ECL BS'!J25+'ECL BS'!J31 -> 68.870979 | ... AM36: ='ECL BS'!AM19+'ECL BS'!AM25+'ECL BS'!AM31 -> 104.32403 | BM36: =O36 -> 59.418349 | BN36: =AA36 -> 47.026388 | BO36: =AM36 -> 104.32403
A38: ENR (Stress) | B38: Inputs | C38: =C32 -> 45352 | D38: =EDATE(C38,1) -> 45383 | E38: =EDATE(D38,1) -> 45413 | F38: =EDATE(E38,1) -> 45444 | G38: =EDATE(F38,1) -> 45474 | H38: =EDATE(G38,1) -> 45505 | I38: =EDATE(H38,1) -> 45536 | J38: =EDATE(I38,1) -> 45566 | K38: =EDATE(J38,1) -> 45597 | ... BJ38: =EDATE(BI38,1) -> 47150 | BM38: =BM32 -> FY24 | BN38: =BN32 -> FY25 | BO38: =BO32 -> FY26
A39: =A38 -> ENR (Stress) | B39: SMHFC | C39: =SUM(C40:C42) -> 78777.342 | D39: =SUM(D40:D42) -> 80016.05 | E39: =SUM(E40:E42) -> 81263.959 | F39: =SUM(F40:F42) -> 82589.784 | G39: =SUM(G40:G42) -> 83962.455 | H39: =SUM(H40:H42) -> 85453.725 | I39: =SUM(I40:I42) -> 85079.435 | J39: =SUM(J40:J42) -> 86182.149 | ... BJ39: =SUM(BJ40:BJ42) -> 0 | BM39: =SUM(BM40:BM42) -> 86930.596 | BN39: =SUM(BN40:BN42) -> 92702.224 | BO39: =SUM(BO40:BO42) -> 143181.26
A40: =A39 -> ENR (Stress) | B40: HL | C40: ='Input - ENR'!C16 -> 52026.136 | D40: ='Input - ENR'!D16 -> 52427.211 | E40: ='Input - ENR'!E16 -> 53343.308 | F40: ='Input - ENR'!F16 -> 54301.817 | G40: ='Input - ENR'!G16 -> 55283.254 | H40: ='Input - ENR'!H16 -> 56336.702 | I40: ='Input - ENR'!I16 -> 57443.134 | J40: ='Input - ENR'!J16 -> 58210.554 | ... AM40: ='Input - ENR'!AM16 -> 102687.74 | BM40: =O40 -> 62701.13 | BN40: =AA40 -> 69324.804 | BO40: =AM40 -> 102687.74
A41: =A40 -> ENR (Stress) | B41: LAP | C41: ='Input - ENR'!C17 -> 19204.152 | D41: ='Input - ENR'!D17 -> 20089.604 | E41: ='Input - ENR'!E17 -> 20678.004 | F41: ='Input - ENR'!F17 -> 21279.43 | G41: ='Input - ENR'!G17 -> 21876.99 | H41: ='Input - ENR'!H17 -> 22499.638 | I41: ='Input - ENR'!I17 -> 21190.748 | J41: ='Input - ENR'!J17 -> 21699.963 | ... AM41: ='Input - ENR'!AM17 -> 30668.49 | BM41: =O41 -> 18786.779 | BN41: =AA41 -> 19064.451 | BO41: =AM41 -> 30668.49
A42: =A41 -> ENR (Stress) | B42: DF | C42: ='Input - ENR'!C18 -> 7547.0548 | D42: ='Input - ENR'!D18 -> 7499.2351 | E42: ='Input - ENR'!E18 -> 7242.6473 | F42: ='Input - ENR'!F18 -> 7008.5371 | G42: ='Input - ENR'!G18 -> 6802.2111 | H42: ='Input - ENR'!H18 -> 6617.3849 | I42: ='Input - ENR'!I18 -> 6445.553 | J42: ='Input - ENR'!J18 -> 6271.6308 | ... AM42: ='Input - ENR'!AM18 -> 9825.028 | BM42: =O42 -> 5442.6873 | BN42: =AA42 -> 4312.9699 | BO42: =AM42 -> 9825.028
A44: ANR (Stress) | B44: Inputs | C44: =C38 -> 45352 | D44: =EDATE(C44,1) -> 45383 | E44: =EDATE(D44,1) -> 45413 | F44: =EDATE(E44,1) -> 45444 | G44: =EDATE(F44,1) -> 45474 | H44: =EDATE(G44,1) -> 45505 | I44: =EDATE(H44,1) -> 45536 | J44: =EDATE(I44,1) -> 45566 | K44: =EDATE(J44,1) -> 45597 | ... BJ44: =EDATE(BI44,1) -> 47150 | BM44: =BM38 -> FY24 | BN44: =BN38 -> FY25 | BO44: =BO38 -> FY26
A45: =A44 -> ANR (Stress) | B45: SMHFC | C45: =SUM(C46:C48) -> 86554.433 | D45: =SUM(D46:D48) -> 88358.894 | E45: =SUM(E46:E48) -> 89259.1 | F45: =SUM(F46:F48) -> 90235.884 | G45: =SUM(G46:G48) -> 91333.291 | H45: =SUM(H46:H48) -> 92447.995 | I45: =SUM(I46:I48) -> 93762.196 | J45: =SUM(J46:J48) -> 94797.18 | ... BJ45: =SUM(BJ46:BJ48) -> 0 | BM45: =SUM(BM46:BM48) -> 94084.743 | BN45: =SUM(BN46:BN48) -> 100354.01 | BO45: =SUM(BO46:BO48) -> 126041.24
A46: =A45 -> ANR (Stress) | B46: HL | C46: ='Input - ANR'!C10 -> 50793.946 | D46: ='Input - ANR'!D10 -> 51905.961 | E46: ='Input - ANR'!E10 -> 52737.653 | F46: ='Input - ANR'!F10 -> 53621.68 | G46: ='Input - ANR'!G10 -> 54568.555 | H46: ='Input - ANR'!H10 -> 55518.816 | I46: ='Input - ANR'!I10 -> 56612.593 | J46: ='Input - ANR'!J10 -> 57504.898 | ... AM46: ='Input - ANR'!AM10 -> 99067.598 | BM46: =AVERAGE(D46:O46) -> 56912.186 | BN46: =AVERAGE(P46:AA46) -> 63303.718 | BO46: =AVERAGE(AB46:AM46) -> 80722.958
A47: =A46 -> ANR (Stress) | B47: LAP | C47: ='Input - ANR'!C11 -> 28570.328 | D47: ='Input - ANR'!D11 -> 29172.184 | E47: ='Input - ANR'!E11 -> 29470.946 | F47: ='Input - ANR'!F11 -> 29816.807 | G47: ='Input - ANR'!G11 -> 30192.774 | H47: ='Input - ANR'!H11 -> 30553.85 | I47: ='Input - ANR'!I11 -> 30968.449 | J47: ='Input - ANR'!J11 -> 31296.697 | ... AM47: ='Input - ANR'!AM11 -> 47435.787 | BM47: =AVERAGE(D47:O47) -> 31015.92 | BN47: =AVERAGE(P47:AA47) -> 32878.516 | BO47: =AVERAGE(AB47:AM47) -> 39622.537
A48: =A47 -> ANR (Stress) | B48: DF | C48: ='Input - ANR'!C12 -> 7190.1585 | D48: ='Input - ANR'!D12 -> 7280.7491 | E48: ='Input - ANR'!E12 -> 7050.5007 | F48: ='Input - ANR'!F12 -> 6797.3964 | G48: ='Input - ANR'!G12 -> 6571.9614 | H48: ='Input - ANR'!H12 -> 6375.3294 | I48: ='Input - ANR'!I12 -> 6181.153 | J48: ='Input - ANR'!J12 -> 5995.585 | ... AM48: ='Input - ANR'!AM12 -> 8837.2199 | BM48: =AVERAGE(D48:O48) -> 6156.6378 | BN48: =AVERAGE(P48:AA48) -> 4171.7809 | BO48: =AVERAGE(AB48:AM48) -> 5695.7457
A50: GNPA (Stress)-CV | B50: Inputs | C50: =C38 -> 45352 | D50: =EDATE(C50,1) -> 45383 | E50: =EDATE(D50,1) -> 45413 | F50: =EDATE(E50,1) -> 45444 | G50: =EDATE(F50,1) -> 45474 | H50: =EDATE(G50,1) -> 45505 | I50: =EDATE(H50,1) -> 45536 | J50: =EDATE(I50,1) -> 45566 | K50: =EDATE(J50,1) -> 45597 | ... BJ50: =EDATE(BI50,1) -> 47150 | BM50: =BM44 -> FY24 | BN50: =BN44 -> FY25 | BO50: =BO44 -> FY26
A51: =A50 -> GNPA (Stress)-CV | B51: SMHFC | C51: =SUM(C52:C54) -> 2071.7715 | D51: =SUM(D52:D54) -> 2190.3467 | E51: =SUM(E52:E54) -> 2291.2012 | F51: =SUM(F52:F54) -> 2390.6239 | G51: =SUM(G52:G54) -> 2502.7966 | H51: =SUM(H52:H54) -> 2610.4879 | I51: =SUM(I52:I54) -> 2614.7493 | J51: =SUM(J52:J54) -> 2750.7516 | ... BJ51: =SUM(BJ52:BJ54) -> 0 | BM51: =SUM(BM52:BM54) -> 3094.7105 | BN51: =SUM(BN52:BN54) -> 3456.5928 | BO51: =SUM(BO52:BO54) -> 3396.9269
A52: =A51 -> GNPA (Stress)-CV | B52: HL | C52: ='Input - GNPA'!C16*1.05 -> 1226.6907 | D52: ='Input - GNPA'!D16*1.05 -> 1255.0441 | E52: ='Input - GNPA'!E16*1.05 -> 1290.5578 | F52: ='Input - GNPA'!F16*1.05 -> 1325.5214 | G52: ='Input - GNPA'!G16*1.05 -> 1369.2699 | H52: ='Input - GNPA'!H16*1.05 -> 1409.6214 | I52: ='Input - GNPA'!I16*1.05 -> 1453.4155 | J52: ='Input - GNPA'!J16*1.05 -> 1510.7682 | ... AM52: ='Input - GNPA'!AM16*1.05 -> 2195.9111 | BM52: =O52 -> 1827.2798 | BN52: =AA52 -> 2093.1925 | BO52: =AM52 -> 2195.9111
A53: =A52 -> GNPA (Stress)-CV | B53: LAP | C53: ='Input - GNPA'!C17*1.05 -> 845.08079 | D53: ='Input - GNPA'!D17*1.05 -> 926.17444 | E53: ='Input - GNPA'!E17*1.05 -> 991.84802 | F53: ='Input - GNPA'!F17*1.05 -> 1056.6659 | G53: ='Input - GNPA'!G17*1.05 -> 1125.4836 | H53: ='Input - GNPA'!H17*1.05 -> 1193.2425 | I53: ='Input - GNPA'!I17*1.05 -> 1154.126 | J53: ='Input - GNPA'!J17*1.05 -> 1233.1982 | ... AM53: ='Input - GNPA'!AM17*1.05 -> 1194.8909 | BM53: =O53 -> 1262.5411 | BN53: =AA53 -> 1360.2438 | BO53: =AM53 -> 1194.8909
A54: =A53 -> GNPA (Stress)-CV | B54: DF | C54: ='Input - GNPA'!C18*1.053 -> 0 | D54: ='Input - GNPA'!D18*1.053 -> 9.1282293 | E54: ='Input - GNPA'!E18*1.053 -> 8.7953381 | F54: ='Input - GNPA'!F18*1.053 -> 8.4366006 | G54: ='Input - GNPA'!G18*1.053 -> 8.0429968 | H54: ='Input - GNPA'!H18*1.053 -> 7.6239753 | I54: ='Input - GNPA'!I18*1.053 -> 7.2077783 | J54: ='Input - GNPA'!J18*1.053 -> 6.7852091 | ... AM54: ='Input - GNPA'!AM18*1.053 -> 6.1248966 | BM54: =O54 -> 4.8894966 | BN54: =AA54 -> 3.156421 | BO54: =AM54 -> 6.1248966
A56: NNPA (Stress)-CV | B56: Inputs | C56: =C50 -> 45352 | D56: =EDATE(C56,1) -> 45383 | E56: =EDATE(D56,1) -> 45413 | F56: =EDATE(E56,1) -> 45444 | G56: =EDATE(F56,1) -> 45474 | H56: =EDATE(G56,1) -> 45505 | I56: =EDATE(H56,1) -> 45536 | J56: =EDATE(I56,1) -> 45566 | K56: =EDATE(J56,1) -> 45597 | ... BJ56: =EDATE(BI56,1) -> 47150 | BM56: =BM50 -> FY24 | BN56: =BN50 -> FY25 | BO56: =BO50 -> FY26
A57: =A56 -> NNPA (Stress)-CV | B57: SMHFC | C57: =SUM(C58:C60) -> 1287.6013 | D57: =SUM(D58:D60) -> 1376.5914 | E57: =SUM(E58:E60) -> 1446.7194 | F57: =SUM(F58:F60) -> 1515.5245 | G57: =SUM(G58:G60) -> 1593.6805 | H57: =SUM(H58:H60) -> 1669.6192 | I57: =SUM(I58:I60) -> 1673.824 | J57: =SUM(J58:J60) -> 1651.494 | ... BJ57: =SUM(BJ58:BJ60) -> 0 | BM57: =SUM(BM58:BM60) -> 1851.8092 | BN57: =SUM(BN58:BN60) -> 2118.8827 | BO57: =SUM(BO58:BO60) -> 2104.6887
A58: =A57 -> NNPA (Stress)-CV | B58: HL | C58: ='Input - GNPA'!C22+'Input - GNPA'!C16*0.05 -> 743.40061 | D58: ='Input - GNPA'!D22+'Input - GNPA'!D16*0.05 -> 767.50541 | E58: ='Input - GNPA'!E22+'Input - GNPA'!E16*0.05 -> 789.77251 | F58: ='Input - GNPA'!F22+'Input - GNPA'!F16*0.05 -> 812.74392 | G58: ='Input - GNPA'!G22+'Input - GNPA'!G16*0.05 -> 841.99754 | H58: ='Input - GNPA'!H22+'Input - GNPA'!H16*0.05 -> 869.3939 | I58: ='Input - GNPA'!I22+'Input - GNPA'!I16*0.05 -> 898.97121 | J58: ='Input - GNPA'!J22+'Input - GNPA'!J16*0.05 -> 868.40691 | ... AM58: ='Input - GNPA'!AM22+'Input - GNPA'!AM16*0.05 -> 1324.6173 | BM58: =O58 -> 1047.6356 | BN58: =AA58 -> 1235.5033 | BO58: =AM58 -> 1324.6173
A59: =A58 -> NNPA (Stress)-CV | B59: LAP | C59: ='Input - GNPA'!C23+'Input - GNPA'!C17*0.05 -> 544.20065 | D59: ='Input - GNPA'!D23+'Input - GNPA'!D17*0.05 -> 599.95777 | E59: ='Input - GNPA'!E23+'Input - GNPA'!E17*0.05 -> 648.15154 | F59: ='Input - GNPA'!F23+'Input - GNPA'!F17*0.05 -> 694.34396 | G59: ='Input - GNPA'!G23+'Input - GNPA'!G17*0.05 -> 743.63996 | H59: ='Input - GNPA'!H23+'Input - GNPA'!H17*0.05 -> 792.60134 | I59: ='Input - GNPA'!I23+'Input - GNPA'!I17*0.05 -> 767.645 | J59: ='Input - GNPA'!J23+'Input - GNPA'!J17*0.05 -> 776.30187 | ... AM59: ='Input - GNPA'!AM23+'Input - GNPA'!AM17*0.05 -> 773.9465 | BM59: =O59 -> 799.28416 | BN59: =AA59 -> 880.22304 | BO59: =AM59 -> 773.9465
A60: =A59 -> NNPA (Stress)-CV | B60: DF | C60: ='Input - GNPA'!C24+'Input - GNPA'!C18*0.053 -> 0 | D60: ='Input - GNPA'!D24+'Input - GNPA'!D18*0.053 -> 9.1282293 | E60: ='Input - GNPA'!E24+'Input - GNPA'!E18*0.053 -> 8.7953381 | F60: ='Input - GNPA'!F24+'Input - GNPA'!F18*0.053 -> 8.4366006 | G60: ='Input - GNPA'!G24+'Input - GNPA'!G18*0.053 -> 8.0429968 | H60: ='Input - GNPA'!H24+'Input - GNPA'!H18*0.053 -> 7.6239753 | I60: ='Input - GNPA'!I24+'Input - GNPA'!I18*0.053 -> 7.2077783 | J60: ='Input - GNPA'!J24+'Input - GNPA'!J18*0.053 -> 6.7852091 | ... AM60: ='Input - GNPA'!AM24+'Input - GNPA'!AM18*0.053 -> 6.1248966 | BM60: =O60 -> 4.8894966 | BN60: =AA60 -> 3.156421 | BO60: =AM60 -> 6.1248966
A62: GNPA% - (Stress)-CV | B62: Inputs | C62: =C14 -> 45352 | D62: =EDATE(C62,1) -> 45383 | E62: =EDATE(D62,1) -> 45413 | F62: =EDATE(E62,1) -> 45444 | G62: =EDATE(F62,1) -> 45474 | H62: =EDATE(G62,1) -> 45505 | I62: =EDATE(H62,1) -> 45536 | J62: =EDATE(I62,1) -> 45566 | K62: =EDATE(J62,1) -> 45597 | ... BJ62: =EDATE(BI62,1) -> 47150 | BM62: =BM56 -> FY24 | BN62: =BN56 -> FY25 | BO62: =BO56 -> FY26
A63: =A62 -> GNPA% - (Stress)-CV | B63: SMHFC | C63: ='Input - GNPA'!C27 -> 0.026384549 | D63: ='Input - GNPA'!D27 -> 0.02746248 | E63: ='Input - GNPA'!E27 -> 0.028285877 | F63: ='Input - GNPA'!F27 -> 0.029039539 | G63: ='Input - GNPA'!G27 -> 0.029905123 | H63: ='Input - GNPA'!H27 -> 0.030647583 | I63: ='Input - GNPA'!I27 -> 0.030832674 | J63: ='Input - GNPA'!J27 -> 0.032021389 | ... AM63: ='Input - GNPA'!AM27 -> 0.023801644 | AN63: =SUM(AN64:AN66) -> 0 | AO63: =SUM(AO64:AO66) -> 0 | AP63: =SUM(AP64:AP66) -> 0 | AQ63: =SUM(AQ64:AQ66) -> 0 | AR63: =SUM(AR64:AR66) -> 0 | AS63: =SUM(AS64:AS66) -> 0 | AT63: =SUM(AT64:AT66) -> 0 | AU63: =SUM(AU64:AU66) -> 0 | ... BJ63: =SUM(BJ64:BJ66) -> 0 | BM63: =O63 -> 0.035715322 | BN63: =AA63 -> 0.037408138 | BO63: =AM63 -> 0.023801644
A64: =A63 -> GNPA% - (Stress)-CV | B64: HL | C64: ='Input - GNPA'!C28 -> 0.023654983 | D64: ='Input - GNPA'!D28 -> 0.024016592 | E64: ='Input - GNPA'!E28 -> 0.024272063 | F64: ='Input - GNPA'!F28 -> 0.02448959 | G64: ='Input - GNPA'!G28 -> 0.024848754 | H64: ='Input - GNPA'!H28 -> 0.025102688 | I64: ='Input - GNPA'!I28 -> 0.025384044 | J64: ='Input - GNPA'!J28 -> 0.026037858 | ... AM64: ='Input - GNPA'!AM28 -> 0.021453854 | BM64: =O64 -> 0.029237407 | BN64: =AA64 -> 0.030292121 | BO64: =AM64 -> 0.021453854
A65: =A64 -> GNPA% - (Stress)-CV | B65: LAP | C65: ='Input - GNPA'!C29 -> 0.044148124 | D65: ='Input - GNPA'!D29 -> 0.046252006 | E65: ='Input - GNPA'!E29 -> 0.048122222 | F65: ='Input - GNPA'!F29 -> 0.049818067 | G65: ='Input - GNPA'!G29 -> 0.051613199 | H65: ='Input - GNPA'!H29 -> 0.053206212 | I65: ='Input - GNPA'!I29 -> 0.054640677 | J65: ='Input - GNPA'!J29 -> 0.057014201 | ... AM65: ='Input - GNPA'!AM29 -> 0.039088141 | BM65: =O65 -> 0.067422113 | BN65: =AA65 -> 0.071581638 | BO65: =AM65 -> 0.039088141
A66: =A65 -> GNPA% - (Stress)-CV | B66: DF | C66: ='Input - GNPA'!C30 -> 0 | D66: ='Input - GNPA'!D30 -> 0.0012176982 | E66: ='Input - GNPA'!E30 -> 0.0012148573 | F66: ='Input - GNPA'!F30 -> 0.0012042321 | G66: ='Input - GNPA'!G30 -> 0.0011828723 | H66: ='Input - GNPA'!H30 -> 0.0011525643 | I66: ='Input - GNPA'!I30 -> 0.001118694 | J66: ='Input - GNPA'!J30 -> 0.0010823129 | ... AM66: ='Input - GNPA'!AM30 -> 0.00062364156 | BM66: =O66 -> 0.00089871262 | BN66: =AA66 -> 0.00073213063 | BO66: =AM66 -> 0.00062364156
A68: NNPA% - (Stress)-CV | B68: Inputs | C68: =C62 -> 45352 | D68: =EDATE(C68,1) -> 45383 | E68: =EDATE(D68,1) -> 45413 | F68: =EDATE(E68,1) -> 45444 | G68: =EDATE(F68,1) -> 45474 | H68: =EDATE(G68,1) -> 45505 | I68: =EDATE(H68,1) -> 45536 | J68: =EDATE(I68,1) -> 45566 | K68: =EDATE(J68,1) -> 45597 | ... BJ68: =EDATE(BI68,1) -> 47150 | BM68: =BM62 -> FY24 | BN68: =BN62 -> FY25 | BO68: =BO62 -> FY26
A69: =A68 -> NNPA% - (Stress)-CV | B69: SMHFC | C69: ='Input - GNPA'!C33 -> 0.016703051 | D69: ='Input - GNPA'!D33 -> 0.017403231 | E69: ='Input - GNPA'!E33 -> 0.018007107 | F69: ='Input - GNPA'!F33 -> 0.018559089 | G69: ='Input - GNPA'!G33 -> 0.019195282 | H69: ='Input - GNPA'!H33 -> 0.019757107 | I69: ='Input - GNPA'!I33 -> 0.01989363 | J69: ='Input - GNPA'!J33 -> 0.019405118 | ... AM69: ='Input - GNPA'!AM33 -> 0.01487465 | AN69: =SUM(AN70:AN72) -> 0 | AO69: =SUM(AO70:AO72) -> 0 | AP69: =SUM(AP70:AP72) -> 0 | AQ69: =SUM(AQ70:AQ72) -> 0 | AR69: =SUM(AR70:AR72) -> 0 | AS69: =SUM(AS70:AS72) -> 0 | AT69: =SUM(AT70:AT72) -> 0 | AU69: =SUM(AU70:AU72) -> 0 | ... BJ69: =SUM(BJ70:BJ72) -> 0 | BM69: =O69 -> 0.021573257 | BN69: =AA69 -> 0.02313496 | BO69: =AM69 -> 0.01487465
A70: =A69 -> NNPA% - (Stress)-CV | B70: HL | C70: ='Input - GNPA'!C34 -> 0.014600841 | D70: ='Input - GNPA'!D34 -> 0.014818428 | E70: ='Input - GNPA'!E34 -> 0.014986238 | F70: ='Input - GNPA'!F34 -> 0.015149235 | G70: ='Input - GNPA'!G34 -> 0.015414876 | H70: ='Input - GNPA'!H34 -> 0.015617758 | I70: ='Input - GNPA'!I34 -> 0.015837007 | J70: ='Input - GNPA'!J34 -> 0.015122789 | ... AM70: ='Input - GNPA'!AM34 -> 0.013061286 | BM70: =O70 -> 0.016938402 | BN70: =AA70 -> 0.018054692 | BO70: =AM70 -> 0.013061286
A71: =A70 -> NNPA% - (Stress)-CV | B71: LAP | C71: ='Input - GNPA'!C35 -> 0.029102133 | D71: ='Input - GNPA'!D35 -> 0.030190597 | E71: ='Input - GNPA'!E35 -> 0.031681711 | F71: ='Input - GNPA'!F35 -> 0.03297646 | G71: ='Input - GNPA'!G35 -> 0.034348982 | H71: ='Input - GNPA'!H35 -> 0.035593393 | I71: ='Input - GNPA'!I35 -> 0.036600921 | J71: ='Input - GNPA'!J35 -> 0.036188121 | ... AM71: ='Input - GNPA'!AM35 -> 0.025511848 | BM71: =O71 -> 0.043031738 | BN71: =AA71 -> 0.046676748 | BO71: =AM71 -> 0.025511848
A72: =A71 -> NNPA% - (Stress)-CV | B72: DF | C72: ='Input - GNPA'!C36 -> 0 | D72: ='Input - GNPA'!D36 -> 0.0012176982 | E72: ='Input - GNPA'!E36 -> 0.0012148573 | F72: ='Input - GNPA'!F36 -> 0.0012042321 | G72: ='Input - GNPA'!G36 -> 0.0011828723 | H72: ='Input - GNPA'!H36 -> 0.0011525643 | I72: ='Input - GNPA'!I36 -> 0.001118694 | J72: ='Input - GNPA'!J36 -> 0.0010823129 | ... AM72: ='Input - GNPA'!AM36 -> 0.00062364156 | BM72: =O72 -> 0.00089871262 | BN72: =AA72 -> 0.00073213063 | BO72: =AM72 -> 0.00062364156

Sheet Output - CoC
D1: Plan | H1: Stress | L1: Variance
B2: Product | C2: Parameter | D2: SL1 | E2: SL2 | F2: SL3 | H2: SL1 | I2: SL2 | J2: SL3 | L2: SL1 | M2: SL2 | N2: SL3
B3: SMHFC | C3: NCL | D3: =SUM(D7,D11,D15) -> 197.57232 | E3: =SUM(E7,E11,E15) -> 601.9846 | F3: =SUM(F7,F11,F15) -> 542.51289 | H3: =SUM(H7,H11,H15) -> 198.18764 | I3: =SUM(I7,I11,I15) -> 680.59102 | J3: =SUM(J7,J11,J15) -> 733.41637 | L3: =H3-D3 -> 0.61531716 | M3: =I3-E3 -> 78.60642 | N3: =J3-F3 -> 190.90348
B4: =B3 -> SMHFC | C4: ECL | D4: =SUM(D8,D12,D16) -> 124.14199 | E4: =SUM(E8,E12,E16) -> 160.88567 | F4: =SUM(F8,F12,F16) -> 340.22178 | H4: =SUM(H8,H12,H16) -> 272.44621 | I4: =SUM(I8,I12,I16) -> 542.14004 | J4: =SUM(J8,J12,J16) -> -298.04612 | L4: =H4-D4 -> 148.30422 | M4: =I4-E4 -> 381.25437 | N4: =J4-F4 -> -638.2679
B5: =B3 -> SMHFC | C5: CoC | D5: =SUM(D9,D13,D17) -> 321.71431 | E5: =SUM(E9,E13,E17) -> 762.87027 | F5: =SUM(F9,F13,F17) -> 882.73467 | H5: =SUM(H9,H13,H17) -> 470.63385 | I5: =SUM(I9,I13,I17) -> 1222.7311 | J5: =SUM(J9,J13,J17) -> 435.37025 | L5: =H5-D5 -> 148.91954 | M5: =I5-E5 -> 459.86079 | N5: =J5-F5 -> -447.36442
B7: HL | C7: NCL | D7: =SUMIF('Calculation - NCL and ECL'!$E$1:$AN$1,$D$2,'Calculation - NCL and ECL'!$E7:$AN7) -> 107.03862 | E7: =SUMIF('Calculation - NCL and ECL'!$E$1:$AN$1,$E$2,'Calculation - NCL and ECL'!$E7:$AN7) -> 299.21568 | F7: =SUMIF('Calculation - NCL and ECL'!$E$1:$AN$1,$F$2,'Calculation - NCL and ECL'!$E7:$AN7) -> 378.03543 | H7: =SUMIF('Calculation - NCL and ECL'!$E$1:$AN$1,$H$2,'Calculation - NCL and ECL'!$E16:$AN16) -> 108.28747 | I7: =SUMIF('Calculation - NCL and ECL'!$E$1:$AN$1,$I$2,'Calculation - NCL and ECL'!$E16:$AN16) -> 346.0241 | J7: =SUMIF('Calculation - NCL and ECL'!$E$1:$AN$1,$J$2,'Calculation - NCL and ECL'!$E16:$AN16) -> 529.10787 | L7: =H7-D7 -> 1.2488542 | M7: =I7-E7 -> 46.808421 | N7: =J7-F7 -> 151.07244
B8: =B7 -> HL | C8: ECL | D8: =SUMIF('Calculation - NCL and ECL'!$E$1:$AN$1,$D$2,'Calculation - NCL and ECL'!$E19:$AN19)+SUMIF('Calculation - NCL and ECL'!$E$1:$AN$1,$D$2,'Calculation - NCL and ECL'!$E37:$AN37) -> 105.34106 | E8: =SUMIF('Calculation - NCL and ECL'!$E$1:$AN$1,$E$2,'Calculation - NCL and ECL'!$E19:$AN19)+SUMIF('Calculation - NCL and ECL'!$E$1:$AN$1,$E$2,'Calculation - NCL and ECL'!$E37:$AN37) -> 201.29442 | F8: =SUMIF('Calculation - NCL and ECL'!$E$1:$AN$1,$F$2,'Calculation - NCL and ECL'!$E19:$AN19)+SUMIF('Calculation - NCL and ECL'!$E$1:$AN$1,$F$2,'Calculation - NCL and ECL'!$E37:$AN37) -> 277.89183 | H8: =SUMIF('Calculation - NCL and ECL'!$E$1:$AN$1,$H$2,'Calculation - NCL and ECL'!$E22:$AN22)+SUMIF('Calculation - NCL and ECL'!$E$1:$AN$1,$H$2,'Calculation - NCL and ECL'!$E37:$AN37) -> 172.26822 | I8: =SUMIF('Calculation - NCL and ECL'!$E$1:$AN$1,$E$2,'Calculation - NCL and ECL'!$E22:$AN22)+SUMIF('Calculation - NCL and ECL'!$E$1:$AN$1,$E$2,'Calculation - NCL and ECL'!$E37:$AN37) -> 389.62508 | J8: =SUMIF('Calculation - NCL and ECL'!$E$1:$AN$1,$F$2,'Calculation - NCL and ECL'!$E22:$AN22)+SUMIF('Calculation - NCL and ECL'!$E$1:$AN$1,$F$2,'Calculation - NCL and ECL'!$E37:$AN37) -> -130.82361 | L8: =H8-D8 -> 66.927163 | M8: =I8-E8 -> 188.33067 | N8: =J8-F8 -> -408.71543
B9: =B7 -> HL | C9: CoC | D9: =SUM(D7:D8) -> 212.37968 | E9: =SUM(E7:E8) -> 500.5101 | F9: =SUM(F7:F8) -> 655.92726 | H9: =SUM(H7:H8) -> 280.55569 | I9: =SUM(I7:I8) -> 735.64919 | J9: =SUM(J7:J8) -> 398.28427 | L9: =H9-D9 -> 68.176017 | M9: =I9-E9 -> 235.13909 | N9: =J9-F9 -> -257.64299
B11: LAP | C11: NCL | D11: =SUMIF('Calculation - NCL and ECL'!$E$1:$AN$1,$D$2,'Calculation - NCL and ECL'!$E8:$AN8) -> 90.533704 | E11: =SUMIF('Calculation - NCL and ECL'!$E$1:$AN$1,$E$2,'Calculation - NCL and ECL'!$E8:$AN8) -> 302.76892 | F11: =SUMIF('Calculation - NCL and ECL'!$E$1:$AN$1,$F$2,'Calculation - NCL and ECL'!$E8:$AN8) -> 164.47746 | H11: =SUMIF('Calculation - NCL and ECL'!$E$1:$AN$1,$H$2,'Calculation - NCL and ECL'!$E17:$AN17) -> 89.900167 | I11: =SUMIF('Calculation - NCL and ECL'!$E$1:$AN$1,$I$2,'Calculation - NCL and ECL'!$E17:$AN17) -> 334.56692 | J11: =SUMIF('Calculation - NCL and ECL'!$E$1:$AN$1,$J$2,'Calculation - NCL and ECL'!$E17:$AN17) -> 204.3085 | L11: =H11-D11 -> -0.63353703 | M11: =I11-E11 -> 31.797999 | N11: =J11-F11 -> 39.831036
B12: =B11 -> LAP | C12: ECL | D12: =SUMIF('Calculation - NCL and ECL'!$E$1:$AN$1,$D$2,'Calculation - NCL and ECL'!$E20:$AN20)+SUMIF('Calculation - NCL and ECL'!$E$1:$AN$1,$D$2,'Calculation - NCL and ECL'!$E38:$AN38) -> 12.445883 | E12: =SUMIF('Calculation - NCL and ECL'!$E$1:$AN$1,$E$2,'Calculation - NCL and ECL'!$E20:$AN20)+SUMIF('Calculation - NCL and ECL'!$E$1:$AN$1,$E$2,'Calculation - NCL and ECL'!$E38:$AN38) -> -63.456252 | F12: =SUMIF('Calculation - NCL and ECL'!$E$1:$AN$1,$F$2,'Calculation - NCL and ECL'!$E20:$AN20)+SUMIF('Calculation - NCL and ECL'!$E$1:$AN$1,$F$2,'Calculation - NCL and ECL'!$E38:$AN38) -> 41.42075 | H12: =SUMIF('Calculation - NCL and ECL'!$E$1:$AN$1,$H$2,'Calculation - NCL and ECL'!$E23:$AN23)+SUMIF('Calculation - NCL and ECL'!$E$1:$AN$1,$H$2,'Calculation - NCL and ECL'!$E38:$AN38) -> 112.40271 | I12: =SUMIF('Calculation - NCL and ECL'!$E$1:$AN$1,$E$2,'Calculation - NCL and ECL'!$E23:$AN23)+SUMIF('Calculation - NCL and ECL'!$E$1:$AN$1,$E$2,'Calculation - NCL and ECL'!$E38:$AN38) -> 177.45645 | J12: =SUMIF('Calculation - NCL and ECL'!$E$1:$AN$1,$F$2,'Calculation - NCL and ECL'!$E23:$AN23)+SUMIF('Calculation - NCL and ECL'!$E$1:$AN$1,$F$2,'Calculation - NCL and ECL'!$E38:$AN38) -> -178.9301 | L12: =H12-D12 -> 99.956829 | M12: =I12-E12 -> 240.9127 | N12: =J12-F12 -> -220.35085
B13: =B11 -> LAP | C13: CoC | D13: =SUM(D11:D12) -> 102.97959 | E13: =SUM(E11:E12) -> 239.31267 | F13: =SUM(F11:F12) -> 205.89821 | H13: =SUM(H11:H12) -> 202.30288 | I13: =SUM(I11:I12) -> 512.02336 | J13: =SUM(J11:J12) -> 25.378405 | L13: =H13-D13 -> 99.323292 | M13: =I13-E13 -> 272.7107 | N13: =J13-F13 -> -180.51981
B15: DF | C15: NCL | D15: =SUMIF('Calculation - NCL and ECL'!$E$1:$AN$1,$D$2,'Calculation - NCL and ECL'!$E9:$AN9) -> 0 | E15: =SUMIF('Calculation - NCL and ECL'!$E$1:$AN$1,$E$2,'Calculation - NCL and ECL'!$E9:$AN9) -> 0 | F15: =SUMIF('Calculation - NCL and ECL'!$E$1:$AN$1,$F$2,'Calculation - NCL and ECL'!$E9:$AN9) -> 0 | H15: =IFERROR(SUMIF('Calculation - NCL and ECL'!$E$1:$AN$1,$H$2,'Calculation - NCL and ECL'!$E18:$AN18),0) -> 0 | I15: =IFERROR(SUMIF('Calculation - NCL and ECL'!$E$1:$AN$1,$H$2,'Calculation - NCL and ECL'!$E18:$AN18),0) -> 0 | J15: =IFERROR(SUMIF('Calculation - NCL and ECL'!$E$1:$AN$1,$H$2,'Calculation - NCL and ECL'!$E18:$AN18),0) -> 0 | L15: =H15-D15 -> 0 | M15: =I15-E15 -> 0 | N15: =J15-F15 -> 0
B16: =B15 -> DF | C16: ECL | D16: =SUMIF('Calculation - NCL and ECL'!$E$1:$AN$1,$D$2,'Calculation - NCL and ECL'!$E21:$AN21)+SUMIF('Calculation - NCL and ECL'!$E$1:$AN$1,$D$2,'Calculation - NCL and ECL'!$E39:$AN39) -> 6.3550475 | E16: =SUMIF('Calculation - NCL and ECL'!$E$1:$AN$1,$E$2,'Calculation - NCL and ECL'!$E21:$AN21)+SUMIF('Calculation - NCL and ECL'!$E$1:$AN$1,$E$2,'Calculation - NCL and ECL'!$E39:$AN39) -> 23.047506 | F16: =SUMIF('Calculation - NCL and ECL'!$E$1:$AN$1,$F$2,'Calculation - NCL and ECL'!$E21:$AN21)+SUMIF('Calculation - NCL and ECL'!$E$1:$AN$1,$F$2,'Calculation - NCL and ECL'!$E39:$AN39) -> 20.9092 | H16: =IFERROR(SUMIF('Calculation - NCL and ECL'!$E$1:$AN$1,$H$2,'Calculation - NCL and ECL'!$E24:$AN24),0)+IFERROR(SUMIF('Calculation - NCL and ECL'!$E$1:$AN$1,$H$2,'Calculation - NCL and ECL'!$E39:$AN39),0) -> -12.224719 | I16: =IFERROR(SUMIF('Calculation - NCL and ECL'!$E$1:$AN$1,$E$2,'Calculation - NCL and ECL'!$E24:$AN24),0)+IFERROR(SUMIF('Calculation - NCL and ECL'!$E$1:$AN$1,$E$2,'Calculation - NCL and ECL'!$E39:$AN39),0) -> -24.94149 | J16: =IFERROR(SUMIF('Calculation - NCL and ECL'!$E$1:$AN$1,$F$2,'Calculation - NCL and ECL'!$E24:$AN24),0)+IFERROR(SUMIF('Calculation - NCL and ECL'!$E$1:$AN$1,$F$2,'Calculation - NCL and ECL'!$E39:$AN39),0) -> 11.707581 | L16: =H16-D16 -> -18.579767 | M16: =I16-E16 -> -47.988995 | N16: =J16-F16 -> -9.201619
B17: =B15 -> DF | C17: CoC | D17: =SUM(D15:D16) -> 6.3550475 | E17: =SUM(E15:E16) -> 23.047506 | F17: =SUM(F15:F16) -> 20.9092 | H17: =SUM(H15:H16) -> -12.224719 | I17: =SUM(I15:I16) -> -24.94149 | J17: =SUM(J15:J16) -> 11.707581 | L17: =H17-D17 -> -18.579767 | M17: =I17-E17 -> -47.988995 | N17: =J17-F17 -> -9.201619

Sheet Input-Stress Parameters
B1: Back - Index | T1: `
B2: Plan Start Month>> | C2: 45352
B3: Stress Start Month>> | C3: 45383
B4: Stress Levels | C4: SL1 | D4: SL2 | E4: SL3 | K4: BOM | L4: EOM
C5: 7 | D5: 25 | E5: 5 | G5: Slowdown | H5: SL1 Duration (in months) | J5: 6 | K5: =C3 -> 45383 | L5: =EDATE(K5,(J5-1)) -> 45536
G6: Recession | H6: SL2 Duration (in months) | J6: 12 | K6: =EDATE(L5,1) -> 45566 | L6: =EDATE(K6,(J6-1)) -> 45901
G7: Recovery | H7: SL3 Duration (in months) | J7: 12 | K7: =EDATE(L6,1) -> 45931 | L7: =EDATE(K7,(J7-1)) -> 46266
B8: =EOMONTH(TODAY(),-1)+1 -> 45444
B9: Parameters | C9: =C2 -> 45352 | D9: =EDATE(C9,1) -> 45383 | E9: =EDATE(D9,1) -> 45413 | F9: =EDATE(E9,1) -> 45444 | G9: =EDATE(F9,1) -> 45474 | H9: =EDATE(G9,1) -> 45505 | I9: =EDATE(H9,1) -> 45536 | J9: =EDATE(I9,1) -> 45566 | K9: =EDATE(J9,1) -> 45597 | ... BJ9: =EDATE(BI9,1) -> 47150
B10: Stress Level | C10: =IF(C9<$K$5,1,IF(C9>$L$5,IF(C9>$L$6,IF(C9>$L$7,1,$E$5),$D$5),$C$5)) -> 1 | D10: =IF(D9<$K$5,1,IF(D9>$L$5,IF(D9>$L$6,IF(D9>$L$7,1,$E$5),$D$5),$C$5)) -> 7 | E10: =IF(E9<$K$5,1,IF(E9>$L$5,IF(E9>$L$6,IF(E9>$L$7,1,$E$5),$D$5),$C$5)) -> 7 | F10: =IF(F9<$K$5,1,IF(F9>$L$5,IF(F9>$L$6,IF(F9>$L$7,1,$E$5),$D$5),$C$5)) -> 7 | G10: =IF(G9<$K$5,1,IF(G9>$L$5,IF(G9>$L$6,IF(G9>$L$7,1,$E$5),$D$5),$C$5)) -> 7 | H10: =IF(H9<$K$5,1,IF(H9>$L$5,IF(H9>$L$6,IF(H9>$L$7,1,$E$5),$D$5),$C$5)) -> 7 | I10: =IF(I9<$K$5,1,IF(I9>$L$5,IF(I9>$L$6,IF(I9>$L$7,1,$E$5),$D$5),$C$5)) -> 7 | J10: =IF(J9<$K$5,1,IF(J9>$L$5,IF(J9>$L$6,IF(J9>$L$7,1,$E$5),$D$5),$C$5)) -> 25 | ... BJ10: =IF(BJ9<$K$5,1,IF(BJ9>$L$5,IF(BJ9>$L$6,IF(BJ9>$L$7,1,$E$5),$D$5),$C$5)) -> 1
B11: Stress stage | C11: =IF(C10=$C$5,$C$4,IF(C10=$D$5,$D$4,IF(C10=$E$5,$E$4,"N"))) -> N | D11: =IF(D10=$C$5,$C$4,IF(D10=$D$5,$D$4,IF(D10=$E$5,$E$4,"N"))) -> SL1 | E11: =IF(E10=$C$5,$C$4,IF(E10=$D$5,$D$4,IF(E10=$E$5,$E$4,"N"))) -> SL1 | F11: =IF(F10=$C$5,$C$4,IF(F10=$D$5,$D$4,IF(F10=$E$5,$E$4,"N"))) -> SL1 | G11: =IF(G10=$C$5,$C$4,IF(G10=$D$5,$D$4,IF(G10=$E$5,$E$4,"N"))) -> SL1 | H11: =IF(H10=$C$5,$C$4,IF(H10=$D$5,$D$4,IF(H10=$E$5,$E$4,"N"))) -> SL1 | I11: =IF(I10=$C$5,$C$4,IF(I10=$D$5,$D$4,IF(I10=$E$5,$E$4,"N"))) -> SL1 | J11: =IF(J10=$C$5,$C$4,IF(J10=$D$5,$D$4,IF(J10=$E$5,$E$4,"N"))) -> SL2 | ... BJ11: =IF(BJ10=$C$5,$C$4,IF(BJ10=$D$5,$D$4,IF(BJ10=$E$5,$E$4,"N"))) -> N
B12: Stress tag | C12: =IF(C11="N",C11,IF(C9>$B$17,"SL4P",IF(C9>$B$16,"SL3P",IF(C9>$B$15,"SL2P","SL1P")))) -> N | D12: =IF(D11="N",D11,IF(D9>$B$17,"SL4P",IF(D9>$B$16,"SL3P",IF(D9>$B$15,"SL2P","SL1P")))) -> SL1P | E12: =IF(E11="N",E11,IF(E9>$B$17,"SL4P",IF(E9>$B$16,"SL3P",IF(E9>$B$15,"SL2P","SL1P")))) -> SL1P | F12: =IF(F11="N",F11,IF(F9>$B$17,"SL4P",IF(F9>$B$16,"SL3P",IF(F9>$B$15,"SL2P","SL1P")))) -> SL1P | G12: =IF(G11="N",G11,IF(G9>$B$17,"SL4P",IF(G9>$B$16,"SL3P",IF(G9>$B$15,"SL2P","SL1P")))) -> SL1P | H12: =IF(H11="N",H11,IF(H9>$B$17,"SL4P",IF(H9>$B$16,"SL3P",IF(H9>$B$15,"SL2P","SL1P")))) -> SL1P | I12: =IF(I11="N",I11,IF(I9>$B$17,"SL4P",IF(I9>$B$16,"SL3P",IF(I9>$B$15,"SL2P","SL1P")))) -> SL1P | J12: =IF(J11="N",J11,IF(J9>$B$17,"SL4P",IF(J9>$B$16,"SL3P",IF(J9>$B$15,"SL2P","SL1P")))) -> SL2P | ... Z12: =IF(Z11="N",Z11,IF(Z9>$B$17,"SL4P",IF(Z9>$B$16,"SL3P",IF(Z9>$B$15,"SL2P","SL1P")))) -> SL4P | AA12: =IF(AA11="N",AA11,IF(AA9>$B$19,"SL4P",IF(AA9>$B$16,"SL3P",IF(AA9>$B$15,"SL2P","SL1P")))) -> SL3P | AB12: =IF(AB11="N",AB11,IF(AB9>$B$19,"SL4P",IF(AB9>$B$16,"SL3P",IF(AB9>$B$15,"SL2P","SL1P")))) -> SL3P | AC12: =IF(AC11="N",AC11,IF(AC9>$B$19,"SL4P",IF(AC9>$B$16,"SL3P",IF(AC9>$B$15,"SL2P","SL1P")))) -> SL3P | AD12: =IF(AD11="N",AD11,IF(AD9>$B$19,"SL4P",IF(AD9>$B$16,"SL3P",IF(AD9>$B$15,"SL2P","SL1P")))) -> SL3P | AE12: =IF(AE11="N",AE11,IF(AE9>$B$19,"SL4P",IF(AE9>$B$16,"SL3P",IF(AE9>$B$15,"SL2P","SL1P")))) -> SL3P | AF12: =IF(AF11="N",AF11,IF(AF9>$B$19,"SL4P",IF(AF9>$B$16,"SL3P",IF(AF9>$B$15,"SL2P","SL1P")))) -> SL3P | AG12: =IF(AG11="N",AG11,IF(AG9>$B$19,"SL4P",IF(AG9>$B$16,"SL3P",IF(AG9>$B$15,"SL2P","SL1P")))) -> SL3P | AH12: =IF(AH11="N",AH11,IF(AH9>$B$19,"SL4P",IF(AH9>$B$16,"SL3P",IF(AH9>$B$15,"SL2P","SL1P")))) -> N | ... AL12: =IF(AL11="N",AL11,IF(AL9>$B$19,"SL4P",IF(AL9>$B$16,"SL3P",IF(AL9>$B$15,"SL2P","SL1P")))) -> N | AM12: =IF(AM11="N",AM11,IF(AM9>$B$17,"SL4P",IF(AM9>$B$16,"SL3P",IF(AM9>$B$15,"SL2P","SL1P")))) -> N | AN12: =IF(AN11="N",AN11,IF(AN9>$B$17,"SL4P",IF(AN9>$B$16,"SL3P",IF(AN9>$B$15,"SL2P","SL1P")))) -> N | AO12: =IF(AO11="N",AO11,IF(AO9>$B$17,"SL4P",IF(AO9>$B$16,"SL3P",IF(AO9>$B$15,"SL2P","SL1P")))) -> N | AP12: =IF(AP11="N",AP11,IF(AP9>$B$17,"SL4P",IF(AP9>$B$16,"SL3P",IF(AP9>$B$15,"SL2P","SL1P")))) -> N | AQ12: =IF(AQ11="N",AQ11,IF(AQ9>$B$17,"SL4P",IF(AQ9>$B$16,"SL3P",IF(AQ9>$B$15,"SL2P","SL1P")))) -> N | AR12: =IF(AR11="N",AR11,IF(AR9>$B$17,"SL4P",IF(AR9>$B$16,"SL3P",IF(AR9>$B$15,"SL2P","SL1P")))) -> N | AS12: =IF(AS11="N",AS11,IF(AS9>$B$17,"SL4P",IF(AS9>$B$16,"SL3P",IF(AS9>$B$15,"SL2P","SL1P")))) -> N | AT12: =IF(AT11="N",AT11,IF(AT9>$B$17,"SL4P",IF(AT9>$B$16,"SL3P",IF(AT9>$B$15,"SL2P","SL1P")))) -> N | ... BJ12: =IF(BJ11="N",BJ11,IF(BJ9>$B$17,"SL4P",IF(BJ9>$B$16,"SL3P",IF(BJ9>$B$15,"SL2P","SL1P")))) -> N
F14: 1 | G14: =F14+1 -> 2 | H14: =G14+1 -> 3 | I14: =H14+1 -> 4 | J14: =I14+1 -> 5 | K14: =J14+1 -> 6 | L14: =K14+1 -> 7 | M14: =L14+1 -> 8 | N14: =M14+1 -> 9 | ... AC14: =AB14+1 -> 24
B15: =EDATE(K5,(D15-1)) -> 45536 | C15: SL1P | D15: 6
B16: =EDATE(K5,(D16-1)) -> 45901 | C16: SL2P | D16: 18 | E16: =D16-D15 -> 12
B17: =EDATE(K5,(D17-1)) -> 45992 | C17: SL3P | D17: 21 | E17: =D17-D16 -> 3
B18: Secured | E18: =SUM(J5:J7)-D17 -> 9
B19: =EDATE(K5,(D19-1)) -> 46631 | C19: SL3P | D19: 42 | E19: 24
D20: =_xlfn.IFNA(VLOOKUP(D9,$B$15:$C$17,2,),D11) -> SL1
B24: Recovery | C24: SL31 Duration (in months) | E24: =J7/2 -> 6 | F24: =K7 -> 45931 | G24: =EDATE(F24,(E24-1)) -> 46082 | H24: SL31
B25: Recovery | C25: SL32 Duration (in months) | E25: =J7/2 -> 6 | F25: =EDATE(G24,1) -> 46113 | G25: =EDATE(F25,(E25-1)) -> 46266 | H25: SL32
B27: Parameters | C27: =C2 -> 45352 | D27: =EDATE(C27,1) -> 45383 | E27: =EDATE(D27,1) -> 45413 | F27: =EDATE(E27,1) -> 45444 | G27: =EDATE(F27,1) -> 45474 | H27: =EDATE(G27,1) -> 45505 | I27: =EDATE(H27,1) -> 45536 | J27: =EDATE(I27,1) -> 45566 | K27: =EDATE(J27,1) -> 45597 | ... BJ27: =EDATE(BI27,1) -> 47150
B28: Stress stage | C28: =IF(C27>=$F$24,IF(C27<=$G$24,$H$24,IF(C27>=$F$25,IF(C27<=$G$25,$H$25,C11))),C11) -> N | D28: =IF(D27>=$F$24,IF(D27<=$G$24,$H$24,IF(D27>=$F$25,IF(D27<=$G$25,$H$25,D11))),D11) -> SL1 | E28: =IF(E27>=$F$24,IF(E27<=$G$24,$H$24,IF(E27>=$F$25,IF(E27<=$G$25,$H$25,E11))),E11) -> SL1 | F28: =IF(F27>=$F$24,IF(F27<=$G$24,$H$24,IF(F27>=$F$25,IF(F27<=$G$25,$H$25,F11))),F11) -> SL1 | G28: =IF(G27>=$F$24,IF(G27<=$G$24,$H$24,IF(G27>=$F$25,IF(G27<=$G$25,$H$25,G11))),G11) -> SL1 | H28: =IF(H27>=$F$24,IF(H27<=$G$24,$H$24,IF(H27>=$F$25,IF(H27<=$G$25,$H$25,H11))),H11) -> SL1 | I28: =IF(I27>=$F$24,IF(I27<=$G$24,$H$24,IF(I27>=$F$25,IF(I27<=$G$25,$H$25,I11))),I11) -> SL1 | J28: =IF(J27>=$F$24,IF(J27<=$G$24,$H$24,IF(J27>=$F$25,IF(J27<=$G$25,$H$25,J11))),J11) -> SL2 | ... BJ28: =IF(BJ27>=$F$24,IF(BJ27<=$G$24,$H$24,IF(BJ27>=$F$25,IF(BJ27<=$G$25,$H$25,BJ11))),BJ11) -> N

Sheet Input - Disbursals
A1: Back - Index | C1: =LOOKUP(C2,'Input-Stress Parameters'!$C$9:$BJ$9,'Input-Stress Parameters'!$C$11:$BJ$11) -> N | D1: =LOOKUP(D2,'Input-Stress Parameters'!$C$9:$BJ$9,'Input-Stress Parameters'!$C$11:$BJ$11) -> SL1 | E1: =LOOKUP(E2,'Input-Stress Parameters'!$C$9:$BJ$9,'Input-Stress Parameters'!$C$11:$BJ$11) -> SL1 | F1: =LOOKUP(F2,'Input-Stress Parameters'!$C$9:$BJ$9,'Input-Stress Parameters'!$C$11:$BJ$11) -> SL1 | G1: =LOOKUP(G2,'Input-Stress Parameters'!$C$9:$BJ$9,'Input-Stress Parameters'!$C$11:$BJ$11) -> SL1 | H1: =LOOKUP(H2,'Input-Stress Parameters'!$C$9:$BJ$9,'Input-Stress Parameters'!$C$11:$BJ$11) -> SL1 | I1: =LOOKUP(I2,'Input-Stress Parameters'!$C$9:$BJ$9,'Input-Stress Parameters'!$C$11:$BJ$11) -> SL1 | J1: =LOOKUP(J2,'Input-Stress Parameters'!$C$9:$BJ$9,'Input-Stress Parameters'!$C$11:$BJ$11) -> SL2 | ... BJ1: =LOOKUP(BJ2,'Input-Stress Parameters'!$C$9:$BJ$9,'Input-Stress Parameters'!$C$11:$BJ$11) -> N
A2: Disbursals - Stress | B2: Inputs | C2: ='Input-Stress Parameters'!C9 -> 45352 | D2: =EDATE(C2,1) -> 45383 | E2: =EDATE(D2,1) -> 45413 | F2: =EDATE(E2,1) -> 45444 | G2: =EDATE(F2,1) -> 45474 | H2: =EDATE(G2,1) -> 45505 | I2: =EDATE(H2,1) -> 45536 | J2: =EDATE(I2,1) -> 45566 | K2: =EDATE(J2,1) -> 45597 | ... BJ2: =EDATE(BI2,1) -> 47150
A3: Disbursals - Stress | B3: SMHFC | C3: =SUM(C4:C6) -> 4986.6667 | D3: =SUM(D4:D6) -> 2255 | E3: =SUM(E4:E6) -> 2402.5 | F3: =SUM(F4:F6) -> 2494 | G3: =SUM(G4:G6) -> 2550.65 | H3: =SUM(H4:H6) -> 2688 | I3: =SUM(I4:I6) -> 2780.125 | J3: =SUM(J4:J6) -> 2540 | ... BJ3: =SUM(BJ4:BJ6) -> 0
A4: Disbursals - Stress | B4: HL | C4: 2975 | D4: 1421 | E4: 1524.25 | F4: 1584.1 | G4: 1614.83 | H4: 1705.2 | I4: 1768.9 | J4: 1610 | K4: 1764 | L4: 1851.5 | M4: 1775.9 | N4: 1713.95 | O4: 1764 | P4: 945.70173 | Q4: 1049.8856 | R4: 1097.5307 | S4: 1126.033 | T4: 1215.9022 | U4: 1287.4757 | V4: 1402.6709 | W4: 1778.7493 | X4: 2142.9694 | Y4: 2398.7705 | Z4: 2598.6681 | AA4: 2988.2989 | AB4: 1742.2284 | AC4: 2192.5605 | AD4: 2585.0137 | AE4: 2979.2252 | AF4: 3548.1969 | AG4: 4199.2735 | AH4: 4493.5524 | AI4: 5128.5109 | AJ4: 5616.9405 | AK4: 5763.4694 | AL4: 5763.4694 | AM4: 6154.213
A5: Disbursals - Stress | B5: LAP | C5: 1275 | D5: 609 | E5: 653.25 | F5: 678.9 | G5: 692.07 | H5: 730.8 | I5: 758.1 | J5: 690 | K5: 756 | L5: 793.5 | M5: 761.1 | N5: 734.55 | O5: 756 | P5: 405.30074 | Q5: 449.95098 | R5: 470.3703 | S5: 482.58559 | T5: 521.10095 | U5: 551.7753 | V5: 601.14467 | W5: 762.32114 | X5: 918.41547 | Y5: 1028.0445 | Z5: 1113.7149 | AA5: 1280.6995 | AB5: 746.66932 | AC5: 939.66879 | AD5: 1107.863 | AE5: 1276.8108 | AF5: 1520.6558 | AG5: 1799.6887 | AH5: 1925.8082 | AI5: 2197.9332 | AJ5: 2407.2602 | AK5: 2470.0583 | AL5: 2470.0583 | AM5: 2637.5199
A6: Disbursals - Stress | B6: DF | C6: 736.66667 | D6: 225 | E6: 225 | F6: 231 | G6: 243.75 | H6: 252 | I6: 253.125 | J6: 240 | K6: 213.6 | L6: 221 | M6: 207 | N6: 198.875 | O6: 230 | P6: 97.125 | Q6: 99.166667 | R6: 99.458333 | S6: 102.08333 | T6: 106.16667 | U6: 105 | V6: 149.33333 | W6: 186.66667 | X6: 238 | Y6: 294 | Z6: 345.33333 | AA6: 483 | AB6: 262.8 | AC6: 313.33333 | AD6: 385 | AE6: 483.33333 | AF6: 592.66667 | AG6: 705 | AH6: 1066.6667 | AI6: 1066.6667 | AJ6: 1133.3333 | AK6: 1200 | AL6: 1233.3333 | AM6: 1533.3333
A8: Disbursals - Plan | B8: Plan | C8: =C2 -> 45352 | D8: =EDATE(C8,1) -> 45383 | E8: =EDATE(D8,1) -> 45413 | F8: =EDATE(E8,1) -> 45444 | G8: =EDATE(F8,1) -> 45474 | H8: =EDATE(G8,1) -> 45505 | I8: =EDATE(H8,1) -> 45536 | J8: =EDATE(I8,1) -> 45566 | K8: =EDATE(J8,1) -> 45597 | ... BJ8: =EDATE(BI8,1) -> 47150
A9: Disbursals - Plan | B9: SMHFC | C9: =SUM(C10:C12) -> 4986.6667 | D9: =SUM(D10:D12) -> 3350 | E9: =SUM(E10:E12) -> 3850 | F9: =SUM(F10:F12) -> 4200 | G9: =SUM(G10:G12) -> 4535 | H9: =SUM(H10:H12) -> 5050 | I9: =SUM(I10:I12) -> 5500 | J9: =SUM(J10:J12) -> 5400 | ... BJ9: =SUM(BJ10:BJ12) -> 0
A10: Disbursals - Plan | B10: HL | C10: 2975 | D10: 2030 | E10: 2345 | F10: 2555 | G10: 2737 | H10: 3045 | I10: 3325 | J10: 3220 | K10: 3675 | L10: 4025 | M10: 4130 | N10: 4130 | O10: 4410 | P10: 2456.3681 | Q10: 2837.5287 | R10: 3091.6358 | S10: 3311.8619 | T10: 3684.5522 | U10: 4023.3616 | V10: 3896.3081 | W10: 4446.8733 | X10: 4870.3851 | Y10: 4997.4386 | Z10: 4997.4386 | AA10: 5336.248 | AB10: 2832.8917 | AC10: 3272.4784 | AD10: 3565.5361 | AE10: 3819.5195 | AF10: 4249.3376 | AG10: 4640.0813 | AH10: 4493.5524 | AI10: 5128.5109 | AJ10: 5616.9405 | AK10: 5763.4694 | AL10: 5763.4694 | AM10: 6154.213
A11: Disbursals - Plan | B11: LAP | C11: 1275 | D11: 870 | E11: 1005 | F11: 1095 | G11: 1173 | H11: 1305 | I11: 1425 | J11: 1380 | K11: 1575 | L11: 1725 | M11: 1770 | N11: 1770 | O11: 1890 | P11: 1052.7292 | Q11: 1216.0837 | R11: 1324.9868 | S11: 1419.3694 | T11: 1579.0938 | U11: 1724.2978 | V11: 1669.8463 | W11: 1905.8029 | X11: 2087.3079 | Y11: 2141.7594 | Z11: 2141.7594 | AA11: 2286.9634 | AB11: 1214.0964 | AC11: 1402.4907 | AD11: 1528.0869 | AE11: 1636.9369 | AF11: 1821.1447 | AG11: 1988.6063 | AH11: 1925.8082 | AI11: 2197.9332 | AJ11: 2407.2602 | AK11: 2470.0583 | AL11: 2470.0583 | AM11: 2637.5199
A12: Disbursals - Plan | B12: DF | C12: 736.66667 | D12: 450 | E12: 500 | F12: 550 | G12: 625 | H12: 700 | I12: 750 | J12: 800 | K12: 800 | L12: 850 | M12: 900 | N12: 925 | O12: 1150 | P12: 525 | Q12: 583.33333 | R12: 641.66667 | S12: 729.16667 | T12: 816.66667 | U12: 875 | V12: 933.33333 | W12: 933.33333 | X12: 991.66667 | Y12: 1050 | Z12: 1079.1667 | AA12: 1341.6667 | AB12: 600 | AC12: 666.66667 | AD12: 733.33333 | AE12: 833.33333 | AF12: 933.33333 | AG12: 1000 | AH12: 1066.6667 | AI12: 1066.6667 | AJ12: 1133.3333 | AK12: 1200 | AL12: 1233.3333 | AM12: 1533.3333

Sheet Input - ANR
A1: Back - Index | C1: =LOOKUP(C2,'Input-Stress Parameters'!$C$9:$BJ$9,'Input-Stress Parameters'!$C$11:$BJ$11) -> N | D1: =LOOKUP(D2,'Input-Stress Parameters'!$C$9:$BJ$9,'Input-Stress Parameters'!$C$11:$BJ$11) -> SL1 | E1: =LOOKUP(E2,'Input-Stress Parameters'!$C$9:$BJ$9,'Input-Stress Parameters'!$C$11:$BJ$11) -> SL1 | F1: =LOOKUP(F2,'Input-Stress Parameters'!$C$9:$BJ$9,'Input-Stress Parameters'!$C$11:$BJ$11) -> SL1 | G1: =LOOKUP(G2,'Input-Stress Parameters'!$C$9:$BJ$9,'Input-Stress Parameters'!$C$11:$BJ$11) -> SL1 | H1: =LOOKUP(H2,'Input-Stress Parameters'!$C$9:$BJ$9,'Input-Stress Parameters'!$C$11:$BJ$11) -> SL1 | I1: =LOOKUP(I2,'Input-Stress Parameters'!$C$9:$BJ$9,'Input-Stress Parameters'!$C$11:$BJ$11) -> SL1 | J1: =LOOKUP(J2,'Input-Stress Parameters'!$C$9:$BJ$9,'Input-Stress Parameters'!$C$11:$BJ$11) -> SL2 | ... BJ1: =LOOKUP(BJ2,'Input-Stress Parameters'!$C$9:$BJ$9,'Input-Stress Parameters'!$C$11:$BJ$11) -> N
A2: ANR - Stress Pre-WriteOff | B2: Inputs | C2: ='Input-Stress Parameters'!C9 -> 45352 | D2: =EDATE(C2,1) -> 45383 | E2: =EDATE(D2,1) -> 45413 | F2: =EDATE(E2,1) -> 45444 | G2: =EDATE(F2,1) -> 45474 | H2: =EDATE(G2,1) -> 45505 | I2: =EDATE(H2,1) -> 45536 | J2: =EDATE(I2,1) -> 45566 | K2: =EDATE(J2,1) -> 45597 | ... BJ2: =EDATE(BI2,1) -> 47150
A3: =$A$2 -> ANR - Stress Pre-WriteOff | B3: SMHFC | C3: =SUM(C4:C6) -> 86554.433 | D3: =SUM(D4:D6) -> 88358.894 | E3: =SUM(E4:E6) -> 89259.1 | F3: =SUM(F4:F6) -> 90235.884 | G3: =SUM(G4:G6) -> 91333.291 | H3: =SUM(H4:H6) -> 92447.995 | I3: =SUM(I4:I6) -> 93762.196 | J3: =SUM(J4:J6) -> 94797.18 | ... BJ3: =SUM(BJ4:BJ6) -> 0
A4: =$A$2 -> ANR - Stress Pre-WriteOff | B4: HL | C4: =C10 -> 50793.946 | D4: =D10 -> 51905.961 | E4: =E10 -> 52737.653 | F4: =F10 -> 53621.68 | G4: =G10 -> 54568.555 | H4: =H10 -> 55518.816 | I4: =I10 -> 56612.593 | J4: =J10 -> 57504.898 | ... AM4: =AM10 -> 99067.598
A5: =$A$2 -> ANR - Stress Pre-WriteOff | B5: LAP | C5: =C11 -> 28570.328 | D5: =D11 -> 29172.184 | E5: =E11 -> 29470.946 | F5: =F11 -> 29816.807 | G5: =G11 -> 30192.774 | H5: =H11 -> 30553.85 | I5: =I11 -> 30968.449 | J5: =J11 -> 31296.697 | ... AM5: =AM11 -> 47435.787
A6: =$A$2 -> ANR - Stress Pre-WriteOff | B6: DF | C6: =C12 -> 7190.1585 | D6: =D12 -> 7280.7491 | E6: =E12 -> 7050.5007 | F6: =F12 -> 6797.3964 | G6: =G12 -> 6571.9614 | H6: =H12 -> 6375.3294 | I6: =I12 -> 6181.153 | J6: =J12 -> 5995.585 | ... AM6: =AM12 -> 8837.2199
A8: ANR - Stress Post-WriteOff | B8: Inputs | C8: =C2 -> 45352 | D8: =EDATE(C8,1) -> 45383 | E8: =EDATE(D8,1) -> 45413 | F8: =EDATE(E8,1) -> 45444 | G8: =EDATE(F8,1) -> 45474 | H8: =EDATE(G8,1) -> 45505 | I8: =EDATE(H8,1) -> 45536 | J8: =EDATE(I8,1) -> 45566 | K8: =EDATE(J8,1) -> 45597 | ... BJ8: =EDATE(BI8,1) -> 47150
A9: =$A$8 -> ANR - Stress Post-WriteOff | B9: SMHFC | C9: =SUM(C10:C12) -> 86554.433 | D9: =SUM(D10:D12) -> 88358.894 | E9: =SUM(E10:E12) -> 89259.1 | F9: =SUM(F10:F12) -> 90235.884 | G9: =SUM(G10:G12) -> 91333.291 | H9: =SUM(H10:H12) -> 92447.995 | I9: =SUM(I10:I12) -> 93762.196 | J9: =SUM(J10:J12) -> 94797.18 | ... BJ9: =SUM(BJ10:BJ12) -> 0
A10: =$A$8 -> ANR - Stress Post-WriteOff | B10: HL | C10: 50793.946 | D10: 51905.961 | E10: 52737.653 | F10: 53621.68 | G10: 54568.555 | H10: 55518.816 | I10: 56612.593 | J10: 57504.898 | K10: 58314.532 | L10: 59237.047 | M10: 60149.799 | N10: 60978.282 | O10: 61796.415 | P10: 62133.77 | Q10: 62029.034 | R10: 61992.038 | S10: 61964.22 | T10: 61993.567 | U10: 62131.731 | V10: 62365.109 | W10: 62836.171 | X10: 63658.992 | Y10: 64773.486 | Z10: 66091.732 | AA10: 67674.761 | AB10: 68720.858 | AC10: 69834.876 | AD10: 71374.545 | AE10: 72739.448 | AF10: 74557.438 | AG10: 76959.473 | AH10: 79800.091 | AI10: 83058.438 | AJ10: 86823.714 | AK10: 90848.652 | AL10: 94890.36 | AM10: 99067.598
A11: =$A$8 -> ANR - Stress Post-WriteOff | B11: LAP | C11: 28570.328 | D11: 29172.184 | E11: 29470.946 | F11: 29816.807 | G11: 30192.774 | H11: 30553.85 | I11: 30968.449 | J11: 31296.697 | K11: 31558.698 | L11: 31880.266 | M11: 32163.726 | N11: 32423.155 | O11: 32693.482 | P11: 32755.621 | Q11: 32624.65 | R11: 32516.873 | S11: 32434.898 | T11: 32389.358 | U11: 32373.428 | V11: 32406.612 | W11: 32560.151 | X11: 32871.934 | Y11: 33306.783 | Z11: 33831.015 | AA11: 34470.87 | AB11: 34905.502 | AC11: 35149.468 | AD11: 35560.918 | AE11: 36136.868 | AF11: 36916.481 | AG11: 37940.548 | AH11: 39155.758 | AI11: 40555.364 | AJ11: 42169.848 | AK11: 43901.281 | AL11: 45642.622 | AM11: 47435.787
A12: =$A$8 -> ANR - Stress Post-WriteOff | B12: DF | C12: 7190.1585 | D12: 7280.7491 | E12: 7050.5007 | F12: 6797.3964 | G12: 6571.9614 | H12: 6375.3294 | I12: 6181.153 | J12: 5995.585 | K12: 5863.6847 | L12: 5686.1502 | M12: 5518.1682 | N12: 5351.6272 | O12: 5207.3484 | P12: 5029.321 | Q12: 4798.3782 | R12: 4584.5553 | S12: 4385.277 | T12: 4202.2394 | U12: 4032.2059 | V12: 3893.5691 | W12: 3802.4286 | X12: 3759.0896 | Y12: 3769.2887 | Z12: 3829.5985 | AA12: 3975.4191 | AB12: 4072.843 | AC12: 4083.768 | AD12: 4151.7848 | AE12: 4295.8332 | AF12: 4528.8449 | AG12: 4851.7278 | AH12: 5378.0489 | AI12: 6041.6169 | AJ12: 6694.101 | AK12: 7367.7423 | AL12: 8045.4175 | AM12: 8837.2199
A14: ANR - Plan | B14: Inputs | C14: =C8 -> 45352 | D14: =EDATE(C14,1) -> 45383 | E14: =EDATE(D14,1) -> 45413 | F14: =EDATE(E14,1) -> 45444 | G14: =EDATE(F14,1) -> 45474 | H14: =EDATE(G14,1) -> 45505 | I14: =EDATE(H14,1) -> 45536 | J14: =EDATE(I14,1) -> 45566 | K14: =EDATE(J14,1) -> 45597 | ... BJ14: =EDATE(BI14,1) -> 47150
A15: ANR - Plan | B15: SMHFC | C15: =SUM(C16:C18) -> 86554.433 | D15: =SUM(D16:D18) -> 88967.667 | E15: =SUM(E16:E18) -> 90615.895 | F15: =SUM(F16:F18) -> 92631.472 | G15: =SUM(G16:G18) -> 95003.155 | H15: =SUM(H16:H18) -> 97662.1 | I15: =SUM(I16:I18) -> 100858.17 | J15: =SUM(J16:J18) -> 104075.75 | ... BJ15: =SUM(BJ16:BJ18) -> 0
A16: ANR - Plan | B16: HL | C16: 50793.946 | D16: 52462.948 | E16: 53662.505 | F16: 55103.803 | G16: 56741.726 | H16: 58544.614 | I16: 60688.233 | J16: 62810.55 | K16: 65074.742 | L16: 67700.65 | M16: 70502.045 | N16: 73301.876 | O16: 76198.748 | P16: 78211.014 | Q16: 79425.325 | R16: 80935.104 | S16: 82623.167 | T16: 84571.644 | U16: 86866.019 | V16: 89230.309 | W16: 91761.855 | X16: 94724.065 | Y16: 97928.765 | Z16: 101162.13 | AA16: 104504.81 | AB16: 106695.15 | AC16: 108368.91 | AD16: 110406.83 | AE16: 112147.15 | AF16: 114201.11 | AG16: 116643.1 | AH16: 119182.79 | AI16: 121932.38 | AJ16: 125201.08 | AK16: 128742.22 | AL16: 132313.14 | AM16: 136032.47
A17: ANR - Plan | B17: LAP | C17: 28570.328 | D17: 29217.729 | E17: 29671.062 | F17: 30216.352 | G17: 30852.696 | H17: 31547.299 | I17: 32382.933 | J17: 33229.848 | K17: 34124.779 | L17: 35194.024 | M17: 36309.649 | N17: 37445.761 | O17: 38648.173 | P17: 39472.68 | Q17: 39947.087 | R17: 40536.89 | S17: 41226.496 | T17: 42041.468 | U17: 42989.258 | V17: 43976.689 | W17: 45056.356 | X17: 46330.244 | Y17: 47696.662 | Z17: 49067.509 | AA17: 50486.789 | AB17: 51409.416 | AC17: 51862.341 | AD17: 52454.441 | AE17: 53157.864 | AF17: 54003.696 | AG17: 55006.09 | AH17: 56051.751 | AI17: 57191.188 | AJ17: 58546.916 | AK17: 60023.211 | AL17: 61512.749 | AM17: 63054.969
A18: ANR - Plan | B18: DF | C18: 7190.1585 | D18: 7286.9899 | E18: 7282.3285 | F18: 7311.3169 | G18: 7408.7332 | H18: 7570.1878 | I18: 7787.0062 | J18: 8035.3505 | K18: 8291.9938 | L18: 8557.2723 | M18: 8853.1454 | N18: 9166.3919 | O18: 9580.4748 | P18: 9774.5339 | Q18: 9682.3989 | R18: 9652.5139 | S18: 9695.0337 | T18: 9819.3725 | U18: 10006.197 | V18: 10237.395 | W18: 10481.933 | X18: 10738.954 | Y18: 11035.842 | Z18: 11355.944 | AA18: 11796.421 | AB18: 11977.081 | AC18: 11819.982 | AD18: 11737.397 | AE18: 11740.649 | AF18: 11840.331 | AG18: 12014.144 | AH18: 12241.221 | AI18: 12485.929 | AJ18: 12747.135 | AK18: 13055.993 | AL18: 13393.337 | AM18: 13870.082

Sheet Input - FInancials
A1: Back - Index | C1: =LOOKUP(C2,'Input-Stress Parameters'!$C$9:$BJ$9,'Input-Stress Parameters'!$C$11:$BJ$11) -> N | D1: =LOOKUP(D2,'Input-Stress Parameters'!$C$9:$BJ$9,'Input-Stress Parameters'!$C$11:$BJ$11) -> SL1 | E1: =LOOKUP(E2,'Input-Stress Parameters'!$C$9:$BJ$9,'Input-Stress Parameters'!$C$11:$BJ$11) -> SL1 | F1: =LOOKUP(F2,'Input-Stress Parameters'!$C$9:$BJ$9,'Input-Stress Parameters'!$C$11:$BJ$11) -> SL1 | G1: =LOOKUP(G2,'Input-Stress Parameters'!$C$9:$BJ$9,'Input-Stress Parameters'!$C$11:$BJ$11) -> SL1 | H1: =LOOKUP(H2,'Input-Stress Parameters'!$C$9:$BJ$9,'Input-Stress Parameters'!$C$11:$BJ$11) -> SL1 | I1: =LOOKUP(I2,'Input-Stress Parameters'!$C$9:$BJ$9,'Input-Stress Parameters'!$C$11:$BJ$11) -> SL1 | J1: =LOOKUP(J2,'Input-Stress Parameters'!$C$9:$BJ$9,'Input-Stress Parameters'!$C$11:$BJ$11) -> SL2 | ... BJ1: =LOOKUP(BJ2,'Input-Stress Parameters'!$C$9:$BJ$9,'Input-Stress Parameters'!$C$11:$BJ$11) -> N
A2: Revenue - Stress | B2: Inputs | C2: ='Input-Stress Parameters'!C9 -> 45352 | D2: =EDATE(C2,1) -> 45383 | E2: =EDATE(D2,1) -> 45413 | F2: =EDATE(E2,1) -> 45444 | G2: =EDATE(F2,1) -> 45474 | H2: =EDATE(G2,1) -> 45505 | I2: =EDATE(H2,1) -> 45536 | J2: =EDATE(I2,1) -> 45566 | K2: =EDATE(J2,1) -> 45597 | ... BJ2: =EDATE(BI2,1) -> 47150
A3: =$A$2 -> Revenue - Stress | B3: FIHFC | C3: =+SUM(C4:C6) -> 0 | D3: =+SUM(D4:D6) -> 0 | E3: =+SUM(E4:E6) -> 0 | F3: =+SUM(F4:F6) -> 0 | G3: =+SUM(G4:G6) -> 0 | H3: =+SUM(H4:H6) -> 0 | I3: =+SUM(I4:I6) -> 0 | J3: =+SUM(J4:J6) -> 0 | ... BJ3: =+SUM(BJ4:BJ6) -> 0
A4: =$A$2 -> Revenue - Stress | B4: HL
A5: =$A$2 -> Revenue - Stress | B5: LAP
A6: =$A$2 -> Revenue - Stress | B6: DF
A8: Revenue - Plan | B8: Inputs | C8: =C2 -> 45352 | D8: =EDATE(C8,1) -> 45383 | E8: =EDATE(D8,1) -> 45413 | F8: =EDATE(E8,1) -> 45444 | G8: =EDATE(F8,1) -> 45474 | H8: =EDATE(G8,1) -> 45505 | I8: =EDATE(H8,1) -> 45536 | J8: =EDATE(I8,1) -> 45566 | K8: =EDATE(J8,1) -> 45597 | ... BJ8: =EDATE(BI8,1) -> 47150
A9: =$A$8 -> Revenue - Plan | B9: FIHFC | C9: =+SUM(C10:C12) -> 0 | D9: =+SUM(D10:D12) -> 0 | E9: =+SUM(E10:E12) -> 0 | F9: =+SUM(F10:F12) -> 0 | G9: =+SUM(G10:G12) -> 0 | H9: =+SUM(H10:H12) -> 0 | I9: =+SUM(I10:I12) -> 0 | J9: =+SUM(J10:J12) -> 0 | ... BJ9: =+SUM(BJ10:BJ12) -> 0
A10: =$A$8 -> Revenue - Plan | B10: HL
A11: =$A$8 -> Revenue - Plan | B11: LAP
A12: =$A$8 -> Revenue - Plan | B12: DF
A14: Cost - Stress | B14: Inputs | C14: =C2 -> 45352 | D14: =EDATE(C14,1) -> 45383 | E14: =EDATE(D14,1) -> 45413 | F14: =EDATE(E14,1) -> 45444 | G14: =EDATE(F14,1) -> 45474 | H14: =EDATE(G14,1) -> 45505 | I14: =EDATE(H14,1) -> 45536 | J14: =EDATE(I14,1) -> 45566 | K14: =EDATE(J14,1) -> 45597 | ... BJ14: =EDATE(BI14,1) -> 47150
A15: =$A$14 -> Cost - Stress | B15: FIHFC | C15: =+SUM(C16:C18) -> 0 | D15: =+SUM(D16:D18) -> 0 | E15: =+SUM(E16:E18) -> 0 | F15: =+SUM(F16:F18) -> 0 | G15: =+SUM(G16:G18) -> 0 | H15: =+SUM(H16:H18) -> 0 | I15: =+SUM(I16:I18) -> 0 | J15: =+SUM(J16:J18) -> 0 | ... BJ15: =+SUM(BJ16:BJ18) -> 0
A16: =$A$14 -> Cost - Stress | B16: HL
A17: =$A$14 -> Cost - Stress | B17: LAP
A18: =$A$14 -> Cost - Stress | B18: DF
A20: Cost - Plan | B20: Inputs | C20: =C2 -> 45352 | D20: =EDATE(C20,1) -> 45383 | E20: =EDATE(D20,1) -> 45413 | F20: =EDATE(E20,1) -> 45444 | G20: =EDATE(F20,1) -> 45474 | H20: =EDATE(G20,1) -> 45505 | I20: =EDATE(H20,1) -> 45536 | J20: =EDATE(I20,1) -> 45566 | K20: =EDATE(J20,1) -> 45597 | ... BJ20: =EDATE(BI20,1) -> 47150
A21: =$A$20 -> Cost - Plan | B21: FIHFC | C21: =+SUM(C22:C24) -> 0 | D21: =+SUM(D22:D24) -> 0 | E21: =+SUM(E22:E24) -> 0 | F21: =+SUM(F22:F24) -> 0 | G21: =+SUM(G22:G24) -> 0 | H21: =+SUM(H22:H24) -> 0 | I21: =+SUM(I22:I24) -> 0 | J21: =+SUM(J22:J24) -> 0 | ... BJ21: =+SUM(BJ22:BJ24) -> 0
A22: =$A$20 -> Cost - Plan | B22: HL
A23: =$A$20 -> Cost - Plan | B23: LAP
A24: =$A$20 -> Cost - Plan | B24: DF
A26: Treasury benefit - Stress | B26: Inputs | C26: =C2 -> 45352 | D26: =EDATE(C26,1) -> 45383 | E26: =EDATE(D26,1) -> 45413 | F26: =EDATE(E26,1) -> 45444 | G26: =EDATE(F26,1) -> 45474 | H26: =EDATE(G26,1) -> 45505 | I26: =EDATE(H26,1) -> 45536 | J26: =EDATE(I26,1) -> 45566 | K26: =EDATE(J26,1) -> 45597 | ... BJ26: =EDATE(BI26,1) -> 47150
A27: =$A$26 -> Treasury benefit - Stress | B27: FIHFC | C27: =+SUM(C28:C30) -> 0 | D27: =+SUM(D28:D30) -> 0 | E27: =+SUM(E28:E30) -> 0 | F27: =+SUM(F28:F30) -> 0 | G27: =+SUM(G28:G30) -> 0 | H27: =+SUM(H28:H30) -> 0 | I27: =+SUM(I28:I30) -> 0 | J27: =+SUM(J28:J30) -> 0 | ... BJ27: =+SUM(BJ28:BJ30) -> 0
A28: =$A$26 -> Treasury benefit - Stress | B28: HL
A29: =$A$26 -> Treasury benefit - Stress | B29: LAP
A30: =$A$26 -> Treasury benefit - Stress | B30: DF
A32: Treasury benefit - Plan | B32: Inputs | C32: =C2 -> 45352 | D32: =EDATE(C32,1) -> 45383 | E32: =EDATE(D32,1) -> 45413 | F32: =EDATE(E32,1) -> 45444 | G32: =EDATE(F32,1) -> 45474 | H32: =EDATE(G32,1) -> 45505 | I32: =EDATE(H32,1) -> 45536 | J32: =EDATE(I32,1) -> 45566 | K32: =EDATE(J32,1) -> 45597 | ... BJ32: =EDATE(BI32,1) -> 47150
A33: =$A$32 -> Treasury benefit - Plan | B33: FIHFC | C33: =+SUM(C34:C36) -> 0 | D33: =+SUM(D34:D36) -> 0 | E33: =+SUM(E34:E36) -> 0 | F33: =+SUM(F34:F36) -> 0 | G33: =+SUM(G34:G36) -> 0 | H33: =+SUM(H34:H36) -> 0 | I33: =+SUM(I34:I36) -> 0 | J33: =+SUM(J34:J36) -> 0 | ... BJ33: =+SUM(BJ34:BJ36) -> 0
A34: =$A$32 -> Treasury benefit - Plan | B34: HL
A35: =$A$32 -> Treasury benefit - Plan | B35: LAP
A36: =$A$32 -> Treasury benefit - Plan | B36: DF
A38: Capital Infusion - Stress | B38: Inputs | C38: =C2 -> 45352 | D38: =EDATE(C38,1) -> 45383 | E38: =EDATE(D38,1) -> 45413 | F38: =EDATE(E38,1) -> 45444 | G38: =EDATE(F38,1) -> 45474 | H38: =EDATE(G38,1) -> 45505 | I38: =EDATE(H38,1) -> 45536 | J38: =EDATE(I38,1) -> 45566 | K38: =EDATE(J38,1) -> 45597 | ... BJ38: =EDATE(BI38,1) -> 47150
A39: =$A$38 -> Capital Infusion - Stress | B39: FIHFC | C39: =+SUM(C40:C42) -> 0 | D39: =+SUM(D40:D42) -> 0 | E39: =+SUM(E40:E42) -> 0 | F39: =+SUM(F40:F42) -> 0 | G39: =+SUM(G40:G42) -> 0 | H39: =+SUM(H40:H42) -> 0 | I39: =+SUM(I40:I42) -> 0 | J39: =+SUM(J40:J42) -> 0 | ... BJ39: =+SUM(BJ40:BJ42) -> 0
A40: =$A$38 -> Capital Infusion - Stress | B40: HL
A41: =$A$38 -> Capital Infusion - Stress | B41: LAP
A42: =$A$38 -> Capital Infusion - Stress | B42: DF
A44: Capital Infusion - Plan | B44: Inputs | C44: =C2 -> 45352 | D44: =EDATE(C44,1) -> 45383 | E44: =EDATE(D44,1) -> 45413 | F44: =EDATE(E44,1) -> 45444 | G44: =EDATE(F44,1) -> 45474 | H44: =EDATE(G44,1) -> 45505 | I44: =EDATE(H44,1) -> 45536 | J44: =EDATE(I44,1) -> 45566 | K44: =EDATE(J44,1) -> 45597 | ... BJ44: =EDATE(BI44,1) -> 47150
A45: =$A$44 -> Capital Infusion - Plan | B45: FIHFC | C45: =+SUM(C46:C48) -> 0 | D45: =+SUM(D46:D48) -> 0 | E45: =+SUM(E46:E48) -> 0 | F45: =+SUM(F46:F48) -> 0 | G45: =+SUM(G46:G48) -> 0 | H45: =+SUM(H46:H48) -> 0 | I45: =+SUM(I46:I48) -> 0 | J45: =+SUM(J46:J48) -> 0 | ... BJ45: =+SUM(BJ46:BJ48) -> 0
A46: =$A$44 -> Capital Infusion - Plan | B46: HL
A47: =$A$44 -> Capital Infusion - Plan | B47: LAP
A48: =$A$44 -> Capital Infusion - Plan | B48: DF

Sheet Calculation - Stage dist
D1: Back - Index | F1: =LOOKUP(F4,'Input-Stress Parameters'!$C$9:$BJ$9,'Input-Stress Parameters'!$C$11:$BJ$11) -> N | G1: =LOOKUP(G4,'Input-Stress Parameters'!$C$9:$BJ$9,'Input-Stress Parameters'!$C$11:$BJ$11) -> SL1 | H1: =LOOKUP(H4,'Input-Stress Parameters'!$C$9:$BJ$9,'Input-Stress Parameters'!$C$11:$BJ$11) -> SL1 | I1: =LOOKUP(I4,'Input-Stress Parameters'!$C$9:$BJ$9,'Input-Stress Parameters'!$C$11:$BJ$11) -> SL1 | J1: =LOOKUP(J4,'Input-Stress Parameters'!$C$9:$BJ$9,'Input-Stress Parameters'!$C$11:$BJ$11) -> SL1 | K1: =LOOKUP(K4,'Input-Stress Parameters'!$C$9:$BJ$9,'Input-Stress Parameters'!$C$11:$BJ$11) -> SL1 | L1: =LOOKUP(L4,'Input-Stress Parameters'!$C$9:$BJ$9,'Input-Stress Parameters'!$C$11:$BJ$11) -> SL1 | M1: =LOOKUP(M4,'Input-Stress Parameters'!$C$9:$BJ$9,'Input-Stress Parameters'!$C$11:$BJ$11) -> SL2 | ... BM1: =LOOKUP(BM4,'Input-Stress Parameters'!$C$9:$BJ$9,'Input-Stress Parameters'!$C$11:$BJ$11) -> N | BQ1: =LOOKUP(BQ4,'Input-Stress Parameters'!$C$9:$BJ$9,'Input-Stress Parameters'!$C$11:$BJ$11) -> #N/A | BR1: =LOOKUP(BR4,'Input-Stress Parameters'!$C$9:$BJ$9,'Input-Stress Parameters'!$C$11:$BJ$11) -> #N/A | BS1: =LOOKUP(BS4,'Input-Stress Parameters'!$C$9:$BJ$9,'Input-Stress Parameters'!$C$11:$BJ$11) -> #N/A | BT1: =LOOKUP(BT4,'Input-Stress Parameters'!$C$9:$BJ$9,'Input-Stress Parameters'!$C$11:$BJ$11) -> #N/A | BU1: =LOOKUP(BU4,'Input-Stress Parameters'!$C$9:$BJ$9,'Input-Stress Parameters'!$C$11:$BJ$11) -> #N/A | BV1: =LOOKUP(BV4,'Input-Stress Parameters'!$C$9:$BJ$9,'Input-Stress Parameters'!$C$11:$BJ$11) -> #N/A | BW1: =LOOKUP(BW4,'Input-Stress Parameters'!$C$9:$BJ$9,'Input-Stress Parameters'!$C$11:$BJ$11) -> #N/A | BX1: =LOOKUP(BX4,'Input-Stress Parameters'!$C$9:$BJ$9,'Input-Stress Parameters'!$C$11:$BJ$11) -> #N/A | ... DX1: =LOOKUP(DX4,'Input-Stress Parameters'!$C$9:$BJ$9,'Input-Stress Parameters'!$C$11:$BJ$11) -> N | EA1: =LOOKUP(EA4,'Input-Stress Parameters'!$C$9:$BJ$9,'Input-Stress Parameters'!$C$11:$BJ$11) -> SL1 | EB1: =LOOKUP(EB4,'Input-Stress Parameters'!$C$9:$BJ$9,'Input-Stress Parameters'!$C$11:$BJ$11) -> SL1 | EC1: =LOOKUP(EC4,'Input-Stress Parameters'!$C$9:$BJ$9,'Input-Stress Parameters'!$C$11:$BJ$11) -> SL2 | ED1: =LOOKUP(ED4,'Input-Stress Parameters'!$C$9:$BJ$9,'Input-Stress Parameters'!$C$11:$BJ$11) -> #REF! | EE1: =LOOKUP(EE4,'Input-Stress Parameters'!$C$9:$BJ$9,'Input-Stress Parameters'!$C$11:$BJ$11) -> #REF! | EF1: =LOOKUP(EF4,'Input-Stress Parameters'!$C$9:$BJ$9,'Input-Stress Parameters'!$C$11:$BJ$11) -> #REF! | EG1: =LOOKUP(EG4,'Input-Stress Parameters'!$C$9:$BJ$9,'Input-Stress Parameters'!$C$11:$BJ$11) -> #REF! | EH1: =LOOKUP(EH4,'Input-Stress Parameters'!$C$9:$BJ$9,'Input-Stress Parameters'!$C$11:$BJ$11) -> #REF! | ... EJ1: =LOOKUP(EJ4,'Input-Stress Parameters'!$C$9:$BJ$9,'Input-Stress Parameters'!$C$11:$BJ$11) -> SL3
A2: =$B5*($B8/$A8) -> 0.001632994 | F2: =LOOKUP(BQ4,'Input-Stress Parameters'!$C$9:$BJ$9,'Input-Stress Parameters'!$C$12:$BJ$12) -> #N/A | G2: =LOOKUP(BR4,'Input-Stress Parameters'!$C$9:$BJ$9,'Input-Stress Parameters'!$C$12:$BJ$12) -> #N/A | H2: =LOOKUP(BS4,'Input-Stress Parameters'!$C$9:$BJ$9,'Input-Stress Parameters'!$C$12:$BJ$12) -> #N/A | I2: =LOOKUP(BT4,'Input-Stress Parameters'!$C$9:$BJ$9,'Input-Stress Parameters'!$C$12:$BJ$12) -> #N/A | J2: =LOOKUP(BU4,'Input-Stress Parameters'!$C$9:$BJ$9,'Input-Stress Parameters'!$C$12:$BJ$12) -> #N/A | K2: =LOOKUP(BV4,'Input-Stress Parameters'!$C$9:$BJ$9,'Input-Stress Parameters'!$C$12:$BJ$12) -> #N/A | L2: =LOOKUP(BW4,'Input-Stress Parameters'!$C$9:$BJ$9,'Input-Stress Parameters'!$C$12:$BJ$12) -> #N/A | M2: =LOOKUP(BX4,'Input-Stress Parameters'!$C$9:$BJ$9,'Input-Stress Parameters'!$C$12:$BJ$12) -> #N/A | ... BM2: =LOOKUP(DX4,'Input-Stress Parameters'!$C$9:$BJ$9,'Input-Stress Parameters'!$C$12:$BJ$12) -> N | EA2: =LOOKUP(EA4,'Input-Stress Parameters'!$C$9:$BJ$9,'Input-Stress Parameters'!$C$12:$BJ$12) -> SL1P | EB2: =LOOKUP(EB4,'Input-Stress Parameters'!$C$9:$BJ$9,'Input-Stress Parameters'!$C$12:$BJ$12) -> SL1P | EC2: =LOOKUP(EC4,'Input-Stress Parameters'!$C$9:$BJ$9,'Input-Stress Parameters'!$C$12:$BJ$12) -> SL2P | ED2: =LOOKUP(ED4,'Input-Stress Parameters'!$C$9:$BJ$9,'Input-Stress Parameters'!$C$12:$BJ$12) -> #REF! | EE2: =LOOKUP(EE4,'Input-Stress Parameters'!$C$9:$BJ$9,'Input-Stress Parameters'!$C$12:$BJ$12) -> #REF! | EF2: =LOOKUP(EF4,'Input-Stress Parameters'!$C$9:$BJ$9,'Input-Stress Parameters'!$C$12:$BJ$12) -> #REF! | EG2: =LOOKUP(EG4,'Input-Stress Parameters'!$C$9:$BJ$9,'Input-Stress Parameters'!$C$12:$BJ$12) -> #REF! | EH2: =LOOKUP(EH4,'Input-Stress Parameters'!$C$9:$BJ$9,'Input-Stress Parameters'!$C$12:$BJ$12) -> #REF! | ... EJ2: =LOOKUP(EJ4,'Input-Stress Parameters'!$C$9:$BJ$9,'Input-Stress Parameters'!$C$12:$BJ$12) -> SL4P
C3: 1 | F3: =IF(F1="N",IF(G1="SL1","SL0","NA")) -> SL0 | G3: =IF(G1="N",IF(H1="SL1","SL0","NA")) -> FALSE | H3: =IF(H1="N",IF(I1="SL1","SL0","NA")) -> FALSE | I3: =IF(I1="N",IF(J1="SL1","SL0","NA")) -> FALSE | J3: =IF(J1="N",IF(K1="SL1","SL0","NA")) -> FALSE | K3: =IF(K1="N",IF(L1="SL1","SL0","NA")) -> FALSE | L3: =IF(L1="N",IF(M1="SL1","SL0","NA")) -> FALSE | M3: =IF(M1="N",IF(N1="SL1","SL0","NA")) -> FALSE | ... AE3: =IF(AE1="N",IF(AF1="SL1","SL0","NA")) -> FALSE | AF3: =IF(AF1="N",IF(AG1="SL1","SL0",IF(AG1="N","SLX","NA"))) -> FALSE | AG3: =IF(AG1="N",IF(AH1="SL1","SL0",IF(AH1="N","SLX","NA"))) -> FALSE | AH3: =IF(AH1="N",IF(AI1="SL1","SL0",IF(AI1="N","SLX","NA"))) -> FALSE | AI3: =IF(AI1="N",IF(AJ1="SL1","SL0",IF(AJ1="N","SLX","NA"))) -> FALSE | AJ3: =IF(AJ1="N",IF(AK1="SL1","SL0",IF(AK1="N","SLX","NA"))) -> FALSE | AK3: =IF(AK1="N",IF(AL1="SL1","SL0",IF(AL1="N","SLX","NA"))) -> SLX | AL3: =IF(AL1="N",IF(AM1="SL1","SL0",IF(AM1="N","SLX","NA"))) -> SLX | AM3: =IF(AM1="N",IF(AN1="SL1","SL0",IF(AN1="N","SLX","NA"))) -> SLX | ... BM3: =IF(BM1="N",IF(BN1="SL1","SL0",IF(BN1="N","SLX","NA"))) -> NA
A4: SLX | B4: =HLOOKUP(A4,$F$3:$BM$95,C6,0) -> 0.017996229 | C4: =C3+1 -> 2 | D4: HL | E4: Plan | F4: ='Input-Stress Parameters'!C2 -> 45352 | G4: =EDATE(F4,1) -> 45383 | H4: =EDATE(G4,1) -> 45413 | I4: =EDATE(H4,1) -> 45444 | J4: =EDATE(I4,1) -> 45474 | K4: =EDATE(J4,1) -> 45505 | L4: =EDATE(K4,1) -> 45536 | M4: =EDATE(L4,1) -> 45566 | N4: =EDATE(M4,1) -> 45597 | ... BM4: =EDATE(BL4,1) -> 47150 | BP4: Stressed | BQ4: 45017 | BR4: =EDATE(BQ4,1) -> 45047 | BS4: =EDATE(BR4,1) -> 45078 | BT4: =EDATE(BS4,1) -> 45108 | BU4: =EDATE(BT4,1) -> 45139 | BV4: =EDATE(BU4,1) -> 45170 | BW4: =EDATE(BV4,1) -> 45200 | BX4: =EDATE(BW4,1) -> 45231 | BY4: =EDATE(BX4,1) -> 45261 | ... DX4: =EDATE(DW4,1) -> 46813 | EA4: =EDATE(EB4,-1) -> 45505 | EB4: ='Input-Stress Parameters'!B15 -> 45536 | EC4: ='Input-Stress Parameters'!B16 -> 45901 | ED4: ='Input-Stress Parameters'!#REF! -> #REF! | EE4: ='Input-Stress Parameters'!#REF! -> #REF! | EF4: ='Input-Stress Parameters'!#REF! -> #REF! | EG4: ='Input-Stress Parameters'!#REF! -> #REF! | EH4: ='Input-Stress Parameters'!#REF! -> #REF! | EI4: ='Input-Stress Parameters'!B17 -> 45992 | EJ4: =EDATE(EI4,1) -> 46023
A5: SL0 | B5: =HLOOKUP(A5,$F$3:$BM$95,C6,0) -> 0.023275618 | C5: =C4+1 -> 3 | D5: Stage1 | E5: Stage1 | F5: 0.95964141 | G5: 0.9605471 | H5: 0.96090265 | I5: 0.96118599 | J5: 0.96172486 | K5: 0.96227701 | L5: 0.96278666 | M5: 0.96359154 | N5: 0.96448905 | O5: 0.96551546 | P5: 0.9666218 | Q5: 0.96759937 | R5: 0.96857801 | S5: 0.96803239 | T5: 0.96762509 | U5: 0.96726971 | V5: 0.96783658 | W5: 0.96791672 | X5: 0.96810754 | Y5: 0.96831018 | Z5: 0.96888963 | AA5: 0.9695536 | AB5: 0.97043139 | AC5: 0.9711735 | AD5: 0.97193157 | AE5: 0.9717399 | AF5: 0.97146942 | AG5: 0.9709802 | AH5: 0.97085213 | AI5: 0.97085709 | AJ5: 0.9709113 | AK5: 0.97114854 | AL5: 0.97159482 | AM5: 0.97217624 | AN5: 0.97296164 | AO5: 0.97368042 | AP5: 0.97445349 | AQ5: 0.95 | AR5: 0.95 | AS5: 0.95 | AT5: 0.95 | AU5: 0.95 | AV5: 0.95 | AW5: 0.95 | AX5: 0.95 | AY5: 0.95 | AZ5: 0.95 | BA5: 0.95 | BB5: 0.95 | BC5: 0.95 | BD5: 0.95 | BE5: 0.95 | BF5: 0.95 | BG5: 0.95 | BH5: 0.95 | BI5: 0.95 | BJ5: 0.95 | BK5: 0.95 | BL5: 0.95 | BM5: 0.95 | EA5: =LOOKUP(EA$4,$F$4:$BM$4,$F5:$BM5) -> 0.96227701 | EB5: =EA5+(EC5-EA5)/'Input-Stress Parameters'!$J$5 -> 0.95877368 | EC5: =1-SUM(EC6:EC7) -> 0.94125703 | ED5: =EC5+(EE5-EC5)/'Input-Stress Parameters'!$J$6 -> 0.93745212 | EE5: =1-SUM(EE6:EE7) -> 0.89559809 | EF5: =1-SUM(EF6:EF7) -> 0.93745212 | EG5: =1-SUM(EG6:EG7) -> #REF! | EH5: =1-SUM(EH6:EH7) -> #REF! | EI5: =EJ5+(EH5-EJ5)/MONTH($EJ$4-$EH$4) -> #REF! | EJ5: =LOOKUP(EJ$4,$F$4:$BM$4,$F5:$BM5) -> 0.97043139
A6: SLX | B6: =HLOOKUP(A6,$F$3:$BM$95,C7,0) -> 0.010855232 | C6: =C5+1 -> 4 | D6: Stage2 | E6: Stage2 | F6: 0.023275618 | G6: 0.022878309 | H6: 0.02274303 | I6: 0.02274595 | J6: 0.022564291 | K6: 0.022314991 | L6: 0.022005027 | M6: 0.02160992 | N6: 0.021019541 | O6: 0.020341828 | P6: 0.019555203 | Q6: 0.018859483 | R6: 0.018214494 | S6: 0.018611928 | T6: 0.019057491 | U6: 0.019479789 | V6: 0.01967179 | W6: 0.019731956 | X6: 0.01966482 | Y6: 0.01945508 | Z6: 0.019048941 | AA6: 0.018528972 | AB6: 0.017833892 | AC6: 0.017230157 | AD6: 0.016681228 | AE6: 0.017181317 | AF6: 0.017412389 | AG6: 0.017799154 | AH6: 0.018037215 | AI6: 0.018149657 | AJ6: 0.018142528 | AK6: 0.017996229 | AL6: 0.017624594 | AM6: 0.017166198 | AN6: 0.016537329 | AO6: 0.015984717 | AP6: 0.015474225 | AQ6: 0.03 | AR6: 0.03 | AS6: 0.03 | AT6: 0.03 | AU6: 0.03 | AV6: 0.03 | AW6: 0.03 | AX6: 0.03 | AY6: 0.03 | AZ6: 0.03 | BA6: 0.03 | BB6: 0.03 | BC6: 0.03 | BD6: 0.03 | BE6: 0.03 | BF6: 0.03 | BG6: 0.03 | BH6: 0.03 | BI6: 0.03 | BJ6: 0.03 | BK6: 0.03 | BL6: 0.03 | BM6: 0.03 | EA6: =LOOKUP(EA$4,$F$4:$BM$4,$F6:$BM6) -> 0.022314991 | EB6: =EA6+(EC6-EA6)/'Input-Stress Parameters'!$J$5 -> 0.024632624 | EC6: =LOOKUP(EC$4,$F$4:$BM$4,$F6:$BM6)*'Calculations - Parameters'!$L$3/'Calculations - Parameters'!$K$3 -> 0.036220788 | ED6: =EC6+(EE6-EC6)/'Input-Stress Parameters'!$J$6 -> 0.038566889 | EE6: =EC6*'Calculations - Parameters'!$M$3/'Calculations - Parameters'!$L$3 -> 0.064373992 | EF6: =ED6 -> 0.038566889 | EG6: =EF6+(EH6-EF6)/MONTH($EH$4-$EF$4) -> #REF! | EH6: =EE6*'Calculations - Parameters'!$N$3/'Calculations - Parameters'!$M$3 -> 0.029584693 | EI6: =EJ6+(EH6-EJ6)/MONTH($EJ$4-$EH$4) -> #REF! | EJ6: =LOOKUP(EJ$4,$F$4:$BM$4,$F6:$BM6) -> 0.017833892
A7: SL0 | B7: =HLOOKUP(A7,$F$3:$BM$95,C7,0) -> 0.017082974 | C7: =C6+1 -> 5 | D7: Stage3 | E7: Stage3 | F7: 0.017082974 | G7: 0.016574595 | H7: 0.016354321 | I7: 0.016068063 | J7: 0.015710847 | K7: 0.015408002 | L7: 0.015208312 | M7: 0.014798541 | N7: 0.014491406 | O7: 0.01414271 | P7: 0.013822993 | Q7: 0.013541147 | R7: 0.013207497 | S7: 0.013355678 | T7: 0.013317424 | U7: 0.013250498 | V7: 0.012491633 | W7: 0.012351322 | X7: 0.012227638 | Y7: 0.012234737 | Z7: 0.012061428 | AA7: 0.011917424 | AB7: 0.011734715 | AC7: 0.011596338 | AD7: 0.011387198 | AE7: 0.011078781 | AF7: 0.011118192 | AG7: 0.011220651 | AH7: 0.011110658 | AI7: 0.010993256 | AJ7: 0.010946175 | AK7: 0.010855232 | AL7: 0.01078059 | AM7: 0.010657561 | AN7: 0.010501031 | AO7: 0.010334867 | AP7: 0.010072289 | AQ7: 0.014 | AR7: 0.014 | AS7: 0.014 | AT7: 0.014 | AU7: 0.014 | AV7: 0.014 | AW7: 0.014 | AX7: 0.014 | AY7: 0.014 | AZ7: 0.014 | BA7: 0.014 | BB7: 0.014 | BC7: 0.014 | BD7: 0.014 | BE7: 0.014 | BF7: 0.014 | BG7: 0.014 | BH7: 0.014 | BI7: 0.014 | BJ7: 0.014 | BK7: 0.014 | BL7: 0.014 | BM7: 0.014 | EA7: =LOOKUP(EA$4,$F$4:$BM$4,$F7:$BM7) -> 0.015408002 | EB7: =EA7+(EC7-EA7)/'Input-Stress Parameters'!$J$5 -> 0.016593699 | EC7: =LOOKUP(EC$4,$F$4:$BM$4,$F7:$BM7)*'Calculations - Parameters'!$L$3/'Calculations - Parameters'!$K$3 -> 0.022522183 | ED7: =EC7+(EE7-EC7)/'Input-Stress Parameters'!$J$6 -> 0.023980995 | EE7: =EC7*'Calculations - Parameters'!$M$3/'Calculations - Parameters'!$L$3 -> 0.040027921 | EF7: =ED7 -> 0.023980995 | EG7: =EF7+(EH7-EF7)/MONTH($EH$4-$EF$4) -> #REF! | EH7: =LOOKUP(EH$4,$F$4:$BM$4,$F7:$BM7) -> #REF! | EI7: =EJ7+(EH7-EJ7)/MONTH($EJ$4-$EH$4) -> #REF! | EJ7: =LOOKUP(EJ$4,$F$4:$BM$4,$F7:$BM7) -> 0.011734715
A8: ='Input-Stress Parameters'!$D$15 -> 6 | B8: =('Calculations - Parameters'!L3/'Calculations - Parameters'!K3-1)*('Input-Stress Parameters'!$J$5/12) -> 0.42095399 | C8: =C7+1 -> 6 | F8: =IF(F$1="N",1,(MAX((F11/$B$5),1))) -> 1 | G8: =IF(G1="N",1,(MAX((G11/$B$5),1))) -> 1.0171854 | H8: =IF(H1="N",1,(MAX((H11/$B$5),1))) -> 1.0343707 | I8: =IF(I1="N",1,(MAX((I11/$B$5),1))) -> 1.0515561 | J8: =IF(J1="N",1,(MAX((J11/$B$5),1))) -> 1.0687415 | K8: =IF(K1="N",1,(MAX((K11/$B$5),1))) -> 1.0859268 | L8: =IF(L1="N",1,(MAX((L11/$B$5),1))) -> 1.1031122 | M8: =IF(M1="N",1,(MAX((M11/$B$5),1))) -> 1.1293199 | N8: =IF(N1="N",1,(MAX((N11/$B$5),1))) -> 1.1555276 | ... BM8: =IF(BM1="N",1,(MAX((BM11/$B$5),1))) -> 1
A9: ='Input-Stress Parameters'!$E$16 -> 12 | B9: =('Calculations - Parameters'!M3/'Calculations - Parameters'!K3-1)-('Calculations - Parameters'!L3/'Calculations - Parameters'!K3-1)*('Input-Stress Parameters'!$J$6/12) -> 1.4316533 | C9: =C8+1 -> 7 | D9: HL | E9: Stress | F9: =$F$4 -> 45352 | G9: =EDATE(F9,1) -> 45383 | H9: =EDATE(G9,1) -> 45413 | I9: =EDATE(H9,1) -> 45444 | J9: =EDATE(I9,1) -> 45474 | K9: =EDATE(J9,1) -> 45505 | L9: =EDATE(K9,1) -> 45536 | M9: =EDATE(L9,1) -> 45566 | N9: =EDATE(M9,1) -> 45597 | ... BM9: =EDATE(BL9,1) -> 47150
A10: 24 | B10: =('Calculations - Parameters'!N3/'Calculations - Parameters'!K3-1)*('Input-Stress Parameters'!$J$7/12)-B9-B8 -> -1.3481596 | C10: =C9+1 -> 8 | D10: Stage1 | E10: Stage1 | F10: =F5 -> 0.95964141 | G10: 0.95904141 | H10: 0.95844141 | I10: 0.95784141 | J10: 0.95724141 | K10: 0.95664141 | L10: 0.95604141 | M10: 0.95505141 | N10: 0.95406141 | O10: 0.95307141 | P10: 0.95208141 | Q10: 0.95109141 | R10: 0.95010141 | S10: 0.94853141 | T10: 0.94696141 | U10: 0.94539141 | V10: 0.94382141 | W10: 0.94225141 | X10: 0.92870092 | Y10: 0.94213709 | Z10: 0.94339846 | AA10: 0.94465983 | AB10: 0.9459212 | AC10: 0.94718256 | AD10: 0.94844393 | AE10: 0.9497053 | AF10: 0.95096666 | AG10: 0.95222803 | AH10: 0.9534894 | AI10: 0.95475077 | AJ10: 0.95601213 | AK10: 0.9572735 | AL10: 0.95853487 | AM10: 0.95979623 | AN10: 0.9610576 | AO10: 0.96231897 | AP10: 0.96358034 | AQ10: =1-AQ11-AQ12 -> 0.956 | AR10: =1-AR11-AR12 -> 0.956 | AS10: =1-AS11-AS12 -> 0.956 | AT10: =1-AT11-AT12 -> 0.956 | AU10: =1-AU11-AU12 -> 0.956 | AV10: =1-AV11-AV12 -> 0.956 | AW10: =1-AW11-AW12 -> 0.956 | AX10: =1-AX11-AX12 -> 0.956 | ... BM10: =1-BM11-BM12 -> 0.956
A11: ='Input-Stress Parameters'!$E$18+1 -> 10 | B11: =B6-('Calculations - Parameters'!N3/'Calculations - Parameters'!K3)*B7 -> -0.014845208 | C11: =C10+1 -> 9 | D11: Stage2 | E11: Stage2 | F11: =IF(F$1="N",F6,IF(F$2="SL1P",(E11+$B5*($B8/$A8)),IF(F$2="SL2P",(E11+$B5*($B9/$A9)),IF(F$2="SL3P",(E11+$B5*($B10/$A10)),IF(F$2="SL4P",(E11+($B12/$A12))))))) -> 0.023275618 | G11: 0.023675618 | H11: 0.024075618 | I11: 0.024475618 | J11: 0.024875618 | K11: 0.025275618 | L11: 0.025675618 | M11: 0.026285618 | N11: 0.026895618 | O11: 0.027505618 | P11: 0.028115618 | Q11: 0.028725618 | R11: 0.029335618 | S11: 0.030345618 | T11: 0.031355618 | U11: 0.032365618 | V11: 0.033375618 | W11: 0.034385618 | X11: 0.035378939 | Y11: 0.034654659 | Z11: 0.03393038 | AA11: 0.0332061 | AB11: 0.032481821 | AC11: 0.031757541 | AD11: 0.031033261 | AE11: 0.030308982 | AF11: 0.029584702 | AG11: 0.028860423 | AH11: 0.028136143 | AI11: 0.027411864 | AJ11: 0.026687584 | AK11: 0.025963304 | AL11: 0.025239025 | AM11: 0.024514745 | AN11: 0.023790466 | AO11: 0.023066186 | AP11: 0.022341906 | AQ11: =IF(AQ$1="N",AQ6,IF(AQ$2="SL1P",(AP11+$B5*($B8/$A8)),IF(AQ$2="SL2P",(AP11+$B5*($B9/$A9)),IF(AQ$2="SL3P",(AP11+$B5*($B10/$A10)),IF(AQ$2="SL4P",(AP11+($B12/$A12))))))) -> 0.03 | AR11: =IF(AR$1="N",AR6,IF(AR$2="SL1P",(AQ11+$B5*($B8/$A8)),IF(AR$2="SL2P",(AQ11+$B5*($B9/$A9)),IF(AR$2="SL3P",(AQ11+$B5*($B10/$A10)),IF(AR$2="SL4P",(AQ11+($B12/$A12))))))) -> 0.03 | AS11: =IF(AS$1="N",AS6,IF(AS$2="SL1P",(AR11+$B5*($B8/$A8)),IF(AS$2="SL2P",(AR11+$B5*($B9/$A9)),IF(AS$2="SL3P",(AR11+$B5*($B10/$A10)),IF(AS$2="SL4P",(AR11+($B12/$A12))))))) -> 0.03 | AT11: =IF(AT$1="N",AT6,IF(AT$2="SL1P",(AS11+$B5*($B8/$A8)),IF(AT$2="SL2P",(AS11+$B5*($B9/$A9)),IF(AT$2="SL3P",(AS11+$B5*($B10/$A10)),IF(AT$2="SL4P",(AS11+($B12/$A12))))))) -> 0.03 | AU11: =IF(AU$1="N",AU6,IF(AU$2="SL1P",(AT11+$B5*($B8/$A8)),IF(AU$2="SL2P",(AT11+$B5*($B9/$A9)),IF(AU$2="SL3P",(AT11+$B5*($B10/$A10)),IF(AU$2="SL4P",(AT11+($B12/$A12))))))) -> 0.03 | AV11: =IF(AV$1="N",AV6,IF(AV$2="SL1P",(AU11+$B5*($B8/$A8)),IF(AV$2="SL2P",(AU11+$B5*($B9/$A9)),IF(AV$2="SL3P",(AU11+$B5*($B10/$A10)),IF(AV$2="SL4P",(AU11+($B12/$A12))))))) -> 0.03 | AW11: =IF(AW$1="N",AW6,IF(AW$2="SL1P",(AV11+$B5*($B8/$A8)),IF(AW$2="SL2P",(AV11+$B5*($B9/$A9)),IF(AW$2="SL3P",(AV11+$B5*($B10/$A10)),IF(AW$2="SL4P",(AV11+($B12/$A12))))))) -> 0.03 | AX11: =IF(AX$1="N",AX6,IF(AX$2="SL1P",(AW11+$B5*($B8/$A8)),IF(AX$2="SL2P",(AW11+$B5*($B9/$A9)),IF(AX$2="SL3P",(AW11+$B5*($B10/$A10)),IF(AX$2="SL4P",(AW11+($B12/$A12))))))) -> 0.03 | ... BM11: =IF(BM$1="N",BM6,IF(BM$2="SL1P",(BL11+$B5*($B8/$A8)),IF(BM$2="SL2P",(BL11+$B5*($B9/$A9)),IF(BM$2="SL3P",(BL11+$B5*($B10/$A10)),IF(BM$2="SL4P",(BL11+($B12/$A12))))))) -> 0.03
A12: =A11 -> 10 | B12: =B4-('Calculations - Parameters'!N3/'Calculations - Parameters'!K3)*B5 -> -0.01702072 | C12: =C11+1 -> 10 | D12: Stage3 | E12: Stage3 | F12: =IF(F$1="N",F7,IF(F$2="SL1P",(E12+$B7*($B8/$A8)),IF(F$2="SL2P",(E12+$B7*($B9/$A9)),IF(F$2="SL3P",(E12+$B7*($B10/$A10)),IF(F$2="SL4P",(E12+($B11/$A11))))))) -> 0.017082974 | G12: 0.017282974 | H12: 0.017482974 | I12: 0.017682974 | J12: 0.017882974 | K12: 0.018082974 | L12: 0.018282974 | M12: 0.018662974 | N12: 0.019042974 | O12: 0.019422974 | P12: 0.019802974 | Q12: 0.020182974 | R12: 0.020562974 | S12: 0.021122974 | T12: 0.021682974 | U12: 0.022242974 | V12: 0.022802974 | W12: 0.023362974 | X12: 0.023745333 | Y12: 0.023208246 | Z12: 0.022671158 | AA12: 0.022134071 | AB12: 0.021596983 | AC12: 0.021059895 | AD12: 0.020522808 | AE12: 0.01998572 | AF12: 0.019448633 | AG12: 0.018911545 | AH12: 0.018374458 | AI12: 0.01783737 | AJ12: 0.017300283 | AK12: 0.016763195 | AL12: 0.016226108 | AM12: 0.01568902 | AN12: 0.015151932 | AO12: 0.014614845 | AP12: 0.014077757 | AQ12: =IF(AQ$1="N",AQ7,IF(AQ$2="SL1P",(AP12+$B7*($B8/$A8)),IF(AQ$2="SL2P",(AP12+$B7*($B9/$A9)),IF(AQ$2="SL3P",(AP12+$B7*($B10/$A10)),IF(AQ$2="SL4P",(AP12+($B11/$A11))))))) -> 0.014 | AR12: =IF(AR$1="N",AR7,IF(AR$2="SL1P",(AQ12+$B7*($B8/$A8)),IF(AR$2="SL2P",(AQ12+$B7*($B9/$A9)),IF(AR$2="SL3P",(AQ12+$B7*($B10/$A10)),IF(AR$2="SL4P",(AQ12+($B11/$A11))))))) -> 0.014 | AS12: =IF(AS$1="N",AS7,IF(AS$2="SL1P",(AR12+$B7*($B8/$A8)),IF(AS$2="SL2P",(AR12+$B7*($B9/$A9)),IF(AS$2="SL3P",(AR12+$B7*($B10/$A10)),IF(AS$2="SL4P",(AR12+($B11/$A11))))))) -> 0.014 | AT12: =IF(AT$1="N",AT7,IF(AT$2="SL1P",(AS12+$B7*($B8/$A8)),IF(AT$2="SL2P",(AS12+$B7*($B9/$A9)),IF(AT$2="SL3P",(AS12+$B7*($B10/$A10)),IF(AT$2="SL4P",(AS12+($B11/$A11))))))) -> 0.014 | AU12: =IF(AU$1="N",AU7,IF(AU$2="SL1P",(AT12+$B7*($B8/$A8)),IF(AU$2="SL2P",(AT12+$B7*($B9/$A9)),IF(AU$2="SL3P",(AT12+$B7*($B10/$A10)),IF(AU$2="SL4P",(AT12+($B11/$A11))))))) -> 0.014 | AV12: =IF(AV$1="N",AV7,IF(AV$2="SL1P",(AU12+$B7*($B8/$A8)),IF(AV$2="SL2P",(AU12+$B7*($B9/$A9)),IF(AV$2="SL3P",(AU12+$B7*($B10/$A10)),IF(AV$2="SL4P",(AU12+($B11/$A11))))))) -> 0.014 | AW12: =IF(AW$1="N",AW7,IF(AW$2="SL1P",(AV12+$B7*($B8/$A8)),IF(AW$2="SL2P",(AV12+$B7*($B9/$A9)),IF(AW$2="SL3P",(AV12+$B7*($B10/$A10)),IF(AW$2="SL4P",(AV12+($B11/$A11))))))) -> 0.014 | AX12: =IF(AX$1="N",AX7,IF(AX$2="SL1P",(AW12+$B7*($B8/$A8)),IF(AX$2="SL2P",(AW12+$B7*($B9/$A9)),IF(AX$2="SL3P",(AW12+$B7*($B10/$A10)),IF(AX$2="SL4P",(AW12+($B11/$A11))))))) -> 0.014 | ... BM12: =IF(BM$1="N",BM7,IF(BM$2="SL1P",(BL12+$B7*($B8/$A8)),IF(BM$2="SL2P",(BL12+$B7*($B9/$A9)),IF(BM$2="SL3P",(BL12+$B7*($B10/$A10)),IF(BM$2="SL4P",(BL12+($B11/$A11))))))) -> 0.014
C13: =C12+1 -> 11
A14: SLX | B14: =HLOOKUP(A14,$F$3:$BM$95,C16,0) -> 0.026267928 | C14: =C13+1 -> 12 | D14: LAP | E14: Plan | F14: =$F$4 -> 45352 | G14: =EDATE(F14,1) -> 45383 | H14: =EDATE(G14,1) -> 45413 | I14: =EDATE(H14,1) -> 45444 | J14: =EDATE(I14,1) -> 45474 | K14: =EDATE(J14,1) -> 45505 | L14: =EDATE(K14,1) -> 45536 | M14: =EDATE(L14,1) -> 45566 | N14: =EDATE(M14,1) -> 45597 | ... BM14: =EDATE(BL14,1) -> 47150
A15: SL0 | B15: =HLOOKUP(A15,$F$3:$BM$95,C16,0) -> 0.04310385 | C15: =C14+1 -> 13 | D15: Stage1 | E15: Stage1 | F15: 0.92406923 | G15: 0.92599899 | H15: 0.92836357 | I15: 0.92382127 | J15: 0.92760685 | K15: 0.93148123 | L15: 0.92903584 | M15: 0.93358845 | N15: 0.93799925 | O15: 0.9357906 | P15: 0.94226332 | Q15: 0.93943701 | R15: 0.94449985 | S15: 0.94602287 | T15: 0.94775422 | U15: 0.94478949 | V15: 0.94724047 | W15: 0.95001465 | X15: 0.94837849 | Y15: 0.95100118 | Z15: 0.9539392 | AA15: 0.95233633 | AB15: 0.95586909 | AC15: 0.95463241 | AD15: 0.95786358 | AE15: 0.95836648 | AF15: 0.95890312 | AG15: 0.95571302 | AH15: 0.95704834 | AI15: 0.95843157 | AJ15: 0.95620372 | AK15: 0.95808203 | AL15: 0.96026204 | AM15: 0.95921671 | AN15: 0.96179848 | AO15: 0.96113128 | AP15: 0.96355715 | AQ15: 0.95 | AR15: 0.95 | AS15: 0.95 | AT15: 0.95 | AU15: 0.95 | AV15: 0.95 | AW15: 0.95 | AX15: 0.95 | AY15: 0.95 | AZ15: 0.95 | BA15: 0.95 | BB15: 0.95 | BC15: 0.95 | BD15: 0.95 | BE15: 0.95 | BF15: 0.95 | BG15: 0.95 | BH15: 0.95 | BI15: 0.95 | BJ15: 0.95 | BK15: 0.95 | BL15: 0.95 | BM15: 0.95
A16: SLX | B16: =HLOOKUP(A16,$F$3:$BM$95,C17,0) -> 0.015650038 | C16: =C15+1 -> 14 | D16: Stage2 | E16: Stage2 | F16: 0.04310385 | G16: 0.042250866 | H16: 0.040733634 | I16: 0.043122789 | J16: 0.040777533 | K16: 0.038393706 | L16: 0.039772147 | M16: 0.036880475 | N16: 0.034203958 | O16: 0.03604721 | P16: 0.032883895 | Q16: 0.034342781 | R16: 0.03140982 | S16: 0.030793236 | T16: 0.030165175 | U16: 0.032621403 | V16: 0.03137246 | W16: 0.0299914 | X16: 0.031358401 | Y16: 0.029677526 | Z16: 0.027788385 | AA16: 0.028746708 | AB16: 0.026507144 | AC16: 0.02717084 | AD16: 0.025151508 | AE16: 0.025087812 | AF16: 0.025050298 | AG16: 0.02742382 | AH16: 0.026818048 | AI16: 0.026010187 | AJ16: 0.027430091 | AK16: 0.026267928 | AL16: 0.024861092 | AM16: 0.025424314 | AN16: 0.02366022 | AO16: 0.023967756 | AP16: 0.022430452 | AQ16: 0.03 | AR16: 0.03 | AS16: 0.03 | AT16: 0.03 | AU16: 0.03 | AV16: 0.03 | AW16: 0.03 | AX16: 0.03 | AY16: 0.03 | AZ16: 0.03 | BA16: 0.03 | BB16: 0.03 | BC16: 0.03 | BD16: 0.03 | BE16: 0.03 | BF16: 0.03 | BG16: 0.03 | BH16: 0.03 | BI16: 0.03 | BJ16: 0.03 | BK16: 0.03 | BL16: 0.03 | BM16: 0.03
A17: SL0 | B17: =HLOOKUP(A17,$F$3:$BM$95,C17,0) -> 0.032826925 | C17: =C16+1 -> 15 | D17: Stage3 | E17: Stage3 | F17: 0.032826925 | G17: 0.031750142 | H17: 0.030902798 | I17: 0.033055944 | J17: 0.031615619 | K17: 0.030125064 | L17: 0.031192014 | M17: 0.029531077 | N17: 0.02779679 | O17: 0.028162194 | P17: 0.02485278 | Q17: 0.026220206 | R17: 0.024090331 | S17: 0.023183891 | T17: 0.022080605 | U17: 0.022589106 | V17: 0.021387067 | W17: 0.019993954 | X17: 0.020263105 | Y17: 0.019321292 | Z17: 0.018272419 | AA17: 0.018916961 | AB17: 0.017623768 | AC17: 0.01819675 | AD17: 0.016984914 | AE17: 0.016545707 | AF17: 0.016046577 | AG17: 0.016863161 | AH17: 0.016133613 | AI17: 0.015558245 | AJ17: 0.016366184 | AK17: 0.015650038 | AL17: 0.01487687 | AM17: 0.01535898 | AN17: 0.014541303 | AO17: 0.014900962 | AP17: 0.014012394 | AQ17: 0.014 | AR17: 0.014 | AS17: 0.014 | AT17: 0.014 | AU17: 0.014 | AV17: 0.014 | AW17: 0.014 | AX17: 0.014 | AY17: 0.014 | AZ17: 0.014 | BA17: 0.014 | BB17: 0.014 | BC17: 0.014 | BD17: 0.014 | BE17: 0.014 | BF17: 0.014 | BG17: 0.014 | BH17: 0.014 | BI17: 0.014 | BJ17: 0.014 | BK17: 0.014 | BL17: 0.014 | BM17: 0.014
A18: ='Input-Stress Parameters'!$D$15 -> 6 | B18: =('Calculations - Parameters'!L4/'Calculations - Parameters'!K4-1)*('Input-Stress Parameters'!$J$5/12) -> 0.37648303 | C18: =C17+1 -> 16 | F18: =IF(F$1="N",1,(MAX((F21/$B$15),1))) -> 1 | G18: =IF(G$1="N",1,(MAX((G21/$B$15),1))) -> 1.0092799 | H18: =IF(H$1="N",1,(MAX((H21/$B$15),1))) -> 1.0185598 | I18: =IF(I$1="N",1,(MAX((I21/$B$15),1))) -> 1.0278397 | J18: =IF(J$1="N",1,(MAX((J21/$B$15),1))) -> 1.0371197 | K18: =IF(K$1="N",1,(MAX((K21/$B$15),1))) -> 1.0463996 | L18: =IF(L$1="N",1,(MAX((L21/$B$15),1))) -> 1.0556795 | M18: =IF(M$1="N",1,(MAX((M21/$B$15),1))) -> 1.0707593 | ... BM18: =IF(BM$1="N",1,(MAX((BM21/$B$15),1))) -> 1
A19: ='Input-Stress Parameters'!$E$16 -> 12 | B19: =('Calculations - Parameters'!M4/'Calculations - Parameters'!K4-1)-('Calculations - Parameters'!L4/'Calculations - Parameters'!K4-1)*('Input-Stress Parameters'!$J$6/12) -> 1.0634748 | C19: =C18+1 -> 17 | D19: LAP | E19: Stress | F19: =$F$4 -> 45352 | G19: =EDATE(F19,1) -> 45383 | H19: =EDATE(G19,1) -> 45413 | I19: =EDATE(H19,1) -> 45444 | J19: =EDATE(I19,1) -> 45474 | K19: =EDATE(J19,1) -> 45505 | L19: =EDATE(K19,1) -> 45536 | M19: =EDATE(L19,1) -> 45566 | N19: =EDATE(M19,1) -> 45597 | ... BM19: =EDATE(BL19,1) -> 47150
A20: 24 | B20: =('Calculations - Parameters'!N4/'Calculations - Parameters'!K4-1)*('Input-Stress Parameters'!$J$7/12)-B19-B18 -> -0.95567744 | C20: =C19+1 -> 18 | D20: Stage1 | E20: Stage1 | F20: =1-F21-F22 -> 0.92406923 | G20: 0.92255923 | H20: 0.92104923 | I20: 0.91953923 | J20: 0.91802923 | K20: 0.91651923 | L20: 0.91500923 | M20: 0.91271923 | N20: 0.91042923 | O20: 0.90813923 | P20: 0.90584923 | Q20: 0.90355923 | R20: 0.90126923 | S20: 0.89744923 | T20: 0.89362923 | U20: 0.88980923 | V20: 0.88598923 | W20: 0.88216923 | X20: 0.87791008 | Y20: 0.88163493 | Z20: 0.88495872 | AA20: 0.88828251 | AB20: 0.89160629 | AC20: 0.89493008 | AD20: 0.89825387 | AE20: 0.90157765 | AF20: 0.90490144 | AG20: 0.90822523 | AH20: 0.91154902 | AI20: 0.9148728 | AJ20: 0.91819659 | AK20: 0.92186503 | AL20: 0.92553347 | AM20: 0.92920191 | AN20: 0.93287035 | AO20: 0.9365388 | AP20: 0.94020724 | AQ20: =1-AQ21-AQ22 -> 0.956 | AR20: =1-AR21-AR22 -> 0.956 | AS20: =1-AS21-AS22 -> 0.956 | AT20: =1-AT21-AT22 -> 0.956 | AU20: =1-AU21-AU22 -> 0.956 | AV20: =1-AV21-AV22 -> 0.956 | AW20: =1-AW21-AW22 -> 0.956 | AX20: =1-AX21-AX22 -> 0.956 | ... BM20: =1-BM21-BM22 -> 0.956
A21: ='Input-Stress Parameters'!$E$18+1 -> 10 | B21: =B16-('Calculations - Parameters'!N4/'Calculations - Parameters'!K4)*B17 -> -0.033074322 | C21: =C20+1 -> 19 | D21: Stage2 | E21: Stage2 | F21: =IF(F$1="N",F16,IF(F$2="SL1P",(E21+$B15*($B18/$A18)),IF(F$2="SL2P",(E21+$B15*($B19/$A19)),IF(F$2="SL3P",(E21+$B15*($B20/$A20)),IF(F$2="SL4P",(E21+($B22/$A22))))))) -> 0.04310385 | G21: 0.04350385 | H21: 0.04390385 | I21: 0.04430385 | J21: 0.04470385 | K21: 0.04510385 | L21: 0.04550385 | M21: 0.04615385 | N21: 0.04680385 | O21: 0.04745385 | P21: 0.04810385 | Q21: 0.04875385 | R21: 0.04940385 | S21: 0.05048385 | T21: 0.05156385 | U21: 0.05264385 | V21: 0.05372385 | W21: 0.05480385 | X21: 0.056035004 | Y21: 0.05479471 | Z21: 0.053554415 | AA21: 0.05231412 | AB21: 0.051073825 | AC21: 0.04983353 | AD21: 0.048593235 | AE21: 0.047352941 | AF21: 0.046112646 | AG21: 0.044872351 | AH21: 0.043632056 | AI21: 0.042391761 | AJ21: 0.041151466 | AK21: 0.039566517 | AL21: 0.037981568 | AM21: 0.036396619 | AN21: 0.03481167 | AO21: 0.033226721 | AP21: 0.031641772 | AQ21: =IF(AQ$1="N",AQ16,IF(AQ$2="SL1P",(AP21+$B15*($B18/$A18)),IF(AQ$2="SL2P",(AP21+$B15*($B19/$A19)),IF(AQ$2="SL3P",(AP21+$B15*($B20/$A20)),IF(AQ$2="SL4P",(AP21+($B22/$A22))))))) -> 0.03 | AR21: =IF(AR$1="N",AR16,IF(AR$2="SL1P",(AQ21+$B15*($B18/$A18)),IF(AR$2="SL2P",(AQ21+$B15*($B19/$A19)),IF(AR$2="SL3P",(AQ21+$B15*($B20/$A20)),IF(AR$2="SL4P",(AQ21+($B22/$A22))))))) -> 0.03 | AS21: =IF(AS$1="N",AS16,IF(AS$2="SL1P",(AR21+$B15*($B18/$A18)),IF(AS$2="SL2P",(AR21+$B15*($B19/$A19)),IF(AS$2="SL3P",(AR21+$B15*($B20/$A20)),IF(AS$2="SL4P",(AR21+($B22/$A22))))))) -> 0.03 | AT21: =IF(AT$1="N",AT16,IF(AT$2="SL1P",(AS21+$B15*($B18/$A18)),IF(AT$2="SL2P",(AS21+$B15*($B19/$A19)),IF(AT$2="SL3P",(AS21+$B15*($B20/$A20)),IF(AT$2="SL4P",(AS21+($B22/$A22))))))) -> 0.03 | AU21: =IF(AU$1="N",AU16,IF(AU$2="SL1P",(AT21+$B15*($B18/$A18)),IF(AU$2="SL2P",(AT21+$B15*($B19/$A19)),IF(AU$2="SL3P",(AT21+$B15*($B20/$A20)),IF(AU$2="SL4P",(AT21+($B22/$A22))))))) -> 0.03 | AV21: =IF(AV$1="N",AV16,IF(AV$2="SL1P",(AU21+$B15*($B18/$A18)),IF(AV$2="SL2P",(AU21+$B15*($B19/$A19)),IF(AV$2="SL3P",(AU21+$B15*($B20/$A20)),IF(AV$2="SL4P",(AU21+($B22/$A22))))))) -> 0.03 | AW21: =IF(AW$1="N",AW16,IF(AW$2="SL1P",(AV21+$B15*($B18/$A18)),IF(AW$2="SL2P",(AV21+$B15*($B19/$A19)),IF(AW$2="SL3P",(AV21+$B15*($B20/$A20)),IF(AW$2="SL4P",(AV21+($B22/$A22))))))) -> 0.03 | AX21: =IF(AX$1="N",AX16,IF(AX$2="SL1P",(AW21+$B15*($B18/$A18)),IF(AX$2="SL2P",(AW21+$B15*($B19/$A19)),IF(AX$2="SL3P",(AW21+$B15*($B20/$A20)),IF(AX$2="SL4P",(AW21+($B22/$A22))))))) -> 0.03 | ... BM21: =IF(BM$1="N",BM16,IF(BM$2="SL1P",(BL21+$B15*($B18/$A18)),IF(BM$2="SL2P",(BL21+$B15*($B19/$A19)),IF(BM$2="SL3P",(BL21+$B15*($B20/$A20)),IF(BM$2="SL4P",(BL21+($B22/$A22))))))) -> 0.03
A22: =A21 -> 10 | B22: =B14-('Calculations - Parameters'!N4/'Calculations - Parameters'!K4)*B15 -> -0.037710269 | C22: =C21+1 -> 20 | D22: Stage3 | E22: Stage3 | F22: =IF(F$1="N",F17,IF(F$2="SL1P",(E22+$B17*($B18/$A18)),IF(F$2="SL2P",(E22+$B17*($B19/$A19)),IF(F$2="SL3P",(E22+$B17*($B20/$A20)),IF(F$2="SL4P",(E22+($B21/$A21))))))) -> 0.032826925 | G22: 0.033936925 | H22: 0.035046925 | I22: 0.036156925 | J22: 0.037266925 | K22: 0.038376925 | L22: 0.039486925 | M22: 0.041126925 | N22: 0.042766925 | O22: 0.044406925 | P22: 0.046046925 | Q22: 0.047686925 | R22: 0.049326925 | S22: 0.052066925 | T22: 0.054806925 | U22: 0.057546925 | V22: 0.060286925 | W22: 0.063026925 | X22: 0.06565385 | Y22: 0.063570358 | Z22: 0.061486866 | AA22: 0.059403373 | AB22: 0.057319881 | AC22: 0.055236389 | AD22: 0.053152897 | AE22: 0.051069405 | AF22: 0.048985913 | AG22: 0.04690242 | AH22: 0.044818928 | AI22: 0.042735436 | AJ22: 0.040651944 | AK22: 0.038568452 | AL22: 0.03648496 | AM22: 0.034401467 | AN22: 0.032317975 | AO22: 0.030234483 | AP22: 0.028150991 | AQ22: =IF(AQ$1="N",AQ17,IF(AQ$2="SL1P",(AP22+$B17*($B18/$A18)),IF(AQ$2="SL2P",(AP22+$B17*($B19/$A19)),IF(AQ$2="SL3P",(AP22+$B17*($B20/$A20)),IF(AQ$2="SL4P",(AP22+($B21/$A21))))))) -> 0.014 | AR22: =IF(AR$1="N",AR17,IF(AR$2="SL1P",(AQ22+$B17*($B18/$A18)),IF(AR$2="SL2P",(AQ22+$B17*($B19/$A19)),IF(AR$2="SL3P",(AQ22+$B17*($B20/$A20)),IF(AR$2="SL4P",(AQ22+($B21/$A21))))))) -> 0.014 | AS22: =IF(AS$1="N",AS17,IF(AS$2="SL1P",(AR22+$B17*($B18/$A18)),IF(AS$2="SL2P",(AR22+$B17*($B19/$A19)),IF(AS$2="SL3P",(AR22+$B17*($B20/$A20)),IF(AS$2="SL4P",(AR22+($B21/$A21))))))) -> 0.014 | AT22: =IF(AT$1="N",AT17,IF(AT$2="SL1P",(AS22+$B17*($B18/$A18)),IF(AT$2="SL2P",(AS22+$B17*($B19/$A19)),IF(AT$2="SL3P",(AS22+$B17*($B20/$A20)),IF(AT$2="SL4P",(AS22+($B21/$A21))))))) -> 0.014 | AU22: =IF(AU$1="N",AU17,IF(AU$2="SL1P",(AT22+$B17*($B18/$A18)),IF(AU$2="SL2P",(AT22+$B17*($B19/$A19)),IF(AU$2="SL3P",(AT22+$B17*($B20/$A20)),IF(AU$2="SL4P",(AT22+($B21/$A21))))))) -> 0.014 | AV22: =IF(AV$1="N",AV17,IF(AV$2="SL1P",(AU22+$B17*($B18/$A18)),IF(AV$2="SL2P",(AU22+$B17*($B19/$A19)),IF(AV$2="SL3P",(AU22+$B17*($B20/$A20)),IF(AV$2="SL4P",(AU22+($B21/$A21))))))) -> 0.014 | AW22: =IF(AW$1="N",AW17,IF(AW$2="SL1P",(AV22+$B17*($B18/$A18)),IF(AW$2="SL2P",(AV22+$B17*($B19/$A19)),IF(AW$2="SL3P",(AV22+$B17*($B20/$A20)),IF(AW$2="SL4P",(AV22+($B21/$A21))))))) -> 0.014 | AX22: =IF(AX$1="N",AX17,IF(AX$2="SL1P",(AW22+$B17*($B18/$A18)),IF(AX$2="SL2P",(AW22+$B17*($B19/$A19)),IF(AX$2="SL3P",(AW22+$B17*($B20/$A20)),IF(AX$2="SL4P",(AW22+($B21/$A21))))))) -> 0.014 | ... BM22: =IF(BM$1="N",BM17,IF(BM$2="SL1P",(BL22+$B17*($B18/$A18)),IF(BM$2="SL2P",(BL22+$B17*($B19/$A19)),IF(BM$2="SL3P",(BL22+$B17*($B20/$A20)),IF(BM$2="SL4P",(BL22+($B21/$A21))))))) -> 0.014
C23: =C22+1 -> 21
A24: SLX | B24: =HLOOKUP(A24,$F$3:$BM$95,C26,0) -> 0 | C24: =C23+1 -> 22 | D24: DF | E24: Plan | F24: =$F$4 -> 45352 | G24: =EDATE(F24,1) -> 45383 | H24: =EDATE(G24,1) -> 45413 | I24: =EDATE(H24,1) -> 45444 | J24: =EDATE(I24,1) -> 45474 | K24: =EDATE(J24,1) -> 45505 | L24: =EDATE(K24,1) -> 45536 | M24: =EDATE(L24,1) -> 45566 | N24: =EDATE(M24,1) -> 45597 | ... BM24: =EDATE(BL24,1) -> 47150
A25: SL0 | B25: =HLOOKUP(A25,$F$3:$BM$95,C26,0) -> 0 | C25: =C24+1 -> 23 | D25: Stage1 | E25: Stage1 | F25: 0.99884935 | G25: 0.99884404 | H25: 0.99884674 | I25: 0.99885683 | J25: 0.9988771 | K25: 0.99890588 | L25: 0.99893803 | M25: 0.99897256 | N25: 0.99900291 | O25: 0.99903512 | P25: 0.99906845 | Q25: 0.99909996 | R25: 0.99914686 | S25: 0.99913593 | T25: 0.99913056 | U25: 0.99913059 | V25: 0.99913816 | W25: 0.99915242 | X25: 0.99917 | Y25: 0.99919024 | Z25: 0.9992083 | AA25: 0.9992285 | AB25: 0.99925029 | AC25: 0.99927139 | AD25: 0.99930499 | AE25: 0.99929355 | AF25: 0.99928642 | AG25: 0.99928359 | AH25: 0.99928682 | AI25: 0.99929558 | AJ25: 0.99930728 | AK25: 0.99932144 | AL25: 0.99933418 | AM25: 0.99934894 | AN25: 0.99936529 | AO25: 0.99938133 | AP25: 0.99940798 | AQ25: 1 | AR25: 1 | AS25: 1 | AT25: 1 | AU25: 1 | AV25: 1 | AW25: 1 | AX25: 1 | AY25: 1 | AZ25: 1 | BA25: 1 | BB25: 1 | BC25: 1 | BD25: 1 | BE25: 1 | BF25: 1 | BG25: 1 | BH25: 1 | BI25: 1 | BJ25: 1 | BK25: 1 | BL25: 1 | BM25: 1
A26: SLX | B26: =HLOOKUP(A26,$F$3:$BM$95,C27,0) -> 0.00067855681 | C26: =C25+1 -> 24 | D26: Stage2 | E26: Stage2 | F26: 0 | G26: 0 | H26: 0 | I26: 0 | J26: 0 | K26: 0 | L26: 0 | M26: 0 | N26: 0 | O26: 0 | P26: 0 | Q26: 0 | R26: 0 | S26: 0 | T26: 0 | U26: 0 | V26: 0 | W26: 0 | X26: 0 | Y26: 0 | Z26: 0 | AA26: 0 | AB26: 0 | AC26: 0 | AD26: 0 | AE26: 0 | AF26: 0 | AG26: 0 | AH26: 0 | AI26: 0 | AJ26: 0 | AK26: 0 | AL26: 0 | AM26: 0 | AN26: 0 | AO26: 0 | AP26: 0 | AQ26: 0 | AR26: 0 | AS26: 0 | AT26: 0 | AU26: 0 | AV26: 0 | AW26: 0 | AX26: 0 | AY26: 0 | AZ26: 0 | BA26: 0 | BB26: 0 | BC26: 0 | BD26: 0 | BE26: 0 | BF26: 0 | BG26: 0 | BH26: 0 | BI26: 0 | BJ26: 0 | BK26: 0 | BL26: 0 | BM26: 0
A27: SL0 | B27: =HLOOKUP(A27,$F$3:$BM$95,C27,0) -> 0.0011506472 | C27: =C26+1 -> 25 | D27: Stage3 | E27: Stage3 | F27: 0.0011506472 | G27: 0.0011559557 | H27: 0.0011532589 | I27: 0.0011431724 | J27: 0.0011228957 | K27: 0.0010941244 | L27: 0.0010619715 | M27: 0.0010274351 | N27: 0.00099709095 | O27: 0.00096488484 | P27: 0.00093155262 | Q27: 0.00090004332 | R27: 0.00085314409 | S27: 0.00086406637 | T27: 0.00086943602 | U27: 0.0008694143 | V27: 0.0008618442 | W27: 0.00084757785 | X27: 0.00082999545 | Y27: 0.00080976154 | Z27: 0.00079170064 | AA27: 0.00077149535 | AB27: 0.00074970529 | AC27: 0.00072861327 | AD27: 0.00069500851 | AE27: 0.00070645184 | AF27: 0.00071357637 | AG27: 0.0007164128 | AH27: 0.00071318201 | AI27: 0.00070442412 | AJ27: 0.00069271772 | AK27: 0.00067855681 | AL27: 0.00066581984 | AM27: 0.00065105602 | AN27: 0.00063471338 | AO27: 0.0006186736 | AP27: 0.00059202029 | AQ27: 0 | AR27: 0 | AS27: 0 | AT27: 0 | AU27: 0 | AV27: 0 | AW27: 0 | AX27: 0 | AY27: 0 | AZ27: 0 | BA27: 0 | BB27: 0 | BC27: 0 | BD27: 0 | BE27: 0 | BF27: 0 | BG27: 0 | BH27: 0 | BI27: 0 | BJ27: 0 | BK27: 0 | BL27: 0 | BM27: 0
A28: ='Input-Stress Parameters'!$D$15 -> 6 | B28: =IFERROR(('Calculations - Parameters'!L5/'Calculations - Parameters'!K5-1)*('Input-Stress Parameters'!$J$5/12),0) -> 0 | C28: =C27+1 -> 26 | F28: =IF(F$1="N",1,(MAX((F31/$B$25),1))) -> 1 | G28: =IFERROR(IF(G$1="N",1,(MAX((G31/$B$25),1))),100%) -> 1 | H28: =IFERROR(IF(H$1="N",1,(MAX((H31/$B$25),1))),100%) -> 1 | I28: =IFERROR(IF(I$1="N",1,(MAX((I31/$B$25),1))),100%) -> 1 | J28: =IFERROR(IF(J$1="N",1,(MAX((J31/$B$25),1))),100%) -> 1 | K28: =IFERROR(IF(K$1="N",1,(MAX((K31/$B$25),1))),100%) -> 1 | L28: =IFERROR(IF(L$1="N",1,(MAX((L31/$B$25),1))),100%) -> 1 | M28: =IFERROR(IF(M$1="N",1,(MAX((M31/$B$25),1))),100%) -> 1 | N28: =IFERROR(IF(N$1="N",1,(MAX((N31/$B$25),1))),100%) -> 1 | ... AP28: =IFERROR(IF(AP$1="N",1,(MAX((AP31/$B$25),1))),100%) -> 1 | AQ28: =IF(AQ$1="N",1,(MAX((AQ31/$B$25),1))) -> 1 | AR28: =IF(AR$1="N",1,(MAX((AR31/$B$25),1))) -> 1 | AS28: =IF(AS$1="N",1,(MAX((AS31/$B$25),1))) -> 1 | AT28: =IF(AT$1="N",1,(MAX((AT31/$B$25),1))) -> 1 | AU28: =IF(AU$1="N",1,(MAX((AU31/$B$25),1))) -> 1 | AV28: =IF(AV$1="N",1,(MAX((AV31/$B$25),1))) -> 1 | AW28: =IF(AW$1="N",1,(MAX((AW31/$B$25),1))) -> 1 | AX28: =IF(AX$1="N",1,(MAX((AX31/$B$25),1))) -> 1 | ... BM28: =IF(BM$1="N",1,(MAX((BM31/$B$25),1))) -> 1
A29: ='Input-Stress Parameters'!$E$16 -> 12 | B29: =('Calculations - Parameters'!M5/'Calculations - Parameters'!K5-1)-('Calculations - Parameters'!L5/'Calculations - Parameters'!K5-1)*('Input-Stress Parameters'!$J$6/12) -> #VALUE! | C29: =C28+1 -> 27 | D29: DF | E29: Stress | F29: =$F$4 -> 45352 | G29: =EDATE(F29,1) -> 45383 | H29: =EDATE(G29,1) -> 45413 | I29: =EDATE(H29,1) -> 45444 | J29: =EDATE(I29,1) -> 45474 | K29: =EDATE(J29,1) -> 45505 | L29: =EDATE(K29,1) -> 45536 | M29: =EDATE(L29,1) -> 45566 | N29: =EDATE(M29,1) -> 45597 | ... BM29: =EDATE(BL29,1) -> 47150
A30: ='Input-Stress Parameters'!$E$17 -> 3 | B30: =('Calculations - Parameters'!N5/'Calculations - Parameters'!K5-1)*('Input-Stress Parameters'!$J$7/12)-B29-B28 -> #VALUE! | C30: =C29+1 -> 28 | D30: Stage1 | E30: Stage1 | F30: =1-F31-F32 -> 0.99884935 | G30: =1-G31-G32 -> 0.99884404 | H30: =1-H31-H32 -> 0.99884674 | I30: =1-I31-I32 -> 0.99885683 | J30: =1-J31-J32 -> 0.9988771 | K30: =1-K31-K32 -> 0.99890588 | L30: =1-L31-L32 -> 0.99893803 | M30: =1-M31-M32 -> 0.99897256 | ... BM30: =1-BM31-BM32 -> 1
A31: ='Input-Stress Parameters'!$E$18+1 -> 10 | B31: =B26-('Calculations - Parameters'!N5/'Calculations - Parameters'!K5)*B27 -> #VALUE! | C31: =C30+1 -> 29 | D31: Stage2 | E31: Stage2 | F31: =F26 -> 0 | G31: =G26 -> 0 | H31: =H26 -> 0 | I31: =I26 -> 0 | J31: =J26 -> 0 | K31: =K26 -> 0 | L31: =L26 -> 0 | M31: =M26 -> 0 | ... AP31: =AP26 -> 0 | AQ31: =IFERROR(IF(AQ$1="N",AQ26,IF(AQ$2="SL1P",(AP31+$B27*($B28/$A28)),IF(AQ$2="SL2P",(AP31+$B25*($B29/$A29)),IF(AQ$2="SL3P",(AP31+$B25*($B30/$A30)),IF(AQ$2="SL4P",(AP31+($B32/$A32))))))),AQ26) -> 0 | AR31: =IFERROR(IF(AR$1="N",AR26,IF(AR$2="SL1P",(AQ31+$B27*($B28/$A28)),IF(AR$2="SL2P",(AQ31+$B25*($B29/$A29)),IF(AR$2="SL3P",(AQ31+$B25*($B30/$A30)),IF(AR$2="SL4P",(AQ31+($B32/$A32))))))),AR26) -> 0 | AS31: =IFERROR(IF(AS$1="N",AS26,IF(AS$2="SL1P",(AR31+$B27*($B28/$A28)),IF(AS$2="SL2P",(AR31+$B25*($B29/$A29)),IF(AS$2="SL3P",(AR31+$B25*($B30/$A30)),IF(AS$2="SL4P",(AR31+($B32/$A32))))))),AS26) -> 0 | AT31: =IFERROR(IF(AT$1="N",AT26,IF(AT$2="SL1P",(AS31+$B27*($B28/$A28)),IF(AT$2="SL2P",(AS31+$B25*($B29/$A29)),IF(AT$2="SL3P",(AS31+$B25*($B30/$A30)),IF(AT$2="SL4P",(AS31+($B32/$A32))))))),AT26) -> 0 | AU31: =IFERROR(IF(AU$1="N",AU26,IF(AU$2="SL1P",(AT31+$B27*($B28/$A28)),IF(AU$2="SL2P",(AT31+$B25*($B29/$A29)),IF(AU$2="SL3P",(AT31+$B25*($B30/$A30)),IF(AU$2="SL4P",(AT31+($B32/$A32))))))),AU26) -> 0 | AV31: =IFERROR(IF(AV$1="N",AV26,IF(AV$2="SL1P",(AU31+$B27*($B28/$A28)),IF(AV$2="SL2P",(AU31+$B25*($B29/$A29)),IF(AV$2="SL3P",(AU31+$B25*($B30/$A30)),IF(AV$2="SL4P",(AU31+($B32/$A32))))))),AV26) -> 0 | AW31: =IFERROR(IF(AW$1="N",AW26,IF(AW$2="SL1P",(AV31+$B27*($B28/$A28)),IF(AW$2="SL2P",(AV31+$B25*($B29/$A29)),IF(AW$2="SL3P",(AV31+$B25*($B30/$A30)),IF(AW$2="SL4P",(AV31+($B32/$A32))))))),AW26) -> 0 | AX31: =IFERROR(IF(AX$1="N",AX26,IF(AX$2="SL1P",(AW31+$B27*($B28/$A28)),IF(AX$2="SL2P",(AW31+$B25*($B29/$A29)),IF(AX$2="SL3P",(AW31+$B25*($B30/$A30)),IF(AX$2="SL4P",(AW31+($B32/$A32))))))),AX26) -> 0 | ... BM31: =IFERROR(IF(BM$1="N",BM26,IF(BM$2="SL1P",(BL31+$B27*($B28/$A28)),IF(BM$2="SL2P",(BL31+$B25*($B29/$A29)),IF(BM$2="SL3P",(BL31+$B25*($B30/$A30)),IF(BM$2="SL4P",(BL31+($B32/$A32))))))),BM26) -> 0
A32: =A31 -> 10 | B32: =B24-('Calculations - Parameters'!N5/'Calculations - Parameters'!K5)*B25 -> #VALUE! | C32: =C31+1 -> 30 | D32: Stage3 | E32: Stage3 | F32: =F27 -> 0.0011506472 | G32: =G27 -> 0.0011559557 | H32: =H27 -> 0.0011532589 | I32: =I27 -> 0.0011431724 | J32: =J27 -> 0.0011228957 | K32: =K27 -> 0.0010941244 | L32: =L27 -> 0.0010619715 | M32: =M27 -> 0.0010274351 | ... AP32: =AP27 -> 0.00059202029 | AQ32: =IFERROR(IF(AQ$1="N",AQ27,IF(AQ$2="SL1P",(AP32+$B27*($B28/$A28)),IF(AQ$2="SL2P",(AP32+$B27*($B29/$A29)),IF(AQ$2="SL3P",(AP32+$B27*($B30/$A30)),IF(AQ$2="SL4P",(AP32+($B31/$A31))))))),AQ27) -> 0 | AR32: =IFERROR(IF(AR$1="N",AR27,IF(AR$2="SL1P",(AQ32+$B27*($B28/$A28)),IF(AR$2="SL2P",(AQ32+$B27*($B29/$A29)),IF(AR$2="SL3P",(AQ32+$B27*($B30/$A30)),IF(AR$2="SL4P",(AQ32+($B31/$A31))))))),AR27) -> 0 | AS32: =IFERROR(IF(AS$1="N",AS27,IF(AS$2="SL1P",(AR32+$B27*($B28/$A28)),IF(AS$2="SL2P",(AR32+$B27*($B29/$A29)),IF(AS$2="SL3P",(AR32+$B27*($B30/$A30)),IF(AS$2="SL4P",(AR32+($B31/$A31))))))),AS27) -> 0 | AT32: =IFERROR(IF(AT$1="N",AT27,IF(AT$2="SL1P",(AS32+$B27*($B28/$A28)),IF(AT$2="SL2P",(AS32+$B27*($B29/$A29)),IF(AT$2="SL3P",(AS32+$B27*($B30/$A30)),IF(AT$2="SL4P",(AS32+($B31/$A31))))))),AT27) -> 0 | AU32: =IFERROR(IF(AU$1="N",AU27,IF(AU$2="SL1P",(AT32+$B27*($B28/$A28)),IF(AU$2="SL2P",(AT32+$B27*($B29/$A29)),IF(AU$2="SL3P",(AT32+$B27*($B30/$A30)),IF(AU$2="SL4P",(AT32+($B31/$A31))))))),AU27) -> 0 | AV32: =IFERROR(IF(AV$1="N",AV27,IF(AV$2="SL1P",(AU32+$B27*($B28/$A28)),IF(AV$2="SL2P",(AU32+$B27*($B29/$A29)),IF(AV$2="SL3P",(AU32+$B27*($B30/$A30)),IF(AV$2="SL4P",(AU32+($B31/$A31))))))),AV27) -> 0 | AW32: =IFERROR(IF(AW$1="N",AW27,IF(AW$2="SL1P",(AV32+$B27*($B28/$A28)),IF(AW$2="SL2P",(AV32+$B27*($B29/$A29)),IF(AW$2="SL3P",(AV32+$B27*($B30/$A30)),IF(AW$2="SL4P",(AV32+($B31/$A31))))))),AW27) -> 0 | AX32: =IFERROR(IF(AX$1="N",AX27,IF(AX$2="SL1P",(AW32+$B27*($B28/$A28)),IF(AX$2="SL2P",(AW32+$B27*($B29/$A29)),IF(AX$2="SL3P",(AW32+$B27*($B30/$A30)),IF(AX$2="SL4P",(AW32+($B31/$A31))))))),AX27) -> 0 | ... BM32: =IFERROR(IF(BM$1="N",BM27,IF(BM$2="SL1P",(BL32+$B27*($B28/$A28)),IF(BM$2="SL2P",(BL32+$B27*($B29/$A29)),IF(BM$2="SL3P",(BL32+$B27*($B30/$A30)),IF(BM$2="SL4P",(BL32+($B31/$A31))))))),BM27) -> 0
D34: SMHFC | E34: Plan | F34: =$F$4 -> 45352 | G34: =EDATE(F34,1) -> 45383 | H34: =EDATE(G34,1) -> 45413 | I34: =EDATE(H34,1) -> 45444 | J34: =EDATE(I34,1) -> 45474 | K34: =EDATE(J34,1) -> 45505 | L34: =EDATE(K34,1) -> 45536 | M34: =EDATE(L34,1) -> 45566 | N34: =EDATE(M34,1) -> 45597 | ... AP34: =EDATE(AO34,1) -> 46447
D35: Stage1 | E35: Stage1 | F35: 0.95472592 | G35: 0.9556002 | H35: 0.95624398 | I35: 0.95586421 | J35: 0.95695244 | K35: 0.9581124 | L35: 0.95834751 | M35: 0.95981219 | N35: 0.96130661 | O35: 0.96209236 | P35: 0.96411967 | Q35: 0.9646946 | R35: 0.96630674 | S35: 0.96607796 | T35: 0.96601184 | U35: 0.96539617 | V35: 0.96615707 | W35: 0.96668057 | X35: 0.96669882 | Y35: 0.96727597 | Z35: 0.96818891 | AA35: 0.96854152 | AB35: 0.9697746 | AC35: 0.97025421 | AD35: 0.97136969 | AE35: 0.97122038 | AF35: 0.97103536 | AG35: 0.97018607 | AH35: 0.97025867 | AI35: 0.97046029 | AJ35: 0.97020223 | AK35: 0.9706708 | AL35: 0.97135302 | AM35: 0.97167888 | AN35: 0.97268372 | AO35: 0.97318434 | AP35: 0.97418117
D36: Stage2 | E36: Stage2 | F36: 0.025879438 | G36: 0.02552123 | H36: 0.025158126 | I36: 0.025447215 | J36: 0.024866564 | K36: 0.024205979 | L36: 0.024074884 | M36: 0.02321171 | N36: 0.022264658 | O36: 0.02191449 | P36: 0.020764593 | Q36: 0.020317346 | R36: 0.019326476 | S36: 0.0195703 | T36: 0.019834997 | U36: 0.020501772 | V36: 0.020466695 | W36: 0.020288154 | X36: 0.020394814 | Y36: 0.019964655 | Z36: 0.019349847 | AA36: 0.019053705 | AB36: 0.018170366 | AC36: 0.017754195 | AD36: 0.017002945 | AE36: 0.017416435 | AF36: 0.017636717 | AG36: 0.018303193 | AH36: 0.018418601 | AI36: 0.018388618 | AJ36: 0.018574194 | AK36: 0.018286412 | AL36: 0.017785608 | AM36: 0.017494352 | AN36: 0.016737833 | AO36: 0.016327782 | AP36: 0.015682762
D37: Stage3 | E37: Stage3 | F37: 0.019394642 | G37: 0.01887857 | H37: 0.018597892 | I37: 0.018688571 | J37: 0.018180991 | K37: 0.017681617 | L37: 0.017577607 | M37: 0.016976105 | N37: 0.016428728 | O37: 0.015993154 | P37: 0.015115742 | Q37: 0.014988054 | R37: 0.014366784 | S37: 0.014351744 | T37: 0.014153161 | U37: 0.014102063 | V37: 0.013376237 | W37: 0.013031273 | X37: 0.012906365 | Y37: 0.01275938 | Z37: 0.012461244 | AA37: 0.012404774 | AB37: 0.012055036 | AC37: 0.011991597 | AD37: 0.011627365 | AE37: 0.011363183 | AF37: 0.011327928 | AG37: 0.011510735 | AH37: 0.011322724 | AI37: 0.011151093 | AJ37: 0.011223577 | AK37: 0.011042791 | AL37: 0.010861369 | AM37: 0.010826766 | AN37: 0.010578445 | AO37: 0.01048788 | AP37: 0.010136072
D39: SMHFC | E39: Stress | F39: =$F$4 -> 45352 | G39: =EDATE(F39,1) -> 45383 | H39: =EDATE(G39,1) -> 45413 | I39: =EDATE(H39,1) -> 45444 | J39: =EDATE(I39,1) -> 45474 | K39: =EDATE(J39,1) -> 45505 | L39: =EDATE(K39,1) -> 45536 | M39: =EDATE(L39,1) -> 45566 | N39: =EDATE(M39,1) -> 45597 | ... AP39: =EDATE(AO39,1) -> 46447
D40: Stage1 | E40: Stage1 | F40: ='Calculation - Stagewise ECL'!C76/'Calculation - Stagewise ECL'!C$79 -> 0.95472592 | G40: ='Calculation - Stagewise ECL'!D76/'Calculation - Stagewise ECL'!D$79 -> 0.95361221 | H40: ='Calculation - Stagewise ECL'!E76/'Calculation - Stagewise ECL'!E$79 -> 0.95252791 | I40: ='Calculation - Stagewise ECL'!F76/'Calculation - Stagewise ECL'!F$79 -> 0.95145332 | J40: ='Calculation - Stagewise ECL'!G76/'Calculation - Stagewise ECL'!G$79 -> 0.95039752 | K40: ='Calculation - Stagewise ECL'!H76/'Calculation - Stagewise ECL'!H$79 -> 0.94935028 | L40: ='Calculation - Stagewise ECL'!I76/'Calculation - Stagewise ECL'!I$79 -> 0.94907133 | M40: ='Calculation - Stagewise ECL'!J76/'Calculation - Stagewise ECL'!J$79 -> 0.94758873 | ... AP40: ='Calculation - Stagewise ECL'!AM76/'Calculation - Stagewise ECL'!AM$79 -> 0.96103245
D41: Stage2 | E41: Stage2 | F41: ='Calculation - Stagewise ECL'!C77/'Calculation - Stagewise ECL'!C$79 -> 0.025879438 | G41: ='Calculation - Stagewise ECL'!D77/'Calculation - Stagewise ECL'!D$79 -> 0.026434968 | H41: ='Calculation - Stagewise ECL'!E77/'Calculation - Stagewise ECL'!E$79 -> 0.026975268 | I41: ='Calculation - Stagewise ECL'!F77/'Calculation - Stagewise ECL'!F$79 -> 0.027507411 | J41: ='Calculation - Stagewise ECL'!G77/'Calculation - Stagewise ECL'!G$79 -> 0.028026703 | K41: ='Calculation - Stagewise ECL'!H77/'Calculation - Stagewise ECL'!H$79 -> 0.028539016 | L41: ='Calculation - Stagewise ECL'!I77/'Calculation - Stagewise ECL'!I$79 -> 0.028669073 | M41: ='Calculation - Stagewise ECL'!J77/'Calculation - Stagewise ECL'!J$79 -> 0.029375425 | ... AP41: ='Calculation - Stagewise ECL'!AM77/'Calculation - Stagewise ECL'!AM$79 -> 0.022800786
D42: Stage3 | E42: Stage3 | F42: ='Calculation - Stagewise ECL'!C78/'Calculation - Stagewise ECL'!C$79 -> 0.019394642 | G42: ='Calculation - Stagewise ECL'!D78/'Calculation - Stagewise ECL'!D$79 -> 0.019952825 | H42: ='Calculation - Stagewise ECL'!E78/'Calculation - Stagewise ECL'!E$79 -> 0.02049682 | I42: ='Calculation - Stagewise ECL'!F78/'Calculation - Stagewise ECL'!F$79 -> 0.021039264 | J42: ='Calculation - Stagewise ECL'!G78/'Calculation - Stagewise ECL'!G$79 -> 0.021575778 | K42: ='Calculation - Stagewise ECL'!H78/'Calculation - Stagewise ECL'!H$79 -> 0.022110707 | L42: ='Calculation - Stagewise ECL'!I78/'Calculation - Stagewise ECL'!I$79 -> 0.022259595 | M42: ='Calculation - Stagewise ECL'!J78/'Calculation - Stagewise ECL'!J$79 -> 0.023035844 | ... AP42: ='Calculation - Stagewise ECL'!AM78/'Calculation - Stagewise ECL'!AM$79 -> 0.016166767

Sheet Input - PDLGD
A1: Back - Index | B1: PD | H1: LGD | N1: Downturn LGD | T1: This year's def %
A2: Inputs | B2: Current | C2: Current | D2: Current | E2: Current | F2: Current | G2: Current | H2: Current | I2: Current | J2: Current | K2: Current | L2: Current | M2: Current | N2: Current | O2: Current | P2: Current | Q2: Current | R2: Current | S2: Current | T2: Current | U2: 2023 | V2: 2024 | W2: 2025 | X2: 2026 | Y2: 2027
A3: HL | B3: 0.011137659 | C3: =B3 -> 0.011137659 | D3: =C3 -> 0.011137659 | E3: =D3 -> 0.011137659 | F3: =E3 -> 0.011137659 | G3: =F3 -> 0.011137659 | H3: 0.41511421 | I3: =H3 -> 0.41511421 | J3: =I3 -> 0.41511421 | K3: =J3 -> 0.41511421 | L3: =K3 -> 0.41511421 | M3: =L3 -> 0.41511421 | N3: 0.465 | O3: =N3 -> 0.465 | P3: =O3 -> 0.465 | Q3: =P3 -> 0.465 | R3: =Q3 -> 0.465 | S3: =R3 -> 0.465 | T3: 0.15 | U3: 0.2 | V3: 0.75 | W3: 0.75 | X3: 0.104869 | Y3: 0.104869
A4: LAP | B4: 0.019218244 | C4: =B4 -> 0.019218244 | D4: =C4 -> 0.019218244 | E4: =D4 -> 0.019218244 | F4: =E4 -> 0.019218244 | G4: =F4 -> 0.019218244 | H4: 0.35972496 | I4: =H4 -> 0.35972496 | J4: =I4 -> 0.35972496 | K4: =J4 -> 0.35972496 | L4: =K4 -> 0.35972496 | M4: =L4 -> 0.35972496 | N4: 0.41 | O4: =N4 -> 0.41 | P4: =O4 -> 0.41 | Q4: =P4 -> 0.41 | R4: =Q4 -> 0.41 | S4: =R4 -> 0.41 | T4: 0.15 | U4: 0.2 | V4: 0.75 | W4: 0.75 | X4: 0.104869 | Y4: 0.104869
A5: DF | C5: =B5 -> 0 | D5: =C5 -> 0 | E5: =D5 -> 0 | F5: =E5 -> 0 | G5: =F5 -> 0 | I5: =H5 -> 0 | J5: =I5 -> 0 | K5: =J5 -> 0 | L5: =K5 -> 0 | M5: =L5 -> 0 | O5: =N5 -> 0 | P5: =O5 -> 0 | Q5: =P5 -> 0 | R5: =Q5 -> 0 | S5: =R5 -> 0 | T5: 0 | U5: =T5 -> 0 | V5: =U5 -> 0 | W5: =V5 -> 0 | X5: =W5 -> 0 | Y5: =X5 -> 0
B7: weighted Avg of current bucket marginal PD of 7 years for new and old book

Sheet Calculations - Parameters
A1: Back - Index | B1: Segment | E1: Stress | H1: R | K1: Current PD | L1: PD - Stress | O1: Current LGD | P1: Downturn LGD | Q1: LGD - Stress | T1: NCL plan | X1: NCL stress (base) | AB1: NCL stress | AF1: ECL plan | AI1: ECL % plan | AL1: ECL % stress | AO1: ECL (Pre-WriteOff) | AR1: ECL (Post-WriteOff) | AU1: Stress level | AW1: PD - Stress | AY1: LGD - Stress
A2: Inputs | B2: SL1 | C2: SL2 | D2: SL3 | E2: SL1 | F2: SL2 | G2: SL3 | H2: SL1 | I2: SL2 | J2: SL3 | L2: SL1 | M2: SL2 | N2: SL3 | Q2: SL1 | R2: SL2 | S2: SL3 | T2: SL1 | U2: SL2 | V2: SL31 | W2: SL32 | X2: SL1 | Y2: SL2 | Z2: SL31 | AA2: SL32 | AB2: SL1 | AC2: SL2 | AD2: SL31 | AE2: SL32 | AF2: SL1 | AG2: SL2 | AH2: SL3 | AI2: SL1 | AJ2: SL2 | AK2: SL3 | AL2: SL1 | AM2: SL2 | AN2: SL3 | AO2: SL1 | AP2: SL2 | AQ2: SL3 | AR2: SL1 | AS2: SL2 | AT2: SL3 | AU2: SL31 | AV2: SL32 | AW2: SL31 | AX2: SL32 | AY2: SL31 | AZ2: SL32
A3: HL | B3: Retail | C3: Retail | D3: Retail | E3: ='Input-Stress Parameters'!C$5 -> 7 | F3: ='Input-Stress Parameters'!D$5 -> 25 | G3: ='Input-Stress Parameters'!E$5 -> 5 | H3: =0.03*(1-EXP(-35*$K3))/(1-EXP(-35))+(0.16*(1-(1-EXP(-35*$K3))/(1-EXP(-35)))) -> 0.11803341 | I3: =0.03*(1-EXP(-35*$K3))/(1-EXP(-35))+(0.16*(1-(1-EXP(-35*$K3))/(1-EXP(-35)))) -> 0.11803341 | J3: =0.03*(1-EXP(-35*$K3))/(1-EXP(-35))+(0.16*(1-(1-EXP(-35*$K3))/(1-EXP(-35)))) -> 0.11803341 | K3: ='Input - PDLGD'!B3 -> 0.011137659 | L3: =IFERROR(IF(E3=1,$K3,NORMSDIST((1-H3)^(-0.5)*NORMSINV($K3)+(H3/(1-H3))^0.5*NORMSINV(1-(1/E3)))), "") -> 0.020514544 | M3: =IFERROR(IF(F3=1,$K3,NORMSDIST((1-I3)^(-0.5)*NORMSINV($K3)+(I3/(1-I3))^0.5*NORMSINV(1-(1/F3)))), "") -> 0.03645981 | N3: =IFERROR(IF(G3=1,$K3,NORMSDIST((1-J3)^(-0.5)*NORMSINV($K3)+(J3/(1-J3))^0.5*NORMSINV(1-(1/G3)))), "") -> 0.016756026 | O3: ='Input - PDLGD'!H3 -> 0.41511421 | P3: ='Input - PDLGD'!N3 -> 0.465 | Q3: =IF(E3=1,$O3,IF(E3<=7,($P3+$O3)/2,$P3)) -> 0.44005711 | R3: =IF(F3=1,$O3,IF(F3<=7,($P3+$O3)/2,$P3)) -> 0.465 | S3: =IF(G3=1,$O3,IF(G3<=7,($P3+$O3)/2,$P3)) -> 0.44005711 | T3: =SUMIF('Input - NCL'!$C$2:$BJ$2,T$2,'Input - NCL'!$C11:$BJ11) -> 107.03862 | U3: =SUMIF('Input - NCL'!$C$2:$BJ$2,U$2,'Input - NCL'!$C11:$BJ11) -> 299.21568 | V3: =SUMIF('Input - NCL'!$C$2:$BJ$2,V$2,'Input - NCL'!$C11:$BJ11) -> 117.4876 | W3: =SUMIF('Input - NCL'!$C$2:$BJ$2,W$2,'Input - NCL'!$C11:$BJ11) -> 260.54783 | X3: =SUMIF('Input - NCL'!$C$2:$BJ$2,X$2,'Input - NCL'!$C5:$BJ5) -> 103.22743 | Y3: =SUMIF('Input - NCL'!$C$2:$BJ$2,Y$2,'Input - NCL'!$C5:$BJ5) -> 233.75597 | Z3: =SUMIF('Input - NCL'!$C$2:$BJ$2,Z$2,'Input - NCL'!$C5:$BJ5) -> 77.726215 | AA3: =SUMIF('Input - NCL'!$C$2:$BJ$2,AA$2,'Input - NCL'!$C5:$BJ5) -> 169.06709 | AB3: =IF(X3<=0,X3,IFERROR(X3*'Input - PDLGD'!T3*(L3/'Input - PDLGD'!B3)*(Q3/'Input - PDLGD'!H3)+X3*(1-'Input - PDLGD'!T3)*(Q3/'Input - PDLGD'!H3),"")) -> 123.24954 | AC3: =IF(Y3<=0,Y3,IFERROR(Y3*'Input - PDLGD'!U3*(M3/'Input - PDLGD'!C3)*(R3/'Input - PDLGD'!I3)+Y3*(1-'Input - PDLGD'!U3)*(R3/'Input - PDLGD'!I3),"")) -> 380.91244 | AD3: =IF(Z3<=0,Z3,IFERROR(Z3*'Input - PDLGD'!V3*(AW3/'Input - PDLGD'!D3)*(AY3/'Input - PDLGD'!J3)+Z3*(1-'Input - PDLGD'!V3)*(AY3/'Input - PDLGD'!J3),"")) -> 166.63966 | AE3: =IF(AA3<=0,AA3,IFERROR(AA3*'Input - PDLGD'!W3*(AX3/'Input - PDLGD'!E3)*(AZ3/'Input - PDLGD'!K3)+AA3*(1-'Input - PDLGD'!W3)*(AZ3/'Input - PDLGD'!K3),"")) -> 362.46822 | AF3: =SUMIF('Plan - CoC'!$C$1:$BJ$1,AF$2,'Plan - CoC'!$C16:$BJ16) -> 115.94613 | AG3: =SUMIF('Plan - CoC'!$C$1:$BJ$1,AG$2,'Plan - CoC'!$C16:$BJ16) -> 230.80921 | AH3: =SUMIF('Plan - CoC'!$C$1:$BJ$1,AH$2,'Plan - CoC'!$C16:$BJ16) -> 303.13851 | AI3: =AF3*LOOKUP(AI$2,'Input-Stress Parameters'!$C$4:$E$4,'Input-Stress Parameters'!$J$5:$J$7)/SUMIF('Input - ENR'!$C$1:$BJ$1,AI$2,'Input - ENR'!$C10:$BJ10) -> 0.0020237958 | AJ3: =AG3*LOOKUP(AJ$2,'Input-Stress Parameters'!$C$4:$E$4,'Input-Stress Parameters'!$J$5:$J$7)/SUMIF('Input - ENR'!$C$1:$BJ$1,AJ$2,'Input - ENR'!$C10:$BJ10) -> 0.0029768786 | AK3: =AH3*LOOKUP(AK$2,'Input-Stress Parameters'!$C$4:$E$4,'Input-Stress Parameters'!$J$5:$J$7)/SUMIF('Input - ENR'!$C$1:$BJ$1,AK$2,'Input - ENR'!$C10:$BJ10) -> 0.0028428966 | AL3: =IF(AI3<0,AI3,AI3*(L3/'Input - PDLGD'!B3)) -> 0.0037276456 | AM3: =IF(AJ3<0,AJ3,AJ3*(M3/'Input - PDLGD'!C3)) -> 0.0097449946 | AN3: =IF(AK3<0,AK3,AK3*(N3/'Input - PDLGD'!D3)) -> 0.0042769892 | AO3: =AL3*SUMIF('Input - ENR'!$C$1:$BJ$1,AO$2,'Input - ENR'!$C4:$BJ4)/LOOKUP(AO$2,'Input-Stress Parameters'!$C$4:$E$4,'Input-Stress Parameters'!$J$5:$J$7) -> 204.48337 | AP3: =AM3*SUMIF('Input - ENR'!$C$1:$BJ$1,'Calculations - Parameters'!AP$2,'Input - ENR'!$C4:$BJ4)/LOOKUP(AP$2,'Input-Stress Parameters'!$C$4:$E$4,'Input-Stress Parameters'!$J$5:$J$7) -> 599.74735 | AQ3: =AN3*SUMIF('Input - ENR'!$C$1:$BJ$1,'Calculations - Parameters'!AQ$2,'Input - ENR'!$C4:$BJ4)/LOOKUP(AQ$2,'Input-Stress Parameters'!$C$4:$E$4,'Input-Stress Parameters'!$J$5:$J$7) -> 299.04724 | AR3: =SUMIF('Calculation - NCL and ECL'!$E$1:$AN$1,'Calculations - Parameters'!AR$2,'Calculation - NCL and ECL'!$E22:$AN22) -> 182.87329 | AS3: =SUMIF('Calculation - NCL and ECL'!$E$1:$AN$1,'Calculations - Parameters'!AS$2,'Calculation - NCL and ECL'!$E22:$AN22) -> 419.13987 | AT3: =SUMIF('Calculation - NCL and ECL'!$E$1:$AN$1,'Calculations - Parameters'!AT$2,'Calculation - NCL and ECL'!$E22:$AN22) -> -105.57693 | AU3: 10 | AV3: 10 | AW3: =IFERROR(IF(AU3=1,$K3,NORMSDIST((1-J3)^(-0.5)*NORMSINV($K3)+(J3/(1-J3))^0.5*NORMSINV(1-(1/AU3)))), "") -> 0.024709678 | AX3: =IFERROR(IF(AV3=1,$K3,NORMSDIST((1-J3)^(-0.5)*NORMSINV($K3)+(J3/(1-J3))^0.5*NORMSINV(1-(1/AV3)))), "") -> 0.024709678 | AY3: =IF(AU3=1,$O3,IF(AU3<=7,($P3+$O3)/2,$P3)) -> 0.465 | AZ3: =IF(AV3=1,$O3,IF(AV3<=7,($P3+$O3)/2,$P3)) -> 0.465
A4: LAP | B4: Retail | C4: Retail | D4: Retail | E4: ='Input-Stress Parameters'!C$5 -> 7 | F4: ='Input-Stress Parameters'!D$5 -> 25 | G4: ='Input-Stress Parameters'!E$5 -> 5 | H4: =0.03*(1-EXP(-35*$K4))/(1-EXP(-35))+(0.16*(1-(1-EXP(-35*$K4))/(1-EXP(-35)))) -> 0.096346824 | I4: =0.03*(1-EXP(-35*$K4))/(1-EXP(-35))+(0.16*(1-(1-EXP(-35*$K4))/(1-EXP(-35)))) -> 0.096346824 | J4: =0.03*(1-EXP(-35*$K4))/(1-EXP(-35))+(0.16*(1-(1-EXP(-35*$K4))/(1-EXP(-35)))) -> 0.096346824 | K4: ='Input - PDLGD'!B4 -> 0.019218244 | L4: =IFERROR(IF(E4=1,$K4,NORMSDIST((1-H4)^(-0.5)*NORMSINV($K4)+(H4/(1-H4))^0.5*NORMSINV(1-(1/E4)))), "") -> 0.03368893 | M4: =IFERROR(IF(F4=1,$K4,NORMSDIST((1-I4)^(-0.5)*NORMSINV($K4)+(I4/(1-I4))^0.5*NORMSINV(1-(1/F4)))), "") -> 0.054127048 | N4: =IFERROR(IF(G4=1,$K4,NORMSDIST((1-J4)^(-0.5)*NORMSINV($K4)+(J4/(1-J4))^0.5*NORMSINV(1-(1/G4)))), "") -> 0.028525263 | O4: ='Input - PDLGD'!H4 -> 0.35972496 | P4: ='Input - PDLGD'!N4 -> 0.41 | Q4: =IF(E4=1,$O4,IF(E4<=7,($P4+$O4)/2,$P4)) -> 0.38486248 | R4: =IF(F4=1,$O4,IF(F4<=7,($P4+$O4)/2,$P4)) -> 0.41 | S4: =IF(G4=1,$O4,IF(G4<=7,($P4+$O4)/2,$P4)) -> 0.38486248 | T4: =SUMIF('Input - NCL'!$C$2:$BJ$2,T$2,'Input - NCL'!$C12:$BJ12) -> 90.533704 | U4: =SUMIF('Input - NCL'!$C$2:$BJ$2,U$2,'Input - NCL'!$C12:$BJ12) -> 302.76892 | V4: =SUMIF('Input - NCL'!$C$2:$BJ$2,V$2,'Input - NCL'!$C12:$BJ12) -> 61.621621 | W4: =SUMIF('Input - NCL'!$C$2:$BJ$2,W$2,'Input - NCL'!$C12:$BJ12) -> 102.85584 | X4: =SUMIF('Input - NCL'!$C$2:$BJ$2,X$2,'Input - NCL'!$C6:$BJ6) -> 94.215514 | Y4: =SUMIF('Input - NCL'!$C$2:$BJ$2,Y$2,'Input - NCL'!$C6:$BJ6) -> 256.38709 | Z4: =SUMIF('Input - NCL'!$C$2:$BJ$2,Z$2,'Input - NCL'!$C6:$BJ6) -> 42.151651 | AA4: =SUMIF('Input - NCL'!$C$2:$BJ$2,AA$2,'Input - NCL'!$C6:$BJ6) -> 70.310139 | AB4: =IF(X4<=0,X4,IFERROR(X4*'Input - PDLGD'!T4*(L4/'Input - PDLGD'!B4)*(Q4/'Input - PDLGD'!H4)+X4*(1-'Input - PDLGD'!T4)*(Q4/'Input - PDLGD'!H4),"")) -> 112.18404 | AC4: =IF(Y4<=0,Y4,IFERROR(Y4*'Input - PDLGD'!U4*(M4/'Input - PDLGD'!C4)*(R4/'Input - PDLGD'!I4)+Y4*(1-'Input - PDLGD'!U4)*(R4/'Input - PDLGD'!I4),"")) -> 398.37961 | AD4: =IF(Z4<=0,Z4,IFERROR(Z4*'Input - PDLGD'!V4*(N4/'Input - PDLGD'!D4)*(S4/'Input - PDLGD'!J4)+Z4*(1-'Input - PDLGD'!V4)*(S4/'Input - PDLGD'!J4),"")) -> 61.476969 | AE4: =IF(AA4<=0,AA4,IFERROR(AA4*'Input - PDLGD'!W4*(AX4/'Input - PDLGD'!E4)*(AZ4/'Input - PDLGD'!K4)+AA4*(1-'Input - PDLGD'!W4)*(AZ4/'Input - PDLGD'!K4),"")) -> 142.83153 | AF4: =SUMIF('Plan - CoC'!$C$1:$BJ$1,AF$2,'Plan - CoC'!$C17:$BJ17) -> 15.742999 | AG4: =SUMIF('Plan - CoC'!$C$1:$BJ$1,AG$2,'Plan - CoC'!$C17:$BJ17) -> -40.447607 | AH4: =SUMIF('Plan - CoC'!$C$1:$BJ$1,AH$2,'Plan - CoC'!$C17:$BJ17) -> 55.209816 | AI4: =AF4*LOOKUP(AI$2,'Input-Stress Parameters'!$C$4:$E$4,'Input-Stress Parameters'!$J$5:$J$7)/SUMIF('Input - ENR'!$C$1:$BJ$1,AI$2,'Input - ENR'!$C11:$BJ11) -> 0.00076974726 | AJ4: =AG4*LOOKUP(AJ$2,'Input-Stress Parameters'!$C$4:$E$4,'Input-Stress Parameters'!$J$5:$J$7)/SUMIF('Input - ENR'!$C$1:$BJ$1,AJ$2,'Input - ENR'!$C11:$BJ11) -> -0.0016993288 | AK4: =AH4*LOOKUP(AK$2,'Input-Stress Parameters'!$C$4:$E$4,'Input-Stress Parameters'!$J$5:$J$7)/SUMIF('Input - ENR'!$C$1:$BJ$1,AK$2,'Input - ENR'!$C11:$BJ11) -> 0.0018290912 | AL4: =IF(AI4<0,AI4,AI4*(L4/'Input - PDLGD'!B4)) -> 0.0013493408 | AM4: =IF(AJ4<0,AJ4,AJ4*(M4/'Input - PDLGD'!C4)) -> -0.0016993288 | AN4: =IF(AK4<0,AK4,AK4*(N4/'Input - PDLGD'!D4)) -> 0.0027148841 | AO4: =AL4*SUMIF('Input - ENR'!$C$1:$BJ$1,'Calculations - Parameters'!AO$2,'Input - ENR'!$C5:$BJ5)/LOOKUP(AO$2,'Input-Stress Parameters'!$C$4:$E$4,'Input-Stress Parameters'!$J$5:$J$7) -> 28.699223 | AP4: =AM4*SUMIF('Input - ENR'!$C$1:$BJ$1,'Calculations - Parameters'!AP$2,'Input - ENR'!$C5:$BJ5)/LOOKUP(AP$2,'Input-Stress Parameters'!$C$4:$E$4,'Input-Stress Parameters'!$J$5:$J$7) -> -33.869822 | AQ4: =AN4*SUMIF('Input - ENR'!$C$1:$BJ$1,'Calculations - Parameters'!AQ$2,'Input - ENR'!$C5:$BJ5)/LOOKUP(AQ$2,'Input-Stress Parameters'!$C$4:$E$4,'Input-Stress Parameters'!$J$5:$J$7) -> 56.391917 | AR4: =SUMIF('Calculation - NCL and ECL'!$E$1:$AN$1,'Calculations - Parameters'!AR$2,'Calculation - NCL and ECL'!$E23:$AN23) -> 115.69983 | AS4: =SUMIF('Calculation - NCL and ECL'!$E$1:$AN$1,'Calculations - Parameters'!AS$2,'Calculation - NCL and ECL'!$E23:$AN23) -> 200.46509 | AT4: =SUMIF('Calculation - NCL and ECL'!$E$1:$AN$1,'Calculations - Parameters'!AT$2,'Calculation - NCL and ECL'!$E23:$AN23) -> -165.14103 | AU4: 10 | AV4: 10 | AW4: =IFERROR(IF(AU4=1,$K4,NORMSDIST((1-J4)^(-0.5)*NORMSINV($K4)+(J4/(1-J4))^0.5*NORMSINV(1-(1/AU4)))), "") -> 0.039265421 | AX4: =IFERROR(IF(AV4=1,$K4,NORMSDIST((1-J4)^(-0.5)*NORMSINV($K4)+(J4/(1-J4))^0.5*NORMSINV(1-(1/AV4)))), "") -> 0.039265421 | AY4: =IF(AU4=1,$O4,IF(AU4<=7,($P4+$O4)/2,$P4)) -> 0.41 | AZ4: =IF(AV4=1,$O4,IF(AV4<=7,($P4+$O4)/2,$P4)) -> 0.41
A5: DF | B5: Retail | C5: Retail | D5: Retail | E5: ='Input-Stress Parameters'!C$5 -> 7 | F5: ='Input-Stress Parameters'!D$5 -> 25 | G5: ='Input-Stress Parameters'!E$5 -> 5 | H5: =0.03*(1-EXP(-35*$K5))/(1-EXP(-35))+(0.16*(1-(1-EXP(-35*$K5))/(1-EXP(-35)))) -> 0.16 | I5: =0.03*(1-EXP(-35*$K5))/(1-EXP(-35))+(0.16*(1-(1-EXP(-35*$K5))/(1-EXP(-35)))) -> 0.16 | J5: =0.03*(1-EXP(-35*$K5))/(1-EXP(-35))+(0.16*(1-(1-EXP(-35*$K5))/(1-EXP(-35)))) -> 0.16 | K5: ='Input - PDLGD'!B5 -> 0 | L5: =IFERROR(IF(E5=1,$K5,NORMSDIST((1-H5)^(-0.5)*NORMSINV($K5)+(H5/(1-H5))^0.5*NORMSINV(1-(1/E5)))), "") | M5: =IFERROR(IF(F5=1,$K5,NORMSDIST((1-I5)^(-0.5)*NORMSINV($K5)+(I5/(1-I5))^0.5*NORMSINV(1-(1/F5)))), "") | N5: =IFERROR(IF(G5=1,$K5,NORMSDIST((1-J5)^(-0.5)*NORMSINV($K5)+(J5/(1-J5))^0.5*NORMSINV(1-(1/G5)))), "") | O5: ='Input - PDLGD'!H5 -> 0 | P5: ='Input - PDLGD'!N5 -> 0 | Q5: =IF(E5=1,$O5,IF(E5<=7,($P5+$O5)/2,$P5)) -> 0 | R5: =IF(F5=1,$O5,IF(F5<=7,($P5+$O5)/2,$P5)) -> 0 | S5: =IF(G5=1,$O5,IF(G5<=7,($P5+$O5)/2,$P5)) -> 0 | T5: =SUMIF('Input - NCL'!$C$2:$BJ$2,T$2,'Input - NCL'!$C13:$BJ13) -> 0 | U5: =SUMIF('Input - NCL'!$C$2:$BJ$2,U$2,'Input - NCL'!$C13:$BJ13) -> 0 | V5: =SUMIF('Input - NCL'!$C$2:$BJ$2,V$2,'Input - NCL'!$C13:$BJ13) -> 0 | W5: =SUMIF('Input - NCL'!$C$2:$BJ$2,W$2,'Input - NCL'!$C13:$BJ13) -> 0 | X5: =SUMIF('Input - NCL'!$C$2:$BJ$2,X$2,'Input - NCL'!$C7:$BJ7) -> 0 | Y5: =SUMIF('Input - NCL'!$C$2:$BJ$2,Y$2,'Input - NCL'!$C7:$BJ7) -> 0 | Z5: =SUMIF('Input - NCL'!$C$2:$BJ$2,Z$2,'Input - NCL'!$C7:$BJ7) -> 0 | AA5: =SUMIF('Input - NCL'!$C$2:$BJ$2,AA$2,'Input - NCL'!$C7:$BJ7) -> 0 | AB5: =IF(X5<=0,X5,IFERROR(X5*'Input - PDLGD'!T5*(L5/'Input - PDLGD'!B5)*(Q5/'Input - PDLGD'!H5)+X5*(1-'Input - PDLGD'!T5)*(Q5/'Input - PDLGD'!H5),"")) -> 0 | AC5: =IF(Y5<=0,Y5,IFERROR(Y5*'Input - PDLGD'!U5*(M5/'Input - PDLGD'!C5)*(R5/'Input - PDLGD'!I5)+Y5*(1-'Input - PDLGD'!U5)*(R5/'Input - PDLGD'!I5),"")) -> 0 | AD5: =IF(Z5<=0,Z5,IFERROR(Z5*'Input - PDLGD'!V5*(N5/'Input - PDLGD'!D5)*(S5/'Input - PDLGD'!J5)+Z5*(1-'Input - PDLGD'!V5)*(S5/'Input - PDLGD'!J5),"")) -> 0 | AE5: =IF(AA5<=0,AA5,IFERROR(AA5*'Input - PDLGD'!W5*(AX5/'Input - PDLGD'!E5)*(AZ5/'Input - PDLGD'!K5)+AA5*(1-'Input - PDLGD'!W5)*(AZ5/'Input - PDLGD'!K5),"")) -> 0 | AF5: =SUMIF('Plan - CoC'!$C$1:$BJ$1,AF$2,'Plan - CoC'!$C18:$BJ18) -> 6.3550475 | AG5: =SUMIF('Plan - CoC'!$C$1:$BJ$1,AG$2,'Plan - CoC'!$C18:$BJ18) -> 23.047506 | AH5: =SUMIF('Plan - CoC'!$C$1:$BJ$1,AH$2,'Plan - CoC'!$C18:$BJ18) -> 20.9092 | AI5: =AF5*LOOKUP(AI$2,'Input-Stress Parameters'!$C$4:$E$4,'Input-Stress Parameters'!$J$5:$J$7)/SUMIF('Input - ENR'!$C$1:$BJ$1,AI$2,'Input - ENR'!$C12:$BJ12) -> 0.00082024401 | AJ5: =AG5*LOOKUP(AJ$2,'Input-Stress Parameters'!$C$4:$E$4,'Input-Stress Parameters'!$J$5:$J$7)/SUMIF('Input - ENR'!$C$1:$BJ$1,AJ$2,'Input - ENR'!$C12:$BJ12) -> 0.0023817243 | AK5: =AH5*LOOKUP(AK$2,'Input-Stress Parameters'!$C$4:$E$4,'Input-Stress Parameters'!$J$5:$J$7)/SUMIF('Input - ENR'!$C$1:$BJ$1,AK$2,'Input - ENR'!$C12:$BJ12) -> 0.0017599168 | AL5: =IF(AI5<0,AI5,AI5*(L5/'Input - PDLGD'!B5)) -> #VALUE! | AM5: =IF(AJ5<0,AJ5,AJ5*(M5/'Input - PDLGD'!C5)) -> #VALUE! | AN5: =IF(AK5<0,AK5,AK5*(N5/'Input - PDLGD'!D5)) -> #VALUE! | AO5: =AL5*SUMIF('Input - ENR'!$C$1:$BJ$1,'Calculations - Parameters'!AO$2,'Input - ENR'!$C6:$BJ6)/LOOKUP(AO$2,'Input-Stress Parameters'!$C$4:$E$4,'Input-Stress Parameters'!$J$5:$J$7) -> #VALUE! | AP5: =AM5*SUMIF('Input - ENR'!$C$1:$BJ$1,'Calculations - Parameters'!AP$2,'Input - ENR'!$C6:$BJ6)/LOOKUP(AP$2,'Input-Stress Parameters'!$C$4:$E$4,'Input-Stress Parameters'!$J$5:$J$7) -> #VALUE! | AQ5: =AN5*SUMIF('Input - ENR'!$C$1:$BJ$1,'Calculations - Parameters'!AQ$2,'Input - ENR'!$C6:$BJ6)/LOOKUP(AQ$2,'Input-Stress Parameters'!$C$4:$E$4,'Input-Stress Parameters'!$J$5:$J$7) -> #VALUE! | AR5: =SUMIF('Calculation - NCL and ECL'!$E$1:$AN$1,'Calculations - Parameters'!AR$2,'Calculation - NCL and ECL'!$E24:$AN24) -> -12.224719 | AS5: =SUMIF('Calculation - NCL and ECL'!$E$1:$AN$1,'Calculations - Parameters'!AS$2,'Calculation - NCL and ECL'!$E24:$AN24) -> -24.94149 | AT5: =SUMIF('Calculation - NCL and ECL'!$E$1:$AN$1,'Calculations - Parameters'!AT$2,'Calculation - NCL and ECL'!$E24:$AN24) -> 11.707581 | AU5: 10 | AV5: 10 | AW5: =IFERROR(IF(AU5=1,$K5,NORMSDIST((1-AK5)^(-0.5)*NORMSINV($K5)+(AK5/(1-AK5))^0.5*NORMSINV(1-(1/AU5)))), "") | AX5: =IFERROR(IF(AV5=1,$K5,NORMSDIST((1-AK5)^(-0.5)*NORMSINV($K5)+(AK5/(1-AK5))^0.5*NORMSINV(1-(1/AV5)))), "") | AY5: =IF(AU5=1,$O5,IF(AU5<=7,($P5+$O5)/2,$P5)) -> 0 | AZ5: =IF(AV5=1,$O5,IF(AV5<=7,($P5+$O5)/2,$P5)) -> 0
AL6: TBD*

Sheet Input - NCL
A1: Back - Index | C1: =LOOKUP(C3,'Input-Stress Parameters'!$C$9:$BJ$9,'Input-Stress Parameters'!$C$11:$BJ$11) -> N | D1: =LOOKUP(D3,'Input-Stress Parameters'!$C$9:$BJ$9,'Input-Stress Parameters'!$C$11:$BJ$11) -> SL1 | E1: =LOOKUP(E3,'Input-Stress Parameters'!$C$9:$BJ$9,'Input-Stress Parameters'!$C$11:$BJ$11) -> SL1 | F1: =LOOKUP(F3,'Input-Stress Parameters'!$C$9:$BJ$9,'Input-Stress Parameters'!$C$11:$BJ$11) -> SL1 | G1: =LOOKUP(G3,'Input-Stress Parameters'!$C$9:$BJ$9,'Input-Stress Parameters'!$C$11:$BJ$11) -> SL1 | H1: =LOOKUP(H3,'Input-Stress Parameters'!$C$9:$BJ$9,'Input-Stress Parameters'!$C$11:$BJ$11) -> SL1 | I1: =LOOKUP(I3,'Input-Stress Parameters'!$C$9:$BJ$9,'Input-Stress Parameters'!$C$11:$BJ$11) -> SL1 | J1: =LOOKUP(J3,'Input-Stress Parameters'!$C$9:$BJ$9,'Input-Stress Parameters'!$C$11:$BJ$11) -> SL2 | ... BJ1: =LOOKUP(BJ3,'Input-Stress Parameters'!$C$9:$BJ$9,'Input-Stress Parameters'!$C$11:$BJ$11) -> N
C2: =LOOKUP($C$3:$BJ$3,'Input-Stress Parameters'!$C$27:$BJ$27,'Input-Stress Parameters'!$C$28:$BJ$28) -> N | D2: =LOOKUP($C$3:$BJ$3,'Input-Stress Parameters'!$C$27:$BJ$27,'Input-Stress Parameters'!$C$28:$BJ$28) -> SL1 | E2: =LOOKUP($C$3:$BJ$3,'Input-Stress Parameters'!$C$27:$BJ$27,'Input-Stress Parameters'!$C$28:$BJ$28) -> SL1 | F2: =LOOKUP($C$3:$BJ$3,'Input-Stress Parameters'!$C$27:$BJ$27,'Input-Stress Parameters'!$C$28:$BJ$28) -> SL1 | G2: =LOOKUP($C$3:$BJ$3,'Input-Stress Parameters'!$C$27:$BJ$27,'Input-Stress Parameters'!$C$28:$BJ$28) -> SL1 | H2: =LOOKUP($C$3:$BJ$3,'Input-Stress Parameters'!$C$27:$BJ$27,'Input-Stress Parameters'!$C$28:$BJ$28) -> SL1 | I2: =LOOKUP($C$3:$BJ$3,'Input-Stress Parameters'!$C$27:$BJ$27,'Input-Stress Parameters'!$C$28:$BJ$28) -> SL1 | J2: =LOOKUP($C$3:$BJ$3,'Input-Stress Parameters'!$C$27:$BJ$27,'Input-Stress Parameters'!$C$28:$BJ$28) -> SL2 | ... AQ2: =LOOKUP($C$3:$BJ$3,'Input-Stress Parameters'!$C$27:$BJ$27,'Input-Stress Parameters'!$C$28:$BJ$28) -> N
A3: NCL - Stress (base) | B3: Inputs | C3: ='Input-Stress Parameters'!C2 -> 45352 | D3: =EDATE(C3,1) -> 45383 | E3: =EDATE(D3,1) -> 45413 | F3: =EDATE(E3,1) -> 45444 | G3: =EDATE(F3,1) -> 45474 | H3: =EDATE(G3,1) -> 45505 | I3: =EDATE(H3,1) -> 45536 | J3: =EDATE(I3,1) -> 45566 | K3: =EDATE(J3,1) -> 45597 | ... BJ3: =EDATE(BI3,1) -> 47150
A4: NCL - Stress (base) | B4: SMHFC | C4: =SUM(C5:C7) -> 66.317611 | D4: =SUM(D5:D7) -> 51.307871 | E4: =SUM(E5:E7) -> 25.675156 | F4: =SUM(F5:F7) -> 31.629914 | G4: =SUM(G5:G7) -> 30.59069 | H4: =SUM(H5:H7) -> 32.489025 | I4: =SUM(I5:I7) -> 25.750284 | J4: =SUM(J5:J7) -> 40.713514 | ... BJ4: =SUM(BJ5:BJ7) -> #DIV/0!
A5: NCL - Stress (base) | B5: HL | C5: ='Input - ENR'!C4*C11/'Input - ENR'!C10 -> 27.583752 | D5: ='Input - ENR'!D4*D11/'Input - ENR'!D10 -> 36.14612 | E5: ='Input - ENR'!E4*E11/'Input - ENR'!E10 -> 10.858758 | F5: ='Input - ENR'!F4*F11/'Input - ENR'!F10 -> 16.20542 | G5: ='Input - ENR'!G4*G11/'Input - ENR'!G10 -> 12.178065 | H5: ='Input - ENR'!H4*H11/'Input - ENR'!H10 -> 16.900141 | I5: ='Input - ENR'!I4*I11/'Input - ENR'!I10 -> 10.938922 | J5: ='Input - ENR'!J4*J11/'Input - ENR'!J10 -> 22.338597 | ... AG5: ='Input - ENR'!AG4*AG11/'Input - ENR'!AG10 -> 23.492274 | AH5: =AH11 -> 35.405992 | AI5: =AI11 -> 29.695936 | AJ5: =AJ11 -> 31.49428 | AK5: =AK11 -> 34.208306 | AL5: =AL11 -> 34.609581 | AM5: =AM11 -> 38.102161 | AN5: ='Input - ENR'!AN4*AN11/'Input - ENR'!AN10 -> #DIV/0! | AO5: ='Input - ENR'!AO4*AO11/'Input - ENR'!AO10 -> #DIV/0! | AP5: ='Input - ENR'!AP4*AP11/'Input - ENR'!AP10 -> #DIV/0! | AQ5: ='Input - ENR'!AQ4*AQ11/'Input - ENR'!AQ10 -> #DIV/0! | AR5: ='Input - ENR'!AR4*AR11/'Input - ENR'!AR10 -> #DIV/0! | AS5: ='Input - ENR'!AS4*AS11/'Input - ENR'!AS10 -> #DIV/0! | AT5: ='Input - ENR'!AT4*AT11/'Input - ENR'!AT10 -> #DIV/0! | AU5: ='Input - ENR'!AU4*AU11/'Input - ENR'!AU10 -> #DIV/0! | ... BJ5: ='Input - ENR'!BJ4*BJ11/'Input - ENR'!BJ10 -> #DIV/0!
A6: NCL - Stress (base) | B6: LAP | C6: ='Input - ENR'!C5*C12/'Input - ENR'!C11 -> 38.733859 | D6: ='Input - ENR'!D5*D12/'Input - ENR'!D11 -> 15.161752 | E6: ='Input - ENR'!E5*E12/'Input - ENR'!E11 -> 14.816398 | F6: ='Input - ENR'!F5*F12/'Input - ENR'!F11 -> 15.424494 | G6: ='Input - ENR'!G5*G12/'Input - ENR'!G11 -> 18.412625 | H6: ='Input - ENR'!H5*H12/'Input - ENR'!H11 -> 15.588883 | I6: ='Input - ENR'!I5*I12/'Input - ENR'!I11 -> 14.811363 | J6: ='Input - ENR'!J5*J12/'Input - ENR'!J11 -> 18.374917 | ... AG6: ='Input - ENR'!AG5*AG12/'Input - ENR'!AG11 -> 10.411419 | AH6: =AH12 -> 13.401204 | AI6: =AI12 -> 15.042314 | AJ6: =AJ12 -> 13.409089 | AK6: =AK12 -> 13.623198 | AL6: =AL12 -> 14.491586 | AM6: =AM12 -> 14.976077 | AN6: ='Input - ENR'!AN5*AN12/'Input - ENR'!AN11 -> #DIV/0! | AO6: ='Input - ENR'!AO5*AO12/'Input - ENR'!AO11 -> #DIV/0! | AP6: ='Input - ENR'!AP5*AP12/'Input - ENR'!AP11 -> #DIV/0! | AQ6: ='Input - ENR'!AQ5*AQ12/'Input - ENR'!AQ11 -> #DIV/0! | AR6: ='Input - ENR'!AR5*AR12/'Input - ENR'!AR11 -> #DIV/0! | AS6: ='Input - ENR'!AS5*AS12/'Input - ENR'!AS11 -> #DIV/0! | AT6: ='Input - ENR'!AT5*AT12/'Input - ENR'!AT11 -> #DIV/0! | AU6: ='Input - ENR'!AU5*AU12/'Input - ENR'!AU11 -> #DIV/0! | ... BJ6: ='Input - ENR'!BJ5*BJ12/'Input - ENR'!BJ11 -> #DIV/0!
A7: NCL - Stress (base) | B7: DF | C7: =IFERROR('Input - ENR'!C18*C13/'Input - ENR'!C12,0) -> 0 | D7: =IFERROR('Input - ENR'!D18*D13/'Input - ENR'!D12,0) -> 0 | E7: =IFERROR('Input - ENR'!E18*E13/'Input - ENR'!E12,0) -> 0 | F7: =IFERROR('Input - ENR'!F18*F13/'Input - ENR'!F12,0) -> 0 | G7: =IFERROR('Input - ENR'!G18*G13/'Input - ENR'!G12,0) -> 0 | H7: =IFERROR('Input - ENR'!H18*H13/'Input - ENR'!H12,0) -> 0 | I7: =IFERROR('Input - ENR'!I18*I13/'Input - ENR'!I12,0) -> 0 | J7: =IFERROR('Input - ENR'!J18*J13/'Input - ENR'!J12,0) -> 0 | ... AG7: =IFERROR('Input - ENR'!AG18*AG13/'Input - ENR'!AG12,0) -> 0 | AH7: =AH13 -> 0 | AI7: =AI13 -> 0 | AJ7: =AJ13 -> 0 | AK7: =AK13 -> 0 | AL7: =AL13 -> 0 | AM7: =AM13 -> 0 | AN7: =IFERROR('Input - ENR'!AN18*AN13/'Input - ENR'!AN12,0) -> 0 | AO7: =IFERROR('Input - ENR'!AO18*AO13/'Input - ENR'!AO12,0) -> 0 | AP7: =IFERROR('Input - ENR'!AP18*AP13/'Input - ENR'!AP12,0) -> 0 | AQ7: =IFERROR('Input - ENR'!AQ18*AQ13/'Input - ENR'!AQ12,0) -> 0 | AR7: =IFERROR('Input - ENR'!AR18*AR13/'Input - ENR'!AR12,0) -> 0 | AS7: =IFERROR('Input - ENR'!AS18*AS13/'Input - ENR'!AS12,0) -> 0 | AT7: =IFERROR('Input - ENR'!AT18*AT13/'Input - ENR'!AT12,0) -> 0 | AU7: =IFERROR('Input - ENR'!AU18*AU13/'Input - ENR'!AU12,0) -> 0 | ... BJ7: =IFERROR('Input - ENR'!BJ18*BJ13/'Input - ENR'!BJ12,0) -> 0
A9: NCL - Plan | B9: Inputs | C9: =$C$3 -> 45352 | D9: =EDATE(C9,1) -> 45383 | E9: =EDATE(D9,1) -> 45413 | F9: =EDATE(E9,1) -> 45444 | G9: =EDATE(F9,1) -> 45474 | H9: =EDATE(G9,1) -> 45505 | I9: =EDATE(H9,1) -> 45536 | J9: =EDATE(I9,1) -> 45566 | K9: =EDATE(J9,1) -> 45597 | ... BJ9: =EDATE(BI9,1) -> 47150
A10: NCL - Plan | B10: SMHFC | C10: =SUM(C11:C13) -> 66.317611 | D10: =SUM(D11:D13) -> 51.60795 | E10: =SUM(E11:E13) -> 25.876003 | F10: =SUM(F11:F13) -> 30.896596 | G10: =SUM(G11:G13) -> 29.972194 | H10: =SUM(H11:H13) -> 32.884256 | I10: =SUM(I11:I13) -> 26.335322 | J10: =SUM(J11:J13) -> 43.200753 | ... BJ10: =SUM(BJ11:BJ13) -> 0
A11: NCL - Plan | B11: HL | C11: 27.583752 | D11: 36.625231 | E11: 11.101824 | F11: 16.751331 | G11: 12.750592 | H11: 17.970252 | I11: 11.839389 | J11: 24.668374 | K11: 13.85888 | L11: 12.984126 | M11: 15.46931 | N11: 13.493476 | O11: 14.912047 | P11: 18.728287 | Q11: 26.828643 | R11: 30.888675 | S11: 82.776033 | T11: 22.807431 | U11: 21.800398 | V11: 12.098567 | W11: 23.747629 | X11: 19.507189 | Y11: 22.101247 | Z11: 18.264385 | AA11: 21.768585 | AB11: 73.24902 | AC11: 28.677115 | AD11: 32.592922 | AE11: 46.492842 | AF11: 44.101537 | AG11: 35.434392 | AH11: 35.405992 | AI11: 29.695936 | AJ11: 31.49428 | AK11: 34.208306 | AL11: 34.609581 | AM11: 38.102161 | AN11: ='Plan - CoC'!AN4-'Plan - CoC'!AN10 -> 0 | AO11: ='Plan - CoC'!AO4-'Plan - CoC'!AO10 -> 0 | AP11: ='Plan - CoC'!AP4-'Plan - CoC'!AP10 -> 0 | AQ11: ='Plan - CoC'!AQ4-'Plan - CoC'!AQ10 -> 0 | AR11: ='Plan - CoC'!AR4-'Plan - CoC'!AR10 -> 0 | AS11: ='Plan - CoC'!AS4-'Plan - CoC'!AS10 -> 0 | AT11: ='Plan - CoC'!AT4-'Plan - CoC'!AT10 -> 0 | AU11: ='Plan - CoC'!AU4-'Plan - CoC'!AU10 -> 0 | ... BJ11: ='Plan - CoC'!BJ4-'Plan - CoC'!BJ10 -> 0
A12: NCL - Plan | B12: LAP | C12: 38.733859 | D12: 14.982719 | E12: 14.77418 | F12: 14.145265 | G12: 17.221602 | H12: 14.914004 | I12: 14.495933 | J12: 18.532379 | K12: 12.550223 | L12: 44.939075 | M12: 54.841097 | N12: 14.941462 | O12: 15.184597 | P12: 17.80816 | Q12: 20.646612 | R12: 35.568841 | S12: 16.579093 | T12: 23.202158 | U12: 27.975222 | V12: 6.1388183 | W12: 7.679943 | X12: 13.586502 | Y12: 12.597694 | Z12: 12.557773 | AA12: 9.0608902 | AB12: 16.334684 | AC12: 16.82566 | AD12: 23.285194 | AE12: 18.514551 | AF12: 14.03416 | AG12: 13.861597 | AH12: 13.401204 | AI12: 15.042314 | AJ12: 13.409089 | AK12: 13.623198 | AL12: 14.491586 | AM12: 14.976077 | AN12: ='Plan - CoC'!AN5-'Plan - CoC'!AN11 -> 0 | AO12: ='Plan - CoC'!AO5-'Plan - CoC'!AO11 -> 0 | AP12: ='Plan - CoC'!AP5-'Plan - CoC'!AP11 -> 0 | AQ12: ='Plan - CoC'!AQ5-'Plan - CoC'!AQ11 -> 0 | AR12: ='Plan - CoC'!AR5-'Plan - CoC'!AR11 -> 0 | AS12: ='Plan - CoC'!AS5-'Plan - CoC'!AS11 -> 0 | AT12: ='Plan - CoC'!AT5-'Plan - CoC'!AT11 -> 0 | AU12: ='Plan - CoC'!AU5-'Plan - CoC'!AU11 -> 0 | ... BJ12: ='Plan - CoC'!BJ5-'Plan - CoC'!BJ11 -> 0
A13: NCL - Plan | B13: DF | C13: 0 | D13: 0 | E13: 0 | F13: 0 | G13: 0 | H13: 0 | I13: 0 | J13: 0 | K13: 0 | L13: 0 | M13: 0 | N13: 0 | O13: 0 | P13: 0 | Q13: 0 | R13: 0 | S13: 0 | T13: 0 | U13: 0 | V13: 0 | W13: 0 | X13: 0 | Y13: 0 | Z13: 0 | AA13: 0 | AB13: 0 | AC13: 0 | AD13: 0 | AE13: 0 | AF13: 0 | AG13: 0 | AH13: 0 | AI13: 0 | AJ13: 0 | AK13: 0 | AL13: 0 | AM13: 0 | AN13: ='Plan - CoC'!AN6-'Plan - CoC'!AN12 -> 0 | AO13: ='Plan - CoC'!AO6-'Plan - CoC'!AO12 -> 0 | AP13: ='Plan - CoC'!AP6-'Plan - CoC'!AP12 -> 0 | AQ13: ='Plan - CoC'!AQ6-'Plan - CoC'!AQ12 -> 0 | AR13: ='Plan - CoC'!AR6-'Plan - CoC'!AR12 -> 0 | AS13: ='Plan - CoC'!AS6-'Plan - CoC'!AS12 -> 0 | AT13: ='Plan - CoC'!AT6-'Plan - CoC'!AT12 -> 0 | AU13: ='Plan - CoC'!AU6-'Plan - CoC'!AU12 -> 0 | ... BJ13: ='Plan - CoC'!BJ6-'Plan - CoC'!BJ12 -> 0

Sheet Calculation - NCL and ECL
A1: Back - Index | E1: =LOOKUP(E3,'Input-Stress Parameters'!$C$9:$BJ$9,'Input-Stress Parameters'!$C$11:$BJ$11) -> N | F1: =LOOKUP(F3,'Input-Stress Parameters'!$C$9:$BJ$9,'Input-Stress Parameters'!$C$11:$BJ$11) -> SL1 | G1: =LOOKUP(G3,'Input-Stress Parameters'!$C$9:$BJ$9,'Input-Stress Parameters'!$C$11:$BJ$11) -> SL1 | H1: =LOOKUP(H3,'Input-Stress Parameters'!$C$9:$BJ$9,'Input-Stress Parameters'!$C$11:$BJ$11) -> SL1 | I1: =LOOKUP(I3,'Input-Stress Parameters'!$C$9:$BJ$9,'Input-Stress Parameters'!$C$11:$BJ$11) -> SL1 | J1: =LOOKUP(J3,'Input-Stress Parameters'!$C$9:$BJ$9,'Input-Stress Parameters'!$C$11:$BJ$11) -> SL1 | K1: =LOOKUP(K3,'Input-Stress Parameters'!$C$9:$BJ$9,'Input-Stress Parameters'!$C$11:$BJ$11) -> SL1 | L1: =LOOKUP(L3,'Input-Stress Parameters'!$C$9:$BJ$9,'Input-Stress Parameters'!$C$11:$BJ$11) -> SL2 | ... AO1: =LOOKUP(AO3,'Input-Stress Parameters'!$C$9:$BJ$9,'Input-Stress Parameters'!$C$11:$BJ$11) -> N
E2: =LOOKUP(E3,'Input-Stress Parameters'!$C$27:$BJ$27,'Input-Stress Parameters'!$C$28:$BJ$28) -> N | F2: =LOOKUP(F3,'Input-Stress Parameters'!$C$27:$BJ$27,'Input-Stress Parameters'!$C$28:$BJ$28) -> SL1 | G2: =LOOKUP(G3,'Input-Stress Parameters'!$C$27:$BJ$27,'Input-Stress Parameters'!$C$28:$BJ$28) -> SL1 | H2: =LOOKUP(H3,'Input-Stress Parameters'!$C$27:$BJ$27,'Input-Stress Parameters'!$C$28:$BJ$28) -> SL1 | I2: =LOOKUP(I3,'Input-Stress Parameters'!$C$27:$BJ$27,'Input-Stress Parameters'!$C$28:$BJ$28) -> SL1 | J2: =LOOKUP(J3,'Input-Stress Parameters'!$C$27:$BJ$27,'Input-Stress Parameters'!$C$28:$BJ$28) -> SL1 | K2: =LOOKUP(K3,'Input-Stress Parameters'!$C$27:$BJ$27,'Input-Stress Parameters'!$C$28:$BJ$28) -> SL1 | L2: =LOOKUP(L3,'Input-Stress Parameters'!$C$27:$BJ$27,'Input-Stress Parameters'!$C$28:$BJ$28) -> SL2 | ... AO2: =LOOKUP(AO3,'Input-Stress Parameters'!$C$27:$BJ$27,'Input-Stress Parameters'!$C$28:$BJ$28) -> N
B3: Parameter | C3: Product | D3: Source | E3: ='Input-Stress Parameters'!C2 -> 45352 | F3: =EDATE(E3,1) -> 45383 | G3: =EDATE(F3,1) -> 45413 | H3: =EDATE(G3,1) -> 45444 | I3: =EDATE(H3,1) -> 45474 | J3: =EDATE(I3,1) -> 45505 | K3: =EDATE(J3,1) -> 45536 | L3: =EDATE(K3,1) -> 45566 | M3: =EDATE(L3,1) -> 45597 | ... AO3: =EDATE(AN3,1) -> 46447
B4: Plan ENR | C4: HL | D4: AIM | E4: ='Input - ENR'!C10 -> 52026.136 | F4: ='Input - ENR'!D10 -> 53122.126 | G4: ='Input - ENR'!E10 -> 54537.358 | H4: ='Input - ENR'!F10 -> 56131.078 | I4: ='Input - ENR'!G10 -> 57882.286 | J4: ='Input - ENR'!H10 -> 59903.922 | K4: ='Input - ENR'!I10 -> 62171.724 | L4: ='Input - ENR'!J10 -> 64281.554 | ... AO4: ='Input - ENR'!AM10 -> 140058.08
B5: Plan ENR | C5: LAP | D5: AIM | E5: ='Input - ENR'!C11 -> 19204.152 | F5: ='Input - ENR'!D11 -> 19852.383 | G5: ='Input - ENR'!E11 -> 20619.084 | H5: ='Input - ENR'!F11 -> 19514.623 | I5: ='Input - ENR'!G11 -> 20461.875 | J5: ='Input - ENR'!H11 -> 21525.575 | K5: ='Input - ENR'!I11 -> 20739.46 | L5: ='Input - ENR'!J11 -> 21885.919 | ... AO5: ='Input - ENR'!AM11 -> 38420.322
B6: Plan ENR | C6: DF | D6: AIM | E6: ='Input - ENR'!C12 -> 7547.0548 | F6: ='Input - ENR'!D12 -> 7512.3961 | G6: ='Input - ENR'!E12 -> 7529.9631 | H6: ='Input - ENR'!F12 -> 7596.402 | I6: ='Input - ENR'!G12 -> 7733.5743 | J6: ='Input - ENR'!H12 -> 7936.9376 | K6: ='Input - ENR'!I12 -> 8177.2413 | L6: ='Input - ENR'!J12 -> 8452.1131 | ... AO6: ='Input - ENR'!AM12 -> 14668.412
B7: Plan NCL | C7: HL | D7: AIM | E7: ='Input - NCL'!C11 -> 27.583752 | F7: ='Input - NCL'!D11 -> 36.625231 | G7: ='Input - NCL'!E11 -> 11.101824 | H7: ='Input - NCL'!F11 -> 16.751331 | I7: ='Input - NCL'!G11 -> 12.750592 | J7: ='Input - NCL'!H11 -> 17.970252 | K7: ='Input - NCL'!I11 -> 11.839389 | L7: ='Input - NCL'!J11 -> 24.668374 | ... AO7: ='Input - NCL'!AM11 -> 38.102161
B8: Plan NCL | C8: LAP | D8: AIM | E8: ='Input - NCL'!C12 -> 38.733859 | F8: ='Input - NCL'!D12 -> 14.982719 | G8: ='Input - NCL'!E12 -> 14.77418 | H8: ='Input - NCL'!F12 -> 14.145265 | I8: ='Input - NCL'!G12 -> 17.221602 | J8: ='Input - NCL'!H12 -> 14.914004 | K8: ='Input - NCL'!I12 -> 14.495933 | L8: ='Input - NCL'!J12 -> 18.532379 | ... AO8: ='Input - NCL'!AM12 -> 14.976077
B9: Plan NCL | C9: DF | D9: AIM | E9: ='Input - NCL'!C13 -> 0 | F9: ='Input - NCL'!D13 -> 0 | G9: ='Input - NCL'!E13 -> 0 | H9: ='Input - NCL'!F13 -> 0 | I9: ='Input - NCL'!G13 -> 0 | J9: ='Input - NCL'!H13 -> 0 | K9: ='Input - NCL'!I13 -> 0 | L9: ='Input - NCL'!J13 -> 0 | ... AO9: ='Input - NCL'!AM13 -> 0
B10: Stressed ENR (Pre-WriteOff) | C10: HL | D10: Finance | E10: ='Input - ENR'!C4 -> 52026.136 | F10: ='Input - ENR'!D4 -> 52427.211 | G10: ='Input - ENR'!E4 -> 53343.308 | H10: ='Input - ENR'!F4 -> 54301.817 | I10: ='Input - ENR'!G4 -> 55283.254 | J10: ='Input - ENR'!H4 -> 56336.702 | K10: ='Input - ENR'!I4 -> 57443.134 | L10: ='Input - ENR'!J4 -> 58210.554 | ... AO10: ='Input - ENR'!AM4 -> 102687.74
B11: Stressed ENR (Pre-WriteOff) | C11: LAP | D11: Finance | E11: ='Input - ENR'!C5 -> 19204.152 | F11: ='Input - ENR'!D5 -> 20089.604 | G11: ='Input - ENR'!E5 -> 20678.004 | H11: ='Input - ENR'!F5 -> 21279.43 | I11: ='Input - ENR'!G5 -> 21876.99 | J11: ='Input - ENR'!H5 -> 22499.638 | K11: ='Input - ENR'!I5 -> 21190.748 | L11: ='Input - ENR'!J5 -> 21699.963 | ... AO11: ='Input - ENR'!AM5 -> 30668.49
B12: Stressed ENR (Pre-WriteOff) | C12: DF | D12: Finance | E12: ='Input - ENR'!C6 -> 7547.0548 | F12: ='Input - ENR'!D6 -> 7499.2351 | G12: ='Input - ENR'!E6 -> 7242.6473 | H12: ='Input - ENR'!F6 -> 7008.5371 | I12: ='Input - ENR'!G6 -> 6802.2111 | J12: ='Input - ENR'!H6 -> 6617.3849 | K12: ='Input - ENR'!I6 -> 6445.553 | L12: ='Input - ENR'!J6 -> 6271.6308 | ... AO12: ='Input - ENR'!AM6 -> 9825.028
B13: Stressed NCL (base) | C13: HL | D13: Derived | E13: ='Input - NCL'!C5 -> 27.583752 | F13: ='Input - NCL'!D5 -> 36.14612 | G13: ='Input - NCL'!E5 -> 10.858758 | H13: ='Input - NCL'!F5 -> 16.20542 | I13: ='Input - NCL'!G5 -> 12.178065 | J13: ='Input - NCL'!H5 -> 16.900141 | K13: ='Input - NCL'!I5 -> 10.938922 | L13: ='Input - NCL'!J5 -> 22.338597 | ... AO13: ='Input - NCL'!AM5 -> 38.102161
B14: Stressed NCL (base) | C14: LAP | D14: Derived | E14: ='Input - NCL'!C6 -> 38.733859 | F14: ='Input - NCL'!D6 -> 15.161752 | G14: ='Input - NCL'!E6 -> 14.816398 | H14: ='Input - NCL'!F6 -> 15.424494 | I14: ='Input - NCL'!G6 -> 18.412625 | J14: ='Input - NCL'!H6 -> 15.588883 | K14: ='Input - NCL'!I6 -> 14.811363 | L14: ='Input - NCL'!J6 -> 18.374917 | ... AO14: ='Input - NCL'!AM6 -> 14.976077
B15: Stressed NCL (base) | C15: DF | D15: Derived | E15: ='Input - NCL'!C7 -> 0 | F15: ='Input - NCL'!D7 -> 0 | G15: ='Input - NCL'!E7 -> 0 | H15: ='Input - NCL'!F7 -> 0 | I15: ='Input - NCL'!G7 -> 0 | J15: ='Input - NCL'!H7 -> 0 | K15: ='Input - NCL'!I7 -> 0 | L15: ='Input - NCL'!J7 -> 0 | ... AO15: ='Input - NCL'!AM7 -> 0
B16: Stressed NCL | C16: HL | D16: Derived | E16: =IF(E$2="N",E13,LOOKUP(E$2,'Calculations - Parameters'!$AB$2:$AE$2,'Calculations - Parameters'!$AB3:$AE3)*E13/LOOKUP(E$2,'Calculations - Parameters'!$AB$2:$AE$2,'Calculations - Parameters'!$X3:$AA3)) -> 27.583752 | F16: =F25-F28 -> 36.827334 | G16: =G25-G28 -> 11.33684 | H16: =H25-H28 -> 17.006431 | I16: =I25-I28 -> 12.966601 | J16: =J25-J28 -> 18.141162 | K16: =K25-K28 -> 12.009106 | L16: =L25-L28 -> 25.121055 | M16: =M25-M28 -> 14.314999 | ... Q16: =Q25-Q28 -> 15.542658 | R16: =IF(R$2="N",R13,LOOKUP(R$2,'Calculations - Parameters'!$AB$2:$AE$2,'Calculations - Parameters'!$AB3:$AE3)*R13/LOOKUP(R$2,'Calculations - Parameters'!$AB$2:$AE$2,'Calculations - Parameters'!$X3:$AA3)) -> 24.011006 | S16: =IF(S$2="N",S13,LOOKUP(S$2,'Calculations - Parameters'!$AB$2:$AE$2,'Calculations - Parameters'!$AB3:$AE3)*S13/LOOKUP(S$2,'Calculations - Parameters'!$AB$2:$AE$2,'Calculations - Parameters'!$X3:$AA3)) -> 33.760804 | T16: =IF(T$2="N",T13,LOOKUP(T$2,'Calculations - Parameters'!$AB$2:$AE$2,'Calculations - Parameters'!$AB3:$AE3)*T13/LOOKUP(T$2,'Calculations - Parameters'!$AB$2:$AE$2,'Calculations - Parameters'!$X3:$AA3)) -> 38.087771 | U16: =IF(U$2="N",U13,LOOKUP(U$2,'Calculations - Parameters'!$AB$2:$AE$2,'Calculations - Parameters'!$AB3:$AE3)*U13/LOOKUP(U$2,'Calculations - Parameters'!$AB$2:$AE$2,'Calculations - Parameters'!$X3:$AA3)) -> 99.848143 | V16: =IF(V$2="N",V13,LOOKUP(V$2,'Calculations - Parameters'!$AB$2:$AE$2,'Calculations - Parameters'!$AB3:$AE3)*V13/LOOKUP(V$2,'Calculations - Parameters'!$AB$2:$AE$2,'Calculations - Parameters'!$X3:$AA3)) -> 26.864911 | W16: =IF(W$2="N",W13,LOOKUP(W$2,'Calculations - Parameters'!$AB$2:$AE$2,'Calculations - Parameters'!$AB3:$AE3)*W13/LOOKUP(W$2,'Calculations - Parameters'!$AB$2:$AE$2,'Calculations - Parameters'!$X3:$AA3)) -> 25.034447 | X16: =IF(X$2="N",X13,LOOKUP(X$2,'Calculations - Parameters'!$AB$2:$AE$2,'Calculations - Parameters'!$AB3:$AE3)*X13/LOOKUP(X$2,'Calculations - Parameters'!$AB$2:$AE$2,'Calculations - Parameters'!$X3:$AA3)) -> 17.900441 | Y16: =IF(Y$2="N",Y13,LOOKUP(Y$2,'Calculations - Parameters'!$AB$2:$AE$2,'Calculations - Parameters'!$AB3:$AE3)*Y13/LOOKUP(Y$2,'Calculations - Parameters'!$AB$2:$AE$2,'Calculations - Parameters'!$X3:$AA3)) -> 34.441443 | ... AO16: =IF(AO$2="N",AO13,LOOKUP(AO$2,'Calculations - Parameters'!$AB$2:$AE$2,'Calculations - Parameters'!$AB3:$AE3)*AO13/LOOKUP(AO$2,'Calculations - Parameters'!$AB$2:$AE$2,'Calculations - Parameters'!$X3:$AA3)) -> 38.102161
B17: Stressed NCL | C17: LAP | D17: Derived | E17: =IF(E$2="N",E14,LOOKUP(E$2,'Calculations - Parameters'!$AB$2:$AE$2,'Calculations - Parameters'!$AB4:$AE4)*E14/LOOKUP(E$2,'Calculations - Parameters'!$AB$2:$AE$2,'Calculations - Parameters'!$X4:$AA4)) -> 38.733859 | F17: =F26-F29 -> 14.882741 | G17: =G26-G29 -> 14.652778 | H17: =H26-H29 -> 14.0117 | I17: =I26-I29 -> 17.112639 | J17: =J26-J29 -> 14.82969 | K17: =K26-K29 -> 14.410619 | L17: =L26-L29 -> 18.512211 | M17: =M26-M29 -> 12.529665 | ... Q17: =Q26-Q29 -> 15.148162 | R17: =IF(R$2="N",R14,LOOKUP(R$2,'Calculations - Parameters'!$AB$2:$AE$2,'Calculations - Parameters'!$AB4:$AE4)*R14/LOOKUP(R$2,'Calculations - Parameters'!$AB$2:$AE$2,'Calculations - Parameters'!$X4:$AA4)) -> 21.618258 | S17: =IF(S$2="N",S14,LOOKUP(S$2,'Calculations - Parameters'!$AB$2:$AE$2,'Calculations - Parameters'!$AB4:$AE4)*S14/LOOKUP(S$2,'Calculations - Parameters'!$AB$2:$AE$2,'Calculations - Parameters'!$X4:$AA4)) -> 24.423822 | T17: =IF(T$2="N",T14,LOOKUP(T$2,'Calculations - Parameters'!$AB$2:$AE$2,'Calculations - Parameters'!$AB4:$AE4)*T14/LOOKUP(T$2,'Calculations - Parameters'!$AB$2:$AE$2,'Calculations - Parameters'!$X4:$AA4)) -> 45.113437 | U17: =IF(U$2="N",U14,LOOKUP(U$2,'Calculations - Parameters'!$AB$2:$AE$2,'Calculations - Parameters'!$AB4:$AE4)*U14/LOOKUP(U$2,'Calculations - Parameters'!$AB$2:$AE$2,'Calculations - Parameters'!$X4:$AA4)) -> 20.306427 | V17: =IF(V$2="N",V14,LOOKUP(V$2,'Calculations - Parameters'!$AB$2:$AE$2,'Calculations - Parameters'!$AB4:$AE4)*V14/LOOKUP(V$2,'Calculations - Parameters'!$AB$2:$AE$2,'Calculations - Parameters'!$X4:$AA4)) -> 27.397544 | W17: =IF(W$2="N",W14,LOOKUP(W$2,'Calculations - Parameters'!$AB$2:$AE$2,'Calculations - Parameters'!$AB4:$AE4)*W14/LOOKUP(W$2,'Calculations - Parameters'!$AB$2:$AE$2,'Calculations - Parameters'!$X4:$AA4)) -> 34.870169 | X17: =IF(X$2="N",X14,LOOKUP(X$2,'Calculations - Parameters'!$AB$2:$AE$2,'Calculations - Parameters'!$AB4:$AE4)*X14/LOOKUP(X$2,'Calculations - Parameters'!$AB$2:$AE$2,'Calculations - Parameters'!$X4:$AA4)) -> 6.9224966 | Y17: =IF(Y$2="N",Y14,LOOKUP(Y$2,'Calculations - Parameters'!$AB$2:$AE$2,'Calculations - Parameters'!$AB4:$AE4)*Y14/LOOKUP(Y$2,'Calculations - Parameters'!$AB$2:$AE$2,'Calculations - Parameters'!$X4:$AA4)) -> 8.3677873 | ... AO17: =IF(AO$2="N",AO14,LOOKUP(AO$2,'Calculations - Parameters'!$AB$2:$AE$2,'Calculations - Parameters'!$AB4:$AE4)*AO14/LOOKUP(AO$2,'Calculations - Parameters'!$AB$2:$AE$2,'Calculations - Parameters'!$X4:$AA4)) -> 14.976077
B18: Stressed NCL | C18: DF | D18: Derived | E18: =IF(E$2="N",E15,LOOKUP(E$2,'Calculations - Parameters'!$AB$2:$AE$2,'Calculations - Parameters'!$AB5:$AE5)*E15/LOOKUP(E$2,'Calculations - Parameters'!$AB$2:$AE$2,'Calculations - Parameters'!$X5:$AA5)) -> 0 | F18: =F27-F30 -> 0 | G18: =G27-G30 -> 0 | H18: =H27-H30 -> 0 | I18: =I27-I30 -> 0 | J18: =J27-J30 -> 0 | K18: =K27-K30 -> 0 | L18: =L27-L30 -> 0 | M18: =M27-M30 -> 0 | ... Q18: =Q27-Q30 -> 0 | R18: =IFERROR(IF(R$2="N",R15,LOOKUP(R$2,'Calculations - Parameters'!$AB$2:$AE$2,'Calculations - Parameters'!$AB5:$AE5)*R15/LOOKUP(R$2,'Calculations - Parameters'!$AB$2:$AE$2,'Calculations - Parameters'!$X5:$AA5)),0) -> 0 | S18: =IFERROR(IF(S$2="N",S15,LOOKUP(S$2,'Calculations - Parameters'!$AB$2:$AE$2,'Calculations - Parameters'!$AB5:$AE5)*S15/LOOKUP(S$2,'Calculations - Parameters'!$AB$2:$AE$2,'Calculations - Parameters'!$X5:$AA5)),0) -> 0 | T18: =IFERROR(IF(T$2="N",T15,LOOKUP(T$2,'Calculations - Parameters'!$AB$2:$AE$2,'Calculations - Parameters'!$AB5:$AE5)*T15/LOOKUP(T$2,'Calculations - Parameters'!$AB$2:$AE$2,'Calculations - Parameters'!$X5:$AA5)),0) -> 0 | U18: =IFERROR(IF(U$2="N",U15,LOOKUP(U$2,'Calculations - Parameters'!$AB$2:$AE$2,'Calculations - Parameters'!$AB5:$AE5)*U15/LOOKUP(U$2,'Calculations - Parameters'!$AB$2:$AE$2,'Calculations - Parameters'!$X5:$AA5)),0) -> 0 | V18: =IFERROR(IF(V$2="N",V15,LOOKUP(V$2,'Calculations - Parameters'!$AB$2:$AE$2,'Calculations - Parameters'!$AB5:$AE5)*V15/LOOKUP(V$2,'Calculations - Parameters'!$AB$2:$AE$2,'Calculations - Parameters'!$X5:$AA5)),0) -> 0 | W18: =IFERROR(IF(W$2="N",W15,LOOKUP(W$2,'Calculations - Parameters'!$AB$2:$AE$2,'Calculations - Parameters'!$AB5:$AE5)*W15/LOOKUP(W$2,'Calculations - Parameters'!$AB$2:$AE$2,'Calculations - Parameters'!$X5:$AA5)),0) -> 0 | X18: =IFERROR(IF(X$2="N",X15,LOOKUP(X$2,'Calculations - Parameters'!$AB$2:$AE$2,'Calculations - Parameters'!$AB5:$AE5)*X15/LOOKUP(X$2,'Calculations - Parameters'!$AB$2:$AE$2,'Calculations - Parameters'!$X5:$AA5)),0) -> 0 | Y18: =IFERROR(IF(Y$2="N",Y15,LOOKUP(Y$2,'Calculations - Parameters'!$AB$2:$AE$2,'Calculations - Parameters'!$AB5:$AE5)*Y15/LOOKUP(Y$2,'Calculations - Parameters'!$AB$2:$AE$2,'Calculations - Parameters'!$X5:$AA5)),0) -> 0 | ... AO18: =IFERROR(IF(AO$2="N",AO15,LOOKUP(AO$2,'Calculations - Parameters'!$AB$2:$AE$2,'Calculations - Parameters'!$AB5:$AE5)*AO15/LOOKUP(AO$2,'Calculations - Parameters'!$AB$2:$AE$2,'Calculations - Parameters'!$X5:$AA5)),0) -> 0
B19: Plan ECL (Model) | C19: HL | D19: AIM | E19: 12.24177 | F19: 10.071501 | G19: 20.325587 | H19: 20.831298 | I19: 17.22907 | J19: 21.171106 | K19: 26.317564 | L19: 14.001267 | M19: 20.850551 | N19: 22.548888 | O19: 21.72194 | P19: 22.340265 | Q19: -4.220846 | R19: 27.6599 | S19: 26.198685 | T19: 27.267261 | U19: -0.020159237 | V19: 24.863059 | W19: 27.598394 | X19: 25.101467 | Y19: 22.647285 | Z19: 26.996247 | AA19: 23.676591 | AB19: 25.642312 | AC19: 14.487854 | AD19: 11.16616 | AE19: 39.167972 | AF19: 34.537332 | AG19: 22.946116 | AH19: 25.428654 | AI19: 31.340515 | AJ19: 20.102376 | AK19: 24.919344 | AL19: 26.671044 | AM19: 22.392058 | AN19: 22.313371 | AO19: 20.895882
B20: Plan ECL (Model) | C20: LAP | D20: AIM | E20: -17.918123 | F20: 5.9273091 | G20: 7.5517746 | H20: -1.95253 | I20: 4.0541847 | J20: 4.8169301 | K20: -4.6546693 | L20: 1.6699516 | M20: 3.8826493 | N20: -21.659173 | O20: -8.3332324 | P20: -11.406831 | Q20: -7.1323389 | R20: 5.6314783 | S20: 5.7359038 | T20: -11.065733 | U20: 6.018945 | V20: 4.8157205 | W20: -8.6049474 | X20: 7.9882407 | Y20: 8.7172851 | Z20: -7.1229703 | AA20: 7.5138907 | AB20: -7.3649733 | AC20: 9.9920788 | AD20: 9.8961396 | AE20: 11.363908 | AF20: -5.0091543 | AG20: 9.3816398 | AH20: 11.97085 | AI20: -2.1171186 | AJ20: 9.2351919 | AK20: 10.102081 | AL20: -3.2200344 | AM20: 10.887666 | AN20: -4.4263126 | AO20: 11.71682
B21: Plan ECL (Model) | C21: DF | D21: AIM | E21: 2.2631753 | F21: -0.3495119 | G21: 0.17715269 | H21: 0.66999579 | I21: 1.3832991 | J21: 2.0507954 | K21: 2.4233164 | L21: 2.7719148 | M21: 2.5939073 | N21: 2.9315506 | O21: 3.2475111 | P21: 3.2910713 | Q21: 5.3487124 | R21: -1.2975168 | S21: -0.62593643 | T21: 0.0025162473 | U21: 0.88473885 | V21: 1.7103067 | W21: 2.1887299 | X21: 2.6364296 | Y21: 2.4671227 | Z21: 2.8969445 | AA21: 3.2991639 | AB21: 3.3814254 | AC21: 5.8114287 | AD21: -2.0410276 | AE21: -1.2376636 | AF21: -0.48589031 | AG21: 0.55375179 | AH21: 1.5266299 | AI21: 2.1008851 | AJ21: 2.6382626 | AK21: 2.468838 | AL21: 2.9825863 | AM21: 3.4633425 | AN21: 3.577079 | AO21: 6.3726825
B22: Stress ECL | C22: HL | D22: Derived | E22: =E19 -> 12.24177 | F22: ='Calculation - Stagewise ECL'!D24 -> 26.191163 | G22: ='Calculation - Stagewise ECL'!E24 -> 32.177183 | H22: ='Calculation - Stagewise ECL'!F24 -> 31.334479 | I22: ='Calculation - Stagewise ECL'!G24 -> 29.810836 | J22: ='Calculation - Stagewise ECL'!H24 -> 31.031067 | K22: ='Calculation - Stagewise ECL'!I24 -> 32.328561 | L22: ='Calculation - Stagewise ECL'!J24 -> 33.186034 | M22: ='Calculation - Stagewise ECL'!K24 -> 37.225314 | ... AO22: ='Calculation - Stagewise ECL'!AM24 -> 16.937631
B23: Stress ECL | C23: LAP | D23: Derived | E23: =E20 -> -17.918123 | F23: ='Calculation - Stagewise ECL'!D48 -> 31.278298 | G23: ='Calculation - Stagewise ECL'!E48 -> 23.893866 | H23: ='Calculation - Stagewise ECL'!F48 -> 29.560409 | I23: ='Calculation - Stagewise ECL'!G48 -> 28.872835 | J23: ='Calculation - Stagewise ECL'!H48 -> 26.075922 | K23: ='Calculation - Stagewise ECL'!I48 -> -23.981502 | L23: ='Calculation - Stagewise ECL'!J48 -> 27.233429 | M23: ='Calculation - Stagewise ECL'!K48 -> 30.42712 | ... AO23: ='Calculation - Stagewise ECL'!AM48 -> 21.035297
B24: Stress ECL | C24: DF | D24: Derived | E24: =E21 -> 2.2631753 | F24: ='Calculation - Stagewise ECL'!D72 -> -0.49147059 | G24: ='Calculation - Stagewise ECL'!E72 -> -2.7795071 | H24: ='Calculation - Stagewise ECL'!F72 -> -2.5677393 | I24: ='Calculation - Stagewise ECL'!G72 -> -2.3076602 | J24: ='Calculation - Stagewise ECL'!H72 -> -2.1055049 | K24: ='Calculation - Stagewise ECL'!I72 -> -1.9728373 | L24: ='Calculation - Stagewise ECL'!J72 -> -1.9975911 | M24: ='Calculation - Stagewise ECL'!K72 -> -2.1375899 | ... AO24: ='Calculation - Stagewise ECL'!AM72 -> 9.9277804
B25: Stress GWO | C25: HL | D25: Derived | E25: =E16+E28 -> 27.583752 | F25: ='Plan - CoC'!D4 -> 41.364333 | G25: ='Plan - CoC'!E4 -> 16.61273 | H25: ='Plan - CoC'!F4 -> 22.733168 | I25: ='Plan - CoC'!G4 -> 17.815778 | J25: ='Plan - CoC'!H4 -> 21.977915 | K25: ='Plan - CoC'!I4 -> 15.819071 | L25: ='Plan - CoC'!J4 -> 29.975829 | M25: ='Plan - CoC'!K4 -> 19.206647 | ... Q25: ='Plan - CoC'!O4 -> 22.305642 | R25: =R16+R28 -> 28.152341 | S25: =S16+S28 -> 37.872156 | T25: =T16+T28 -> 42.202712 | U25: =U16+U28 -> 104.01461 | V25: =V16+V28 -> 31.391918 | W25: =W16+W28 -> 29.935715 | X25: =X16+X28 -> 24.536892 | Y25: =Y16+Y28 -> 41.119185 | ... AO25: =AO16+AO28 -> 47.199753
B26: Stress GWO | C26: LAP | D26: Derived | E26: =E17+E29 -> 38.733859 | F26: ='Plan - CoC'!D5 -> 16.915696 | G26: ='Plan - CoC'!E5 -> 17.121354 | H26: ='Plan - CoC'!F5 -> 16.727618 | I26: ='Plan - CoC'!G5 -> 19.328289 | J26: ='Plan - CoC'!H5 -> 16.544124 | K26: ='Plan - CoC'!I5 -> 16.145401 | L26: ='Plan - CoC'!J5 -> 20.83884 | M26: ='Plan - CoC'!K5 -> 14.9013 | ... Q26: ='Plan - CoC'!O5 -> 19.351467 | R26: =R17+R29 -> 24.396025 | S26: =S17+S29 -> 27.259118 | T26: =T17+T29 -> 48.031189 | U26: =U17+U29 -> 23.397494 | V26: =V17+V29 -> 30.664309 | W26: =W17+W29 -> 38.323277 | X26: =X17+X29 -> 12.037348 | Y26: =Y17+Y29 -> 13.58712 | ... AO26: =AO17+AO29 -> 20.416041
B27: Stress GWO | C27: DF | D27: Derived | E27: =E18+E30 -> 0 | F27: ='Plan - CoC'!D6 -> 0 | G27: ='Plan - CoC'!E6 -> 0 | H27: ='Plan - CoC'!F6 -> 0 | I27: ='Plan - CoC'!G6 -> 0 | J27: ='Plan - CoC'!H6 -> 0 | K27: ='Plan - CoC'!I6 -> 0 | L27: ='Plan - CoC'!J6 -> 0 | M27: ='Plan - CoC'!K6 -> 0 | ... Q27: ='Plan - CoC'!O6 -> 0 | R27: =R18+R30 -> 0 | S27: =S18+S30 -> 0 | T27: =T18+T30 -> 0 | U27: =U18+U30 -> 0 | V27: =V18+V30 -> 0 | W27: =W18+W30 -> 0 | X27: =X18+X30 -> 0 | Y27: =Y18+Y30 -> 0 | ... AO27: =AO18+AO30 -> 0
B28: Stress Recovery | C28: HL | D28: Derived | E28: ='Plan - CoC'!C10 -> 0 | F28: =IF(F$2="SL1",((1-'Calculations - Parameters'!$Q3)/(1-'Calculations - Parameters'!$O$3))*'Plan - CoC'!D10,IF('Calculation - NCL and ECL'!F$2="SL2",((1-'Calculations - Parameters'!$R3)/(1-'Calculations - Parameters'!$O$3))*'Plan - CoC'!D10,IF('Calculation - NCL and ECL'!F$2="SL31",((1-'Calculations - Parameters'!$AY3)/(1-'Calculations - Parameters'!$O$3))*'Plan - CoC'!D10,IF('Calculation - NCL and ECL'!F$2="SL32",((1-'Calculations - Parameters'!$AZ3)/(1-'Calculations - Parameters'!$O$3))*'Plan - CoC'!D10)))) -> 4.5369999 | G28: =IF(G$2="SL1",((1-'Calculations - Parameters'!$Q3)/(1-'Calculations - Parameters'!$O$3))*'Plan - CoC'!E10,IF('Calculation - NCL and ECL'!G$2="SL2",((1-'Calculations - Parameters'!$R3)/(1-'Calculations - Parameters'!$O$3))*'Plan - CoC'!E10,IF('Calculation - NCL and ECL'!G$2="SL31",((1-'Calculations - Parameters'!$AY3)/(1-'Calculations - Parameters'!$O$3))*'Plan - CoC'!E10,IF('Calculation - NCL and ECL'!G$2="SL32",((1-'Calculations - Parameters'!$AZ3)/(1-'Calculations - Parameters'!$O$3))*'Plan - CoC'!E10)))) -> 5.2758892 | H28: =IF(H$2="SL1",((1-'Calculations - Parameters'!$Q3)/(1-'Calculations - Parameters'!$O$3))*'Plan - CoC'!F10,IF('Calculation - NCL and ECL'!H$2="SL2",((1-'Calculations - Parameters'!$R3)/(1-'Calculations - Parameters'!$O$3))*'Plan - CoC'!F10,IF('Calculation - NCL and ECL'!H$2="SL31",((1-'Calculations - Parameters'!$AY3)/(1-'Calculations - Parameters'!$O$3))*'Plan - CoC'!F10,IF('Calculation - NCL and ECL'!H$2="SL32",((1-'Calculations - Parameters'!$AZ3)/(1-'Calculations - Parameters'!$O$3))*'Plan - CoC'!F10)))) -> 5.7267373 | I28: =IF(I$2="SL1",((1-'Calculations - Parameters'!$Q3)/(1-'Calculations - Parameters'!$O$3))*'Plan - CoC'!G10,IF('Calculation - NCL and ECL'!I$2="SL2",((1-'Calculations - Parameters'!$R3)/(1-'Calculations - Parameters'!$O$3))*'Plan - CoC'!G10,IF('Calculation - NCL and ECL'!I$2="SL31",((1-'Calculations - Parameters'!$AY3)/(1-'Calculations - Parameters'!$O$3))*'Plan - CoC'!G10,IF('Calculation - NCL and ECL'!I$2="SL32",((1-'Calculations - Parameters'!$AZ3)/(1-'Calculations - Parameters'!$O$3))*'Plan - CoC'!G10)))) -> 4.8491776 | J28: =IF(J$2="SL1",((1-'Calculations - Parameters'!$Q3)/(1-'Calculations - Parameters'!$O$3))*'Plan - CoC'!H10,IF('Calculation - NCL and ECL'!J$2="SL2",((1-'Calculations - Parameters'!$R3)/(1-'Calculations - Parameters'!$O$3))*'Plan - CoC'!H10,IF('Calculation - NCL and ECL'!J$2="SL31",((1-'Calculations - Parameters'!$AY3)/(1-'Calculations - Parameters'!$O$3))*'Plan - CoC'!H10,IF('Calculation - NCL and ECL'!J$2="SL32",((1-'Calculations - Parameters'!$AZ3)/(1-'Calculations - Parameters'!$O$3))*'Plan - CoC'!H10)))) -> 3.836753 | K28: =IF(K$2="SL1",((1-'Calculations - Parameters'!$Q3)/(1-'Calculations - Parameters'!$O$3))*'Plan - CoC'!I10,IF('Calculation - NCL and ECL'!K$2="SL2",((1-'Calculations - Parameters'!$R3)/(1-'Calculations - Parameters'!$O$3))*'Plan - CoC'!I10,IF('Calculation - NCL and ECL'!K$2="SL31",((1-'Calculations - Parameters'!$AY3)/(1-'Calculations - Parameters'!$O$3))*'Plan - CoC'!I10,IF('Calculation - NCL and ECL'!K$2="SL32",((1-'Calculations - Parameters'!$AZ3)/(1-'Calculations - Parameters'!$O$3))*'Plan - CoC'!I10)))) -> 3.8099655 | L28: =IF(L$2="SL1",((1-'Calculations - Parameters'!$Q3)/(1-'Calculations - Parameters'!$O$3))*'Plan - CoC'!J10,IF('Calculation - NCL and ECL'!L$2="SL2",((1-'Calculations - Parameters'!$R3)/(1-'Calculations - Parameters'!$O$3))*'Plan - CoC'!J10,IF('Calculation - NCL and ECL'!L$2="SL31",((1-'Calculations - Parameters'!$AY3)/(1-'Calculations - Parameters'!$O$3))*'Plan - CoC'!J10,IF('Calculation - NCL and ECL'!L$2="SL32",((1-'Calculations - Parameters'!$AZ3)/(1-'Calculations - Parameters'!$O$3))*'Plan - CoC'!J10)))) -> 4.854774 | M28: =IF(M$2="SL1",((1-'Calculations - Parameters'!$Q3)/(1-'Calculations - Parameters'!$O$3))*'Plan - CoC'!K10,IF('Calculation - NCL and ECL'!M$2="SL2",((1-'Calculations - Parameters'!$R3)/(1-'Calculations - Parameters'!$O$3))*'Plan - CoC'!K10,IF('Calculation - NCL and ECL'!M$2="SL31",((1-'Calculations - Parameters'!$AY3)/(1-'Calculations - Parameters'!$O$3))*'Plan - CoC'!K10,IF('Calculation - NCL and ECL'!M$2="SL32",((1-'Calculations - Parameters'!$AZ3)/(1-'Calculations - Parameters'!$O$3))*'Plan - CoC'!K10)))) -> 4.891648 | ... AI28: =IF(AI$2="SL1",((1-'Calculations - Parameters'!$Q3)/(1-'Calculations - Parameters'!$O$3))*'Plan - CoC'!AG10,IF('Calculation - NCL and ECL'!AI$2="SL2",((1-'Calculations - Parameters'!$R3)/(1-'Calculations - Parameters'!$O$3))*'Plan - CoC'!AG10,IF('Calculation - NCL and ECL'!AI$2="SL31",((1-'Calculations - Parameters'!$AY3)/(1-'Calculations - Parameters'!$O$3))*'Plan - CoC'!AG10,IF('Calculation - NCL and ECL'!AI$2="SL32",((1-'Calculations - Parameters'!$AZ3)/(1-'Calculations - Parameters'!$O$3))*'Plan - CoC'!AG10)))) -> 5.6754884 | AJ28: ='Plan - CoC'!AH10 -> 7.8529738 | AK28: ='Plan - CoC'!AI10 -> 7.9441853 | AL28: ='Plan - CoC'!AJ10 -> 7.953836 | AM28: ='Plan - CoC'!AK10 -> 8.180187 | AN28: ='Plan - CoC'!AL10 -> 9.1307196 | AO28: ='Plan - CoC'!AM10 -> 9.0975916
B29: Stress Recovery | C29: LAP | D29: Derived | E29: ='Plan - CoC'!C11 -> 0 | F29: =IF(F$2="SL1",((1-'Calculations - Parameters'!$Q4)/(1-'Calculations - Parameters'!$O$3))*'Plan - CoC'!D11,IF('Calculation - NCL and ECL'!F$2="SL2",((1-'Calculations - Parameters'!$R4)/(1-'Calculations - Parameters'!$O$3))*'Plan - CoC'!D11,IF('Calculation - NCL and ECL'!F$2="SL31",((1-'Calculations - Parameters'!$AY4)/(1-'Calculations - Parameters'!$O$3))*'Plan - CoC'!D11,IF('Calculation - NCL and ECL'!F$2="SL32",((1-'Calculations - Parameters'!$AZ4)/(1-'Calculations - Parameters'!$O$3))*'Plan - CoC'!D11)))) -> 2.0329549 | G29: =IF(G$2="SL1",((1-'Calculations - Parameters'!$Q4)/(1-'Calculations - Parameters'!$O$3))*'Plan - CoC'!E11,IF('Calculation - NCL and ECL'!G$2="SL2",((1-'Calculations - Parameters'!$R4)/(1-'Calculations - Parameters'!$O$3))*'Plan - CoC'!E11,IF('Calculation - NCL and ECL'!G$2="SL31",((1-'Calculations - Parameters'!$AY4)/(1-'Calculations - Parameters'!$O$3))*'Plan - CoC'!E11,IF('Calculation - NCL and ECL'!G$2="SL32",((1-'Calculations - Parameters'!$AZ4)/(1-'Calculations - Parameters'!$O$3))*'Plan - CoC'!E11)))) -> 2.4685755 | H29: =IF(H$2="SL1",((1-'Calculations - Parameters'!$Q4)/(1-'Calculations - Parameters'!$O$3))*'Plan - CoC'!F11,IF('Calculation - NCL and ECL'!H$2="SL2",((1-'Calculations - Parameters'!$R4)/(1-'Calculations - Parameters'!$O$3))*'Plan - CoC'!F11,IF('Calculation - NCL and ECL'!H$2="SL31",((1-'Calculations - Parameters'!$AY4)/(1-'Calculations - Parameters'!$O$3))*'Plan - CoC'!F11,IF('Calculation - NCL and ECL'!H$2="SL32",((1-'Calculations - Parameters'!$AZ4)/(1-'Calculations - Parameters'!$O$3))*'Plan - CoC'!F11)))) -> 2.7159184 | I29: =IF(I$2="SL1",((1-'Calculations - Parameters'!$Q4)/(1-'Calculations - Parameters'!$O$3))*'Plan - CoC'!G11,IF('Calculation - NCL and ECL'!I$2="SL2",((1-'Calculations - Parameters'!$R4)/(1-'Calculations - Parameters'!$O$3))*'Plan - CoC'!G11,IF('Calculation - NCL and ECL'!I$2="SL31",((1-'Calculations - Parameters'!$AY4)/(1-'Calculations - Parameters'!$O$3))*'Plan - CoC'!G11,IF('Calculation - NCL and ECL'!I$2="SL32",((1-'Calculations - Parameters'!$AZ4)/(1-'Calculations - Parameters'!$O$3))*'Plan - CoC'!G11)))) -> 2.2156497 | J29: =IF(J$2="SL1",((1-'Calculations - Parameters'!$Q4)/(1-'Calculations - Parameters'!$O$3))*'Plan - CoC'!H11,IF('Calculation - NCL and ECL'!J$2="SL2",((1-'Calculations - Parameters'!$R4)/(1-'Calculations - Parameters'!$O$3))*'Plan - CoC'!H11,IF('Calculation - NCL and ECL'!J$2="SL31",((1-'Calculations - Parameters'!$AY4)/(1-'Calculations - Parameters'!$O$3))*'Plan - CoC'!H11,IF('Calculation - NCL and ECL'!J$2="SL32",((1-'Calculations - Parameters'!$AZ4)/(1-'Calculations - Parameters'!$O$3))*'Plan - CoC'!H11)))) -> 1.7144336 | K29: =IF(K$2="SL1",((1-'Calculations - Parameters'!$Q4)/(1-'Calculations - Parameters'!$O$3))*'Plan - CoC'!I11,IF('Calculation - NCL and ECL'!K$2="SL2",((1-'Calculations - Parameters'!$R4)/(1-'Calculations - Parameters'!$O$3))*'Plan - CoC'!I11,IF('Calculation - NCL and ECL'!K$2="SL31",((1-'Calculations - Parameters'!$AY4)/(1-'Calculations - Parameters'!$O$3))*'Plan - CoC'!I11,IF('Calculation - NCL and ECL'!K$2="SL32",((1-'Calculations - Parameters'!$AZ4)/(1-'Calculations - Parameters'!$O$3))*'Plan - CoC'!I11)))) -> 1.7347828 | L29: =IF(L$2="SL1",((1-'Calculations - Parameters'!$Q4)/(1-'Calculations - Parameters'!$O$3))*'Plan - CoC'!J11,IF('Calculation - NCL and ECL'!L$2="SL2",((1-'Calculations - Parameters'!$R4)/(1-'Calculations - Parameters'!$O$3))*'Plan - CoC'!J11,IF('Calculation - NCL and ECL'!L$2="SL31",((1-'Calculations - Parameters'!$AY4)/(1-'Calculations - Parameters'!$O$3))*'Plan - CoC'!J11,IF('Calculation - NCL and ECL'!L$2="SL32",((1-'Calculations - Parameters'!$AZ4)/(1-'Calculations - Parameters'!$O$3))*'Plan - CoC'!J11)))) -> 2.3266292 | M29: =IF(M$2="SL1",((1-'Calculations - Parameters'!$Q4)/(1-'Calculations - Parameters'!$O$3))*'Plan - CoC'!K11,IF('Calculation - NCL and ECL'!M$2="SL2",((1-'Calculations - Parameters'!$R4)/(1-'Calculations - Parameters'!$O$3))*'Plan - CoC'!K11,IF('Calculation - NCL and ECL'!M$2="SL31",((1-'Calculations - Parameters'!$AY4)/(1-'Calculations - Parameters'!$O$3))*'Plan - CoC'!K11,IF('Calculation - NCL and ECL'!M$2="SL32",((1-'Calculations - Parameters'!$AZ4)/(1-'Calculations - Parameters'!$O$3))*'Plan - CoC'!K11)))) -> 2.3716352 | ... AI29: =IF(AI$2="SL1",((1-'Calculations - Parameters'!$Q4)/(1-'Calculations - Parameters'!$O$3))*'Plan - CoC'!AG11,IF('Calculation - NCL and ECL'!AI$2="SL2",((1-'Calculations - Parameters'!$R4)/(1-'Calculations - Parameters'!$O$3))*'Plan - CoC'!AG11,IF('Calculation - NCL and ECL'!AI$2="SL31",((1-'Calculations - Parameters'!$AY4)/(1-'Calculations - Parameters'!$O$3))*'Plan - CoC'!AG11,IF('Calculation - NCL and ECL'!AI$2="SL32",((1-'Calculations - Parameters'!$AZ4)/(1-'Calculations - Parameters'!$O$3))*'Plan - CoC'!AG11)))) -> 3.7217686 | AJ29: ='Plan - CoC'!AH11 -> 5.2144777 | AK29: ='Plan - CoC'!AI11 -> 5.2195841 | AL29: ='Plan - CoC'!AJ11 -> 5.2231378 | AM29: ='Plan - CoC'!AK11 -> 5.469506 | AN29: ='Plan - CoC'!AL11 -> 5.4567672 | AO29: ='Plan - CoC'!AM11 -> 5.4399638
B30: Stress Recovery | C30: DF | D30: Derived | E30: ='Plan - CoC'!C12 -> 0 | F30: ='Plan - CoC'!D12 -> 0 | G30: ='Plan - CoC'!E12 -> 0 | H30: ='Plan - CoC'!F12 -> 0 | I30: ='Plan - CoC'!G12 -> 0 | J30: ='Plan - CoC'!H12 -> 0 | K30: =IF(K$2="SL1",((1-'Calculations - Parameters'!$Q5)/(1-'Calculations - Parameters'!$O$3))*'Plan - CoC'!I12,IF('Calculation - NCL and ECL'!K$2="SL2",((1-'Calculations - Parameters'!$R5)/(1-'Calculations - Parameters'!$O$3))*'Plan - CoC'!I12,IF('Calculation - NCL and ECL'!K$2="SL31",((1-'Calculations - Parameters'!$AY5)/(1-'Calculations - Parameters'!$O$3))*'Plan - CoC'!I12,IF('Calculation - NCL and ECL'!K$2="SL32",((1-'Calculations - Parameters'!$AZ5)/(1-'Calculations - Parameters'!$O$3))*'Plan - CoC'!I12)))) -> 0 | L30: =IF(L$2="SL1",((1-'Calculations - Parameters'!$Q5)/(1-'Calculations - Parameters'!$O$3))*'Plan - CoC'!J12,IF('Calculation - NCL and ECL'!L$2="SL2",((1-'Calculations - Parameters'!$R5)/(1-'Calculations - Parameters'!$O$3))*'Plan - CoC'!J12,IF('Calculation - NCL and ECL'!L$2="SL31",((1-'Calculations - Parameters'!$AY5)/(1-'Calculations - Parameters'!$O$3))*'Plan - CoC'!J12,IF('Calculation - NCL and ECL'!L$2="SL32",((1-'Calculations - Parameters'!$AZ5)/(1-'Calculations - Parameters'!$O$3))*'Plan - CoC'!J12)))) -> 0 | M30: =IF(M$2="SL1",((1-'Calculations - Parameters'!$Q5)/(1-'Calculations - Parameters'!$O$3))*'Plan - CoC'!K12,IF('Calculation - NCL and ECL'!M$2="SL2",((1-'Calculations - Parameters'!$R5)/(1-'Calculations - Parameters'!$O$3))*'Plan - CoC'!K12,IF('Calculation - NCL and ECL'!M$2="SL31",((1-'Calculations - Parameters'!$AY5)/(1-'Calculations - Parameters'!$O$3))*'Plan - CoC'!K12,IF('Calculation - NCL and ECL'!M$2="SL32",((1-'Calculations - Parameters'!$AZ5)/(1-'Calculations - Parameters'!$O$3))*'Plan - CoC'!K12)))) -> 0 | N30: =IF(N$2="SL1",((1-'Calculations - Parameters'!$Q5)/(1-'Calculations - Parameters'!$O$3))*'Plan - CoC'!L12,IF('Calculation - NCL and ECL'!N$2="SL2",((1-'Calculations - Parameters'!$R5)/(1-'Calculations - Parameters'!$O$3))*'Plan - CoC'!L12,IF('Calculation - NCL and ECL'!N$2="SL31",((1-'Calculations - Parameters'!$AY5)/(1-'Calculations - Parameters'!$O$3))*'Plan - CoC'!L12,IF('Calculation - NCL and ECL'!N$2="SL32",((1-'Calculations - Parameters'!$AZ5)/(1-'Calculations - Parameters'!$O$3))*'Plan - CoC'!L12)))) -> 0 | O30: =IF(O$2="SL1",((1-'Calculations - Parameters'!$Q5)/(1-'Calculations - Parameters'!$O$3))*'Plan - CoC'!M12,IF('Calculation - NCL and ECL'!O$2="SL2",((1-'Calculations - Parameters'!$R5)/(1-'Calculations - Parameters'!$O$3))*'Plan - CoC'!M12,IF('Calculation - NCL and ECL'!O$2="SL31",((1-'Calculations - Parameters'!$AY5)/(1-'Calculations - Parameters'!$O$3))*'Plan - CoC'!M12,IF('Calculation - NCL and ECL'!O$2="SL32",((1-'Calculations - Parameters'!$AZ5)/(1-'Calculations - Parameters'!$O$3))*'Plan - CoC'!M12)))) -> 0 | P30: =IF(P$2="SL1",((1-'Calculations - Parameters'!$Q5)/(1-'Calculations - Parameters'!$O$3))*'Plan - CoC'!N12,IF('Calculation - NCL and ECL'!P$2="SL2",((1-'Calculations - Parameters'!$R5)/(1-'Calculations - Parameters'!$O$3))*'Plan - CoC'!N12,IF('Calculation - NCL and ECL'!P$2="SL31",((1-'Calculations - Parameters'!$AY5)/(1-'Calculations - Parameters'!$O$3))*'Plan - CoC'!N12,IF('Calculation - NCL and ECL'!P$2="SL32",((1-'Calculations - Parameters'!$AZ5)/(1-'Calculations - Parameters'!$O$3))*'Plan - CoC'!N12)))) -> 0 | Q30: =IF(Q$2="SL1",((1-'Calculations - Parameters'!$Q5)/(1-'Calculations - Parameters'!$O$3))*'Plan - CoC'!O12,IF('Calculation - NCL and ECL'!Q$2="SL2",((1-'Calculations - Parameters'!$R5)/(1-'Calculations - Parameters'!$O$3))*'Plan - CoC'!O12,IF('Calculation - NCL and ECL'!Q$2="SL31",((1-'Calculations - Parameters'!$AY5)/(1-'Calculations - Parameters'!$O$3))*'Plan - CoC'!O12,IF('Calculation - NCL and ECL'!Q$2="SL32",((1-'Calculations - Parameters'!$AZ5)/(1-'Calculations - Parameters'!$O$3))*'Plan - CoC'!O12)))) -> 0 | R30: =IF(R$2="SL1",((1-'Calculations - Parameters'!$Q5)/(1-'Calculations - Parameters'!$O$3))*'Plan - CoC'!P12,IF('Calculation - NCL and ECL'!R$2="SL2",((1-'Calculations - Parameters'!$R5)/(1-'Calculations - Parameters'!$O$3))*'Plan - CoC'!P12,IF('Calculation - NCL and ECL'!R$2="SL31",((1-'Calculations - Parameters'!$AY5)/(1-'Calculations - Parameters'!$O$3))*'Plan - CoC'!P12,IF('Calculation - NCL and ECL'!R$2="SL32",((1-'Calculations - Parameters'!$AZ5)/(1-'Calculations - Parameters'!$O$3))*'Plan - CoC'!P12)))) -> 0 | ... AI30: =IF(AI$2="SL1",((1-'Calculations - Parameters'!$Q5)/(1-'Calculations - Parameters'!$O$3))*'Plan - CoC'!AG12,IF('Calculation - NCL and ECL'!AI$2="SL2",((1-'Calculations - Parameters'!$R5)/(1-'Calculations - Parameters'!$O$3))*'Plan - CoC'!AG12,IF('Calculation - NCL and ECL'!AI$2="SL31",((1-'Calculations - Parameters'!$AY5)/(1-'Calculations - Parameters'!$O$3))*'Plan - CoC'!AG12,IF('Calculation - NCL and ECL'!AI$2="SL32",((1-'Calculations - Parameters'!$AZ5)/(1-'Calculations - Parameters'!$O$3))*'Plan - CoC'!AG12)))) -> 0 | AJ30: ='Plan - CoC'!AH12 -> 0 | AK30: ='Plan - CoC'!AI12 -> 0 | AL30: ='Plan - CoC'!AJ12 -> 0 | AM30: ='Plan - CoC'!AK12 -> 0 | AN30: ='Plan - CoC'!AL12 -> 0 | AO30: ='Plan - CoC'!AM12 -> 0
B31: Stress NNPA | C31: HL | D31: Derived | E31: ='Input - GNPA'!C22+'Input - GNPA'!C16*0.053 -> 746.90544 | F31: ='Input - GNPA'!D22+'Input - GNPA'!D16*0.053 -> 771.09125 | G31: ='Input - GNPA'!E22+'Input - GNPA'!E16*0.053 -> 793.45982 | H31: ='Input - GNPA'!F22+'Input - GNPA'!F16*0.053 -> 816.53113 | I31: ='Input - GNPA'!G22+'Input - GNPA'!G16*0.053 -> 845.90974 | J31: ='Input - GNPA'!H22+'Input - GNPA'!H16*0.053 -> 873.42139 | K31: ='Input - GNPA'!I22+'Input - GNPA'!I16*0.053 -> 903.12383 | L31: ='Input - GNPA'!J22+'Input - GNPA'!J16*0.053 -> 872.7234 | ... AO31: ='Input - GNPA'!AM22+'Input - GNPA'!AM16*0.053 -> 1330.8914
